Workbook

Sheet Dashboard
A2: SWE Plan dashboard
A4: Plan start | B4: 46294 | E4: Plan length | F4: 24 weeks | J4: Update tasks in Master Plan. All views recalculate in Excel.
A6: TOTAL TASKS | E6: CORE COMPLETE | J6: BLOCKED | N6: ACTUAL HOURS
A7: =COUNTA(PlanTasks[Task ID]) -> 236 | E7: =IF(COUNTIFS(PlanTasks[Scope],"Core")=0,"",COUNTIFS(PlanTasks[Scope],"Core",PlanTasks[Completion check],"Complete")/COUNTIFS(PlanTasks[Scope],"Core")) -> 0.0088495575 | J7: =COUNTIFS(PlanTasks[Status],"Blocked") -> 0 | N7: =SUM(PlanTasks[Actual (h)]) -> 0.5
A11: Category | B11: Tasks | C11: Complete | D11: Progress | E11: Active | F11: Blocked | G11: Est. (h) | H11: Actual (h)
A12: Engineering | B12: =COUNTIFS(PlanTasks[Category],$A12) -> 15 | C12: =COUNTIFS(PlanTasks[Category],$A12,PlanTasks[Completion check],"Complete") -> 1 | D12: =IF(B12=0,"",C12/B12) -> 0.066666667 | E12: =COUNTIFS(PlanTasks[Category],$A12,PlanTasks[Status],"In progress") -> 0 | F12: =COUNTIFS(PlanTasks[Category],$A12,PlanTasks[Status],"Blocked") -> 0 | G12: =SUMIFS(PlanTasks[Estimate (h)],PlanTasks[Category],$A12) -> 15.75 | H12: =SUMIFS(PlanTasks[Actual (h)],PlanTasks[Category],$A12) -> 0.25
A13: Java & Spring | B13: =COUNTIFS(PlanTasks[Category],$A13) -> 31 | C13: =COUNTIFS(PlanTasks[Category],$A13,PlanTasks[Completion check],"Complete") -> 0 | D13: =IF(B13=0,"",C13/B13) -> 0 | E13: =COUNTIFS(PlanTasks[Category],$A13,PlanTasks[Status],"In progress") -> 0 | F13: =COUNTIFS(PlanTasks[Category],$A13,PlanTasks[Status],"Blocked") -> 0 | G13: =SUMIFS(PlanTasks[Estimate (h)],PlanTasks[Category],$A13) -> 23.25 | H13: =SUMIFS(PlanTasks[Actual (h)],PlanTasks[Category],$A13) -> 0
A14: TypeScript & UI | B14: =COUNTIFS(PlanTasks[Category],$A14) -> 29 | C14: =COUNTIFS(PlanTasks[Category],$A14,PlanTasks[Completion check],"Complete") -> 0 | D14: =IF(B14=0,"",C14/B14) -> 0 | E14: =COUNTIFS(PlanTasks[Category],$A14,PlanTasks[Status],"In progress") -> 0 | F14: =COUNTIFS(PlanTasks[Category],$A14,PlanTasks[Status],"Blocked") -> 0 | G14: =SUMIFS(PlanTasks[Estimate (h)],PlanTasks[Category],$A14) -> 21.75 | H14: =SUMIFS(PlanTasks[Actual (h)],PlanTasks[Category],$A14) -> 0
A15: CS & SQL | B15: =COUNTIFS(PlanTasks[Category],$A15) -> 15 | C15: =COUNTIFS(PlanTasks[Category],$A15,PlanTasks[Completion check],"Complete") -> 0 | D15: =IF(B15=0,"",C15/B15) -> 0 | E15: =COUNTIFS(PlanTasks[Category],$A15,PlanTasks[Status],"In progress") -> 0 | F15: =COUNTIFS(PlanTasks[Category],$A15,PlanTasks[Status],"Blocked") -> 0 | G15: =SUMIFS(PlanTasks[Estimate (h)],PlanTasks[Category],$A15) -> 11.5 | H15: =SUMIFS(PlanTasks[Actual (h)],PlanTasks[Category],$A15) -> 0
A16: DSA | B16: =COUNTIFS(PlanTasks[Category],$A16) -> 24 | C16: =COUNTIFS(PlanTasks[Category],$A16,PlanTasks[Completion check],"Complete") -> 0 | D16: =IF(B16=0,"",C16/B16) -> 0 | E16: =COUNTIFS(PlanTasks[Category],$A16,PlanTasks[Status],"In progress") -> 0 | F16: =COUNTIFS(PlanTasks[Category],$A16,PlanTasks[Status],"Blocked") -> 0 | G16: =SUMIFS(PlanTasks[Estimate (h)],PlanTasks[Category],$A16) -> 72 | H16: =SUMIFS(PlanTasks[Actual (h)],PlanTasks[Category],$A16) -> 0
A17: System design | B17: =COUNTIFS(PlanTasks[Category],$A17) -> 10 | C17: =COUNTIFS(PlanTasks[Category],$A17,PlanTasks[Completion check],"Complete") -> 0 | D17: =IF(B17=0,"",C17/B17) -> 0 | E17: =COUNTIFS(PlanTasks[Category],$A17,PlanTasks[Status],"In progress") -> 0 | F17: =COUNTIFS(PlanTasks[Category],$A17,PlanTasks[Status],"Blocked") -> 0 | G17: =SUMIFS(PlanTasks[Estimate (h)],PlanTasks[Category],$A17) -> 10 | H17: =SUMIFS(PlanTasks[Actual (h)],PlanTasks[Category],$A17) -> 0
A18: Projects | B18: =COUNTIFS(PlanTasks[Category],$A18) -> 30 | C18: =COUNTIFS(PlanTasks[Category],$A18,PlanTasks[Completion check],"Complete") -> 0 | D18: =IF(B18=0,"",C18/B18) -> 0 | E18: =COUNTIFS(PlanTasks[Category],$A18,PlanTasks[Status],"In progress") -> 0 | F18: =COUNTIFS(PlanTasks[Category],$A18,PlanTasks[Status],"Blocked") -> 0 | G18: =SUMIFS(PlanTasks[Estimate (h)],PlanTasks[Category],$A18) -> 52.5 | H18: =SUMIFS(PlanTasks[Actual (h)],PlanTasks[Category],$A18) -> 0
A19: AI Engineering | B19: =COUNTIFS(PlanTasks[Category],$A19) -> 7 | C19: =COUNTIFS(PlanTasks[Category],$A19,PlanTasks[Completion check],"Complete") -> 0 | D19: =IF(B19=0,"",C19/B19) -> 0 | E19: =COUNTIFS(PlanTasks[Category],$A19,PlanTasks[Status],"In progress") -> 1 | F19: =COUNTIFS(PlanTasks[Category],$A19,PlanTasks[Status],"Blocked") -> 0 | G19: =SUMIFS(PlanTasks[Estimate (h)],PlanTasks[Category],$A19) -> 5.25 | H19: =SUMIFS(PlanTasks[Actual (h)],PlanTasks[Category],$A19) -> 0
A20: Mock interviews | B20: =COUNTIFS(PlanTasks[Category],$A20) -> 44 | C20: =COUNTIFS(PlanTasks[Category],$A20,PlanTasks[Completion check],"Complete") -> 0 | D20: =IF(B20=0,"",C20/B20) -> 0 | E20: =COUNTIFS(PlanTasks[Category],$A20,PlanTasks[Status],"In progress") -> 0 | F20: =COUNTIFS(PlanTasks[Category],$A20,PlanTasks[Status],"Blocked") -> 0 | G20: =SUMIFS(PlanTasks[Estimate (h)],PlanTasks[Category],$A20) -> 44 | H20: =SUMIFS(PlanTasks[Actual (h)],PlanTasks[Category],$A20) -> 0
A21: Review | B21: =COUNTIFS(PlanTasks[Category],$A21) -> 25 | C21: =COUNTIFS(PlanTasks[Category],$A21,PlanTasks[Completion check],"Complete") -> 1 | D21: =IF(B21=0,"",C21/B21) -> 0.04 | E21: =COUNTIFS(PlanTasks[Category],$A21,PlanTasks[Status],"In progress") -> 0 | F21: =COUNTIFS(PlanTasks[Category],$A21,PlanTasks[Status],"Blocked") -> 0 | G21: =SUMIFS(PlanTasks[Estimate (h)],PlanTasks[Category],$A21) -> 13 | H21: =SUMIFS(PlanTasks[Actual (h)],PlanTasks[Category],$A21) -> 0.25
A22: Career | B22: =COUNTIFS(PlanTasks[Category],$A22) -> 6 | C22: =COUNTIFS(PlanTasks[Category],$A22,PlanTasks[Completion check],"Complete") -> 0 | D22: =IF(B22=0,"",C22/B22) -> 0 | E22: =COUNTIFS(PlanTasks[Category],$A22,PlanTasks[Status],"In progress") -> 0 | F22: =COUNTIFS(PlanTasks[Category],$A22,PlanTasks[Status],"Blocked") -> 0 | G22: =SUMIFS(PlanTasks[Estimate (h)],PlanTasks[Category],$A22) -> 5 | H22: =SUMIFS(PlanTasks[Actual (h)],PlanTasks[Category],$A22) -> 0
A24: Category coverage | B24: =A7-SUM(B12:B22) -> 0 | C24: Tasks outside the listed categories
J25: Complete = evidence + completion date; mocks also require scores and a result.
A26: Category totals include optional work. Effort estimates are proposed; record actual hours as you work.
A29: Week | B29: Core (h) | C29: Capacity (h) | D29: Actual (h) | E29: Complete | F29: Core tasks | G29: Progress | H29: Spare (h)
A30: ='Weekly Review'!A10 -> 1 | B30: ='Weekly Review'!E10 -> 16.25 | C30: ='Weekly Review'!D10 -> 13 | D30: ='Weekly Review'!G10 -> 0.5 | E30: ='Weekly Review'!I10 -> 2 | F30: ='Weekly Review'!H10 -> 15 | G30: ='Weekly Review'!J10 -> 0.13333333 | H30: ='Weekly Review'!K10 -> -3.25
A31: ='Weekly Review'!A11 -> 2 | B31: ='Weekly Review'!E11 -> 11 | C31: ='Weekly Review'!D11 -> 13 | D31: ='Weekly Review'!G11 -> 0 | E31: ='Weekly Review'!I11 -> 0 | F31: ='Weekly Review'!H11 -> 10 | G31: ='Weekly Review'!J11 -> 0 | H31: ='Weekly Review'!K11 -> 2
A32: ='Weekly Review'!A12 -> 3 | B32: ='Weekly Review'!E12 -> 11.75 | C32: ='Weekly Review'!D12 -> 13 | D32: ='Weekly Review'!G12 -> 0 | E32: ='Weekly Review'!I12 -> 0 | F32: ='Weekly Review'!H12 -> 11 | G32: ='Weekly Review'!J12 -> 0 | H32: ='Weekly Review'!K12 -> 1.25
A33: ='Weekly Review'!A13 -> 4 | B33: ='Weekly Review'!E13 -> 13.5 | C33: ='Weekly Review'!D13 -> 13 | D33: ='Weekly Review'!G13 -> 0 | E33: ='Weekly Review'!I13 -> 0 | F33: ='Weekly Review'!H13 -> 13 | G33: ='Weekly Review'!J13 -> 0 | H33: ='Weekly Review'!K13 -> -0.5
A34: ='Weekly Review'!A14 -> 5 | B34: ='Weekly Review'!E14 -> 15.5 | C34: ='Weekly Review'!D14 -> 14 | D34: ='Weekly Review'!G14 -> 0 | E34: ='Weekly Review'!I14 -> 0 | F34: ='Weekly Review'!H14 -> 15 | G34: ='Weekly Review'!J14 -> 0 | H34: ='Weekly Review'!K14 -> -1.5
A35: ='Weekly Review'!A15 -> 6 | B35: ='Weekly Review'!E15 -> 11 | C35: ='Weekly Review'!D15 -> 14 | D35: ='Weekly Review'!G15 -> 0 | E35: ='Weekly Review'!I15 -> 0 | F35: ='Weekly Review'!H15 -> 10 | G35: ='Weekly Review'!J15 -> 0 | H35: ='Weekly Review'!K15 -> 3
A36: ='Weekly Review'!A16 -> 7 | B36: ='Weekly Review'!E16 -> 11.25 | C36: ='Weekly Review'!D16 -> 14 | D36: ='Weekly Review'!G16 -> 0 | E36: ='Weekly Review'!I16 -> 0 | F36: ='Weekly Review'!H16 -> 10 | G36: ='Weekly Review'!J16 -> 0 | H36: ='Weekly Review'!K16 -> 2.75
A37: ='Weekly Review'!A17 -> 8 | B37: ='Weekly Review'!E17 -> 10.25 | C37: ='Weekly Review'!D17 -> 14 | D37: ='Weekly Review'!G17 -> 0 | E37: ='Weekly Review'!I17 -> 0 | F37: ='Weekly Review'!H17 -> 8 | G37: ='Weekly Review'!J17 -> 0 | H37: ='Weekly Review'!K17 -> 3.75
A38: ='Weekly Review'!A18 -> 9 | B38: ='Weekly Review'!E18 -> 10.75 | C38: ='Weekly Review'!D18 -> 15 | D38: ='Weekly Review'!G18 -> 0 | E38: ='Weekly Review'!I18 -> 0 | F38: ='Weekly Review'!H18 -> 9 | G38: ='Weekly Review'!J18 -> 0 | H38: ='Weekly Review'!K18 -> 4.25
A39: ='Weekly Review'!A19 -> 10 | B39: ='Weekly Review'!E19 -> 11.25 | C39: ='Weekly Review'!D19 -> 15 | D39: ='Weekly Review'!G19 -> 0 | E39: ='Weekly Review'!I19 -> 0 | F39: ='Weekly Review'!H19 -> 10 | G39: ='Weekly Review'!J19 -> 0 | H39: ='Weekly Review'!K19 -> 3.75
A40: ='Weekly Review'!A20 -> 11 | B40: ='Weekly Review'!E20 -> 11.25 | C40: ='Weekly Review'!D20 -> 15 | D40: ='Weekly Review'!G20 -> 0 | E40: ='Weekly Review'!I20 -> 0 | F40: ='Weekly Review'!H20 -> 10 | G40: ='Weekly Review'!J20 -> 0 | H40: ='Weekly Review'!K20 -> 3.75
A41: ='Weekly Review'!A21 -> 12 | B41: ='Weekly Review'!E21 -> 10.75 | C41: ='Weekly Review'!D21 -> 15 | D41: ='Weekly Review'!G21 -> 0 | E41: ='Weekly Review'!I21 -> 0 | F41: ='Weekly Review'!H21 -> 9 | G41: ='Weekly Review'!J21 -> 0 | H41: ='Weekly Review'!K21 -> 4.25
... A49: ='Weekly Review'!A29 -> 20 | B49: ='Weekly Review'!E29 -> 12 | C49: ='Weekly Review'!D29 -> 15 | D49: ='Weekly Review'!G29 -> 0 | E49: ='Weekly Review'!I29 -> 0 | F49: ='Weekly Review'!H29 -> 11 | G49: ='Weekly Review'!J29 -> 0 | H49: ='Weekly Review'!K29 -> 3
A50: ='Weekly Review'!A30 -> 21 | B50: ='Weekly Review'!E30 -> 9.25 | C50: ='Weekly Review'!D30 -> 15 | D50: ='Weekly Review'!G30 -> 0 | E50: ='Weekly Review'!I30 -> 0 | F50: ='Weekly Review'!H30 -> 7 | G50: ='Weekly Review'!J30 -> 0 | H50: ='Weekly Review'!K30 -> 5.75 | J50: DSA solved | L50: ='Weekly Review'!F4 -> 0 | N50: Target | P50: ='Weekly Review'!I4 -> 145
A51: ='Weekly Review'!A31 -> 22 | B51: ='Weekly Review'!E31 -> 8.5 | C51: ='Weekly Review'!D31 -> 15 | D51: ='Weekly Review'!G31 -> 0 | E51: ='Weekly Review'!I31 -> 0 | F51: ='Weekly Review'!H31 -> 6 | G51: ='Weekly Review'!J31 -> 0 | H51: ='Weekly Review'!K31 -> 6.5
A52: ='Weekly Review'!A32 -> 23 | B52: ='Weekly Review'!E32 -> 8.5 | C52: ='Weekly Review'!D32 -> 15 | D52: ='Weekly Review'!G32 -> 0 | E52: ='Weekly Review'!I32 -> 0 | F52: ='Weekly Review'!H32 -> 6 | G52: ='Weekly Review'!J32 -> 0 | H52: ='Weekly Review'!K32 -> 6.5 | J52: Mocks passed | L52: ='Weekly Review'!F5 -> 0 | N52: Attempted | P52: ='Weekly Review'!I5 -> 0
A53: ='Weekly Review'!A33 -> 24 | B53: ='Weekly Review'!E33 -> 8.5 | C53: ='Weekly Review'!D33 -> 15 | D53: ='Weekly Review'!G33 -> 0 | E53: ='Weekly Review'!I33 -> 0 | F53: ='Weekly Review'!H33 -> 6 | G53: ='Weekly Review'!J33 -> 0 | H53: ='Weekly Review'!K33 -> 6.5
A55: A negative spare-hours value means core work exceeds the weekly capacity. | J55: Review workload before adding optional tasks.
A58: Progress by plan section
A60: Plan section | B60: Tasks | C60: Complete | D60: Progress | E60: Active | F60: Blocked | G60: Est. (h) | H60: Actual (h) | J60: Section coverage | L60: =A7-SUM(B61:B160) -> 0
A61: Gap closure | B61: =COUNTIFS(PlanTasks[Plan section],$A61) -> 10 | C61: =COUNTIFS(PlanTasks[Plan section],$A61,PlanTasks[Completion check],"Complete") -> 2 | D61: =IF(B61=0,"",C61/B61) -> 0.2 | E61: =COUNTIFS(PlanTasks[Plan section],$A61,PlanTasks[Status],"In progress") -> 0 | F61: =COUNTIFS(PlanTasks[Plan section],$A61,PlanTasks[Status],"Blocked") -> 0 | G61: =SUMIFS(PlanTasks[Estimate (h)],PlanTasks[Plan section],$A61) -> 10.25 | H61: =SUMIFS(PlanTasks[Actual (h)],PlanTasks[Plan section],$A61) -> 0.5
A62: Interview Policy | B62: =COUNTIFS(PlanTasks[Plan section],$A62) -> 1 | C62: =COUNTIFS(PlanTasks[Plan section],$A62,PlanTasks[Completion check],"Complete") -> 0 | D62: =IF(B62=0,"",C62/B62) -> 0 | E62: =COUNTIFS(PlanTasks[Plan section],$A62,PlanTasks[Status],"In progress") -> 1 | F62: =COUNTIFS(PlanTasks[Plan section],$A62,PlanTasks[Status],"Blocked") -> 0 | G62: =SUMIFS(PlanTasks[Estimate (h)],PlanTasks[Plan section],$A62) -> 0.75 | H62: =SUMIFS(PlanTasks[Actual (h)],PlanTasks[Plan section],$A62) -> 0 | J62: If nonzero, add new section labels below the section table and copy its formulas.
A63: SQL | B63: =COUNTIFS(PlanTasks[Plan section],$A63) -> 3 | C63: =COUNTIFS(PlanTasks[Plan section],$A63,PlanTasks[Completion check],"Complete") -> 0 | D63: =IF(B63=0,"",C63/B63) -> 0 | E63: =COUNTIFS(PlanTasks[Plan section],$A63,PlanTasks[Status],"In progress") -> 0 | F63: =COUNTIFS(PlanTasks[Plan section],$A63,PlanTasks[Status],"Blocked") -> 0 | G63: =SUMIFS(PlanTasks[Estimate (h)],PlanTasks[Plan section],$A63) -> 2.25 | H63: =SUMIFS(PlanTasks[Actual (h)],PlanTasks[Plan section],$A63) -> 0
A64: Java Core | B64: =COUNTIFS(PlanTasks[Plan section],$A64) -> 6 | C64: =COUNTIFS(PlanTasks[Plan section],$A64,PlanTasks[Completion check],"Complete") -> 0 | D64: =IF(B64=0,"",C64/B64) -> 0 | E64: =COUNTIFS(PlanTasks[Plan section],$A64,PlanTasks[Status],"In progress") -> 0 | F64: =COUNTIFS(PlanTasks[Plan section],$A64,PlanTasks[Status],"Blocked") -> 0 | G64: =SUMIFS(PlanTasks[Estimate (h)],PlanTasks[Plan section],$A64) -> 4.5 | H64: =SUMIFS(PlanTasks[Actual (h)],PlanTasks[Plan section],$A64) -> 0 | J64: Chart data
A65: JavaScript Core | B65: =COUNTIFS(PlanTasks[Plan section],$A65) -> 3 | C65: =COUNTIFS(PlanTasks[Plan section],$A65,PlanTasks[Completion check],"Complete") -> 0 | D65: =IF(B65=0,"",C65/B65) -> 0 | E65: =COUNTIFS(PlanTasks[Plan section],$A65,PlanTasks[Status],"In progress") -> 0 | F65: =COUNTIFS(PlanTasks[Plan section],$A65,PlanTasks[Status],"Blocked") -> 0 | G65: =SUMIFS(PlanTasks[Estimate (h)],PlanTasks[Plan section],$A65) -> 2.25 | H65: =SUMIFS(PlanTasks[Actual (h)],PlanTasks[Plan section],$A65) -> 0 | J65: Category | K65: Est. (h) | L65: Actual (h)
A66: TypeScript Core | B66: =COUNTIFS(PlanTasks[Plan section],$A66) -> 7 | C66: =COUNTIFS(PlanTasks[Plan section],$A66,PlanTasks[Completion check],"Complete") -> 0 | D66: =IF(B66=0,"",C66/B66) -> 0 | E66: =COUNTIFS(PlanTasks[Plan section],$A66,PlanTasks[Status],"In progress") -> 0 | F66: =COUNTIFS(PlanTasks[Plan section],$A66,PlanTasks[Status],"Blocked") -> 0 | G66: =SUMIFS(PlanTasks[Estimate (h)],PlanTasks[Plan section],$A66) -> 5.25 | H66: =SUMIFS(PlanTasks[Actual (h)],PlanTasks[Plan section],$A66) -> 0 | J66: Engineering | K66: =G12 -> 15.75 | L66: =H12 -> 0.25
A67: Tooling | B67: =COUNTIFS(PlanTasks[Plan section],$A67) -> 4 | C67: =COUNTIFS(PlanTasks[Plan section],$A67,PlanTasks[Completion check],"Complete") -> 0 | D67: =IF(B67=0,"",C67/B67) -> 0 | E67: =COUNTIFS(PlanTasks[Plan section],$A67,PlanTasks[Status],"In progress") -> 0 | F67: =COUNTIFS(PlanTasks[Plan section],$A67,PlanTasks[Status],"Blocked") -> 0 | G67: =SUMIFS(PlanTasks[Estimate (h)],PlanTasks[Plan section],$A67) -> 3.5 | H67: =SUMIFS(PlanTasks[Actual (h)],PlanTasks[Plan section],$A67) -> 0 | J67: Java & Spring | K67: =G13 -> 23.25 | L67: =H13 -> 0
A68: Dual Foundations | B68: =COUNTIFS(PlanTasks[Plan section],$A68) -> 4 | C68: =COUNTIFS(PlanTasks[Plan section],$A68,PlanTasks[Completion check],"Complete") -> 0 | D68: =IF(B68=0,"",C68/B68) -> 0 | E68: =COUNTIFS(PlanTasks[Plan section],$A68,PlanTasks[Status],"In progress") -> 0 | F68: =COUNTIFS(PlanTasks[Plan section],$A68,PlanTasks[Status],"Blocked") -> 0 | G68: =SUMIFS(PlanTasks[Estimate (h)],PlanTasks[Plan section],$A68) -> 8 | H68: =SUMIFS(PlanTasks[Actual (h)],PlanTasks[Plan section],$A68) -> 0 | J68: TypeScript & UI | K68: =G14 -> 21.75 | L68: =H14 -> 0
A69: Weekly problem set | B69: =COUNTIFS(PlanTasks[Plan section],$A69) -> 24 | C69: =COUNTIFS(PlanTasks[Plan section],$A69,PlanTasks[Completion check],"Complete") -> 0 | D69: =IF(B69=0,"",C69/B69) -> 0 | E69: =COUNTIFS(PlanTasks[Plan section],$A69,PlanTasks[Status],"In progress") -> 0 | F69: =COUNTIFS(PlanTasks[Plan section],$A69,PlanTasks[Status],"Blocked") -> 0 | G69: =SUMIFS(PlanTasks[Estimate (h)],PlanTasks[Plan section],$A69) -> 72 | H69: =SUMIFS(PlanTasks[Actual (h)],PlanTasks[Plan section],$A69) -> 0 | J69: CS & SQL | K69: =G15 -> 11.5 | L69: =H15 -> 0
A70: Think-aloud communication | B70: =COUNTIFS(PlanTasks[Plan section],$A70) -> 1 | C70: =COUNTIFS(PlanTasks[Plan section],$A70,PlanTasks[Completion check],"Complete") -> 0 | D70: =IF(B70=0,"",C70/B70) -> 0 | E70: =COUNTIFS(PlanTasks[Plan section],$A70,PlanTasks[Status],"In progress") -> 0 | F70: =COUNTIFS(PlanTasks[Plan section],$A70,PlanTasks[Status],"Blocked") -> 0 | G70: =SUMIFS(PlanTasks[Estimate (h)],PlanTasks[Plan section],$A70) -> 1 | H70: =SUMIFS(PlanTasks[Actual (h)],PlanTasks[Plan section],$A70) -> 0 | J70: DSA | K70: =G16 -> 72 | L70: =H16 -> 0
A71: Foundations + Coding | B71: =COUNTIFS(PlanTasks[Plan section],$A71) -> 1 | C71: =COUNTIFS(PlanTasks[Plan section],$A71,PlanTasks[Completion check],"Complete") -> 0 | D71: =IF(B71=0,"",C71/B71) -> 0 | E71: =COUNTIFS(PlanTasks[Plan section],$A71,PlanTasks[Status],"In progress") -> 0 | F71: =COUNTIFS(PlanTasks[Plan section],$A71,PlanTasks[Status],"Blocked") -> 0 | G71: =SUMIFS(PlanTasks[Estimate (h)],PlanTasks[Plan section],$A71) -> 1 | H71: =SUMIFS(PlanTasks[Actual (h)],PlanTasks[Plan section],$A71) -> 0 | J71: System design | K71: =G17 -> 10 | L71: =H17 -> 0
A72: Weekly review | B72: =COUNTIFS(PlanTasks[Plan section],$A72) -> 24 | C72: =COUNTIFS(PlanTasks[Plan section],$A72,PlanTasks[Completion check],"Complete") -> 0 | D72: =IF(B72=0,"",C72/B72) -> 0 | E72: =COUNTIFS(PlanTasks[Plan section],$A72,PlanTasks[Status],"In progress") -> 0 | F72: =COUNTIFS(PlanTasks[Plan section],$A72,PlanTasks[Status],"Blocked") -> 0 | G72: =SUMIFS(PlanTasks[Estimate (h)],PlanTasks[Plan section],$A72) -> 12 | H72: =SUMIFS(PlanTasks[Actual (h)],PlanTasks[Plan section],$A72) -> 0 | J72: Projects | K72: =G18 -> 52.5 | L72: =H18 -> 0
A73: Coding | B73: =COUNTIFS(PlanTasks[Plan section],$A73) -> 3 | C73: =COUNTIFS(PlanTasks[Plan section],$A73,PlanTasks[Completion check],"Complete") -> 0 | D73: =IF(B73=0,"",C73/B73) -> 0 | E73: =COUNTIFS(PlanTasks[Plan section],$A73,PlanTasks[Status],"In progress") -> 0 | F73: =COUNTIFS(PlanTasks[Plan section],$A73,PlanTasks[Status],"Blocked") -> 0 | G73: =SUMIFS(PlanTasks[Estimate (h)],PlanTasks[Plan section],$A73) -> 3 | H73: =SUMIFS(PlanTasks[Actual (h)],PlanTasks[Plan section],$A73) -> 0 | J73: AI Engineering | K73: =G19 -> 5.25 | L73: =H19 -> 0
A74: DBMS | B74: =COUNTIFS(PlanTasks[Plan section],$A74) -> 5 | C74: =COUNTIFS(PlanTasks[Plan section],$A74,PlanTasks[Completion check],"Complete") -> 0 | D74: =IF(B74=0,"",C74/B74) -> 0 | E74: =COUNTIFS(PlanTasks[Plan section],$A74,PlanTasks[Status],"In progress") -> 0 | F74: =COUNTIFS(PlanTasks[Plan section],$A74,PlanTasks[Status],"Blocked") -> 0 | G74: =SUMIFS(PlanTasks[Estimate (h)],PlanTasks[Plan section],$A74) -> 3.75 | H74: =SUMIFS(PlanTasks[Actual (h)],PlanTasks[Plan section],$A74) -> 0 | J74: Mock interviews | K74: =G20 -> 44 | L74: =H20 -> 0
A75: Coding + SQL | B75: =COUNTIFS(PlanTasks[Plan section],$A75) -> 1 | C75: =COUNTIFS(PlanTasks[Plan section],$A75,PlanTasks[Completion check],"Complete") -> 0 | D75: =IF(B75=0,"",C75/B75) -> 0 | E75: =COUNTIFS(PlanTasks[Plan section],$A75,PlanTasks[Status],"In progress") -> 0 | F75: =COUNTIFS(PlanTasks[Plan section],$A75,PlanTasks[Status],"Blocked") -> 0 | G75: =SUMIFS(PlanTasks[Estimate (h)],PlanTasks[Plan section],$A75) -> 1 | H75: =SUMIFS(PlanTasks[Actual (h)],PlanTasks[Plan section],$A75) -> 0 | J75: Review | K75: =G21 -> 13 | L75: =H21 -> 0.25
A76: OS | B76: =COUNTIFS(PlanTasks[Plan section],$A76) -> 1 | C76: =COUNTIFS(PlanTasks[Plan section],$A76,PlanTasks[Completion check],"Complete") -> 0 | D76: =IF(B76=0,"",C76/B76) -> 0 | E76: =COUNTIFS(PlanTasks[Plan section],$A76,PlanTasks[Status],"In progress") -> 0 | F76: =COUNTIFS(PlanTasks[Plan section],$A76,PlanTasks[Status],"Blocked") -> 0 | G76: =SUMIFS(PlanTasks[Estimate (h)],PlanTasks[Plan section],$A76) -> 0.75 | H76: =SUMIFS(PlanTasks[Actual (h)],PlanTasks[Plan section],$A76) -> 0 | J76: Career | K76: =G22 -> 5 | L76: =H22 -> 0
A77: Modern Java | B77: =COUNTIFS(PlanTasks[Plan section],$A77) -> 3 | C77: =COUNTIFS(PlanTasks[Plan section],$A77,PlanTasks[Completion check],"Complete") -> 0 | D77: =IF(B77=0,"",C77/B77) -> 0 | E77: =COUNTIFS(PlanTasks[Plan section],$A77,PlanTasks[Status],"In progress") -> 0 | F77: =COUNTIFS(PlanTasks[Plan section],$A77,PlanTasks[Status],"Blocked") -> 0 | G77: =SUMIFS(PlanTasks[Estimate (h)],PlanTasks[Plan section],$A77) -> 2.25 | H77: =SUMIFS(PlanTasks[Actual (h)],PlanTasks[Plan section],$A77) -> 0
A78: JVM | B78: =COUNTIFS(PlanTasks[Plan section],$A78) -> 1 | C78: =COUNTIFS(PlanTasks[Plan section],$A78,PlanTasks[Completion check],"Complete") -> 0 | D78: =IF(B78=0,"",C78/B78) -> 0 | E78: =COUNTIFS(PlanTasks[Plan section],$A78,PlanTasks[Status],"In progress") -> 0 | F78: =COUNTIFS(PlanTasks[Plan section],$A78,PlanTasks[Status],"Blocked") -> 0 | G78: =SUMIFS(PlanTasks[Estimate (h)],PlanTasks[Plan section],$A78) -> 0.75 | H78: =SUMIFS(PlanTasks[Actual (h)],PlanTasks[Plan section],$A78) -> 0
A79: Runtime | B79: =COUNTIFS(PlanTasks[Plan section],$A79) -> 2 | C79: =COUNTIFS(PlanTasks[Plan section],$A79,PlanTasks[Completion check],"Complete") -> 0 | D79: =IF(B79=0,"",C79/B79) -> 0 | E79: =COUNTIFS(PlanTasks[Plan section],$A79,PlanTasks[Status],"In progress") -> 0 | F79: =COUNTIFS(PlanTasks[Plan section],$A79,PlanTasks[Status],"Blocked") -> 0 | G79: =SUMIFS(PlanTasks[Estimate (h)],PlanTasks[Plan section],$A79) -> 1.5 | H79: =SUMIFS(PlanTasks[Actual (h)],PlanTasks[Plan section],$A79) -> 0
A80: Mixed Fundamentals | B80: =COUNTIFS(PlanTasks[Plan section],$A80) -> 1 | C80: =COUNTIFS(PlanTasks[Plan section],$A80,PlanTasks[Completion check],"Complete") -> 0 | D80: =IF(B80=0,"",C80/B80) -> 0 | E80: =COUNTIFS(PlanTasks[Plan section],$A80,PlanTasks[Status],"In progress") -> 0 | F80: =COUNTIFS(PlanTasks[Plan section],$A80,PlanTasks[Status],"Blocked") -> 0 | G80: =SUMIFS(PlanTasks[Estimate (h)],PlanTasks[Plan section],$A80) -> 1 | H80: =SUMIFS(PlanTasks[Actual (h)],PlanTasks[Plan section],$A80) -> 0
A81: Fundamentals | B81: =COUNTIFS(PlanTasks[Plan section],$A81) -> 1 | C81: =COUNTIFS(PlanTasks[Plan section],$A81,PlanTasks[Completion check],"Complete") -> 0 | D81: =IF(B81=0,"",C81/B81) -> 0 | E81: =COUNTIFS(PlanTasks[Plan section],$A81,PlanTasks[Status],"In progress") -> 0 | F81: =COUNTIFS(PlanTasks[Plan section],$A81,PlanTasks[Status],"Blocked") -> 0 | G81: =SUMIFS(PlanTasks[Estimate (h)],PlanTasks[Plan section],$A81) -> 0.75 | H81: =SUMIFS(PlanTasks[Actual (h)],PlanTasks[Plan section],$A81) -> 0
A82: Networking | B82: =COUNTIFS(PlanTasks[Plan section],$A82) -> 4 | C82: =COUNTIFS(PlanTasks[Plan section],$A82,PlanTasks[Completion check],"Complete") -> 0 | D82: =IF(B82=0,"",C82/B82) -> 0 | E82: =COUNTIFS(PlanTasks[Plan section],$A82,PlanTasks[Status],"In progress") -> 0 | F82: =COUNTIFS(PlanTasks[Plan section],$A82,PlanTasks[Status],"Blocked") -> 0 | G82: =SUMIFS(PlanTasks[Estimate (h)],PlanTasks[Plan section],$A82) -> 3 | H82: =SUMIFS(PlanTasks[Actual (h)],PlanTasks[Plan section],$A82) -> 0
A83: Spring Core | B83: =COUNTIFS(PlanTasks[Plan section],$A83) -> 1 | C83: =COUNTIFS(PlanTasks[Plan section],$A83,PlanTasks[Completion check],"Complete") -> 0 | D83: =IF(B83=0,"",C83/B83) -> 0 | E83: =COUNTIFS(PlanTasks[Plan section],$A83,PlanTasks[Status],"In progress") -> 0 | F83: =COUNTIFS(PlanTasks[Plan section],$A83,PlanTasks[Status],"Blocked") -> 0 | G83: =SUMIFS(PlanTasks[Estimate (h)],PlanTasks[Plan section],$A83) -> 0.75 | H83: =SUMIFS(PlanTasks[Actual (h)],PlanTasks[Plan section],$A83) -> 0
A84: Spring Boot | B84: =COUNTIFS(PlanTasks[Plan section],$A84) -> 2 | C84: =COUNTIFS(PlanTasks[Plan section],$A84,PlanTasks[Completion check],"Complete") -> 0 | D84: =IF(B84=0,"",C84/B84) -> 0 | E84: =COUNTIFS(PlanTasks[Plan section],$A84,PlanTasks[Status],"In progress") -> 0 | F84: =COUNTIFS(PlanTasks[Plan section],$A84,PlanTasks[Status],"Blocked") -> 0 | G84: =SUMIFS(PlanTasks[Estimate (h)],PlanTasks[Plan section],$A84) -> 1.5 | H84: =SUMIFS(PlanTasks[Actual (h)],PlanTasks[Plan section],$A84) -> 0
A85: Frontend | B85: =COUNTIFS(PlanTasks[Plan section],$A85) -> 2 | C85: =COUNTIFS(PlanTasks[Plan section],$A85,PlanTasks[Completion check],"Complete") -> 0 | D85: =IF(B85=0,"",C85/B85) -> 0 | E85: =COUNTIFS(PlanTasks[Plan section],$A85,PlanTasks[Status],"In progress") -> 0 | F85: =COUNTIFS(PlanTasks[Plan section],$A85,PlanTasks[Status],"Blocked") -> 0 | G85: =SUMIFS(PlanTasks[Estimate (h)],PlanTasks[Plan section],$A85) -> 1.5 | H85: =SUMIFS(PlanTasks[Actual (h)],PlanTasks[Plan section],$A85) -> 0
A86: React | B86: =COUNTIFS(PlanTasks[Plan section],$A86) -> 3 | C86: =COUNTIFS(PlanTasks[Plan section],$A86,PlanTasks[Completion check],"Complete") -> 0 | D86: =IF(B86=0,"",C86/B86) -> 0 | E86: =COUNTIFS(PlanTasks[Plan section],$A86,PlanTasks[Status],"In progress") -> 0 | F86: =COUNTIFS(PlanTasks[Plan section],$A86,PlanTasks[Status],"Blocked") -> 0 | G86: =SUMIFS(PlanTasks[Estimate (h)],PlanTasks[Plan section],$A86) -> 2.25 | H86: =SUMIFS(PlanTasks[Actual (h)],PlanTasks[Plan section],$A86) -> 0
A87: API Core | B87: =COUNTIFS(PlanTasks[Plan section],$A87) -> 4 | C87: =COUNTIFS(PlanTasks[Plan section],$A87,PlanTasks[Completion check],"Complete") -> 0 | D87: =IF(B87=0,"",C87/B87) -> 0 | E87: =COUNTIFS(PlanTasks[Plan section],$A87,PlanTasks[Status],"In progress") -> 0 | F87: =COUNTIFS(PlanTasks[Plan section],$A87,PlanTasks[Status],"Blocked") -> 0 | G87: =SUMIFS(PlanTasks[Estimate (h)],PlanTasks[Plan section],$A87) -> 8 | H87: =SUMIFS(PlanTasks[Actual (h)],PlanTasks[Plan section],$A87) -> 0
A88: Unfamiliar codebase orientation | B88: =COUNTIFS(PlanTasks[Plan section],$A88) -> 1 | C88: =COUNTIFS(PlanTasks[Plan section],$A88,PlanTasks[Completion check],"Complete") -> 0 | D88: =IF(B88=0,"",C88/B88) -> 0 | E88: =COUNTIFS(PlanTasks[Plan section],$A88,PlanTasks[Status],"In progress") -> 0 | F88: =COUNTIFS(PlanTasks[Plan section],$A88,PlanTasks[Status],"Blocked") -> 0 | G88: =SUMIFS(PlanTasks[Estimate (h)],PlanTasks[Plan section],$A88) -> 1 | H88: =SUMIFS(PlanTasks[Actual (h)],PlanTasks[Plan section],$A88) -> 0
... A160: Final Design + Behavioral | B160: =COUNTIFS(PlanTasks[Plan section],$A160) -> 1 | C160: =COUNTIFS(PlanTasks[Plan section],$A160,PlanTasks[Completion check],"Complete") -> 0 | D160: =IF(B160=0,"",C160/B160) -> 0 | E160: =COUNTIFS(PlanTasks[Plan section],$A160,PlanTasks[Status],"In progress") -> 0 | F160: =COUNTIFS(PlanTasks[Plan section],$A160,PlanTasks[Status],"Blocked") -> 0 | G160: =SUMIFS(PlanTasks[Estimate (h)],PlanTasks[Plan section],$A160) -> 1 | H160: =SUMIFS(PlanTasks[Actual (h)],PlanTasks[Plan section],$A160) -> 0

Sheet Master Plan
A1: Software engineering interview plan
A2: Edit tasks here. Dashboard and category tabs update from this table in the same order.
A3: Amber cells are inputs. Add tasks inside PlanTasks. Category key is calculated. Set the plan start date in Weekly Review.
A5: Task ID | B5: Start week | C5: Category | D5: Work type | E5: Task / deliverable | F5: Priority | G5: Status | H5: Evidence / result | I5: Next action / blocker | J5: Due date | K5: Scope | L5: Estimate (h) | M5: Actual (h) | N5: Confidence 0-5 | O5: Done when | P5: Exercise / interview prompt | Q5: Prerequisite IDs | R5: Completed on | S5: Review due | T5: AI practice mode | U5: Origin | V5: Original source rows | W5: Source IDs | X5: End week | Y5: Plan section | Z5: Technical 0-5 | AA5: Communication 0-5 | AB5: Mock result | AC5: Original schedule / reviews | AD5: Completion check | AE5: Category key
A6: G01 | B6: 1 | C6: Review | D6: Setup | E6: Set the target role, baseline and weekly time budget | F6: P0 | G6: Done | H6: java --version, javac --version, npm --version, nvm --version | J6: =IF('Weekly Review'!$C$4="","",'Weekly Review'!$C$4+(X6-1)*7+6) -> 46300 | K6: Core | L6: 1 | M6: 0.25 | N6: 5 | O6: Record target roles, start date, available weekly hours and current Java/TS/SQL baseline. Review the proposed task estimates and optional scope. | R6: 46294 | S6: =IF(R6="","",R6+'Weekly Review'!$C$5) -> 46301 | T6: AI-free first | U6: New gap task | X6: 1 | Y6: Gap closure | Z6: 5 | AA6: 5 | AB6: Strong Pass | AD6: =IF(G6="Done",IF(H6="","Add evidence",IF(R6="","Add completion date",IF(D6="Mock",IF(OR(Z6="",AA6="",AB6="",AB6="Not Attempted"),"Record mock results","Complete"),"Complete"))),"") -> Complete | AE6: =C6&"|"&COUNTIFS($C$6:C6,C6) -> Review|1
A7: G02 | B7: 1 | C7: Engineering | D7: Setup | E7: Run both toolchains and a first test from a clean clone | F7: P0 | G7: Done | H7: already workedon java & js/ts projects | J7: =IF('Weekly Review'!$C$4="","",'Weekly Review'!$C$4+(X7-1)*7+6) -> 46300 | K7: Core | L7: 1.5 | M7: 0.25 | N7: 5 | O7: Install compatible JDK/Node tools, pin project versions and lockfiles, run Java tests and TypeScript typecheck/tests, and commit setup instructions. | R7: 46294 | S7: =IF(R7="","",R7+'Weekly Review'!$C$5) -> 46301 | T7: AI-free first | U7: New gap task | X7: 1 | Y7: Gap closure | Z7: 5 | AA7: 5 | AB7: Strong Pass | AD7: =IF(G7="Done",IF(H7="","Add evidence",IF(R7="","Add completion date",IF(D7="Mock",IF(OR(Z7="",AA7="",AB7="",AB7="Not Attempted"),"Record mock results","Complete"),"Complete"))),"") -> Complete | AE7: =C7&"|"&COUNTIFS($C$6:C7,C7) -> Engineering|1
A8: AI18 | B8: 1 | C8: AI Engineering | D8: Learn | E8: Confirm round policy and rehearse AI-free fallback | F8: P0 | G8: In progress | J8: =IF('Weekly Review'!$C$4="","",'Weekly Review'!$C$4+(X8-1)*7+6) -> 46300 | K8: Core | L8: 0.75 | M8: 0 | N8: 0 | O8: Confirm exact permitted tools and boundaries Code/debug/explain with no assistant Implement and explain independently Solve/debug/explain without AI when required | P8: Transparent AI-assisted session Failure to test: Policy violation 60-min unaided mock Failure to test: Dependency on tools Redo representative task without any assistant Practice mode: AI-free Yes, AI-assisted No | S8: =IF(R8="","",R8+'Weekly Review'!$C$5) | T8: AI-free first | U8: Merged | V8: AI Engineering!18 AI Engineering!19 Real-World Eng!19 Master Roadmap!75 | W8: S026 S027 S025 | X8: 1 | Y8: Interview Policy | AC8: W22–24 Review: Repeat until interview W21–24 | AD8: =IF(G8="Done",IF(H8="","Add evidence",IF(R8="","Add completion date",IF(D8="Mock",IF(OR(Z8="",AA8="",AB8="",AB8="Not Attempted"),"Record mock results","Complete"),"Complete"))),"") | AE8: =C8&"|"&COUNTIFS($C$6:C8,C8) -> AI Engineering|1
A9: CS12 | B9: 1 | C9: CS & SQL | D9: Learn | E9: JOINs | F9: P0 | G9: Not started | J9: =IF('Weekly Review'!$C$4="","",'Weekly Review'!$C$4+(X9-1)*7+6) -> 46300 | K9: Core | L9: 0.75 | M9: 0 | N9: 0 | O9: INNER/LEFT and multi-table reasoning JOINs, GROUP BY, HAVING, subqueries, CTEs, CASE, aggregates | P9: Interview: Return customers with/without orders | S9: =IF(R9="","",R9+'Weekly Review'!$C$5) | T9: AI-free first | U9: Merged | V9: CS Fundamentals!12 Master Roadmap!25 | W9: S020 | X9: 1 | Y9: SQL | AC9: W1–2 Review: W4 + W21–24 W1 | AD9: =IF(G9="Done",IF(H9="","Add evidence",IF(R9="","Add completion date",IF(D9="Mock",IF(OR(Z9="",AA9="",AB9="",AB9="Not Attempted"),"Record mock results","Complete"),"Complete"))),"") | AE9: =C9&"|"&COUNTIFS($C$6:C9,C9) -> CS & SQL|1
A10: JA05 | B10: 1 | C10: Java & Spring | D10: Learn | E10: Syntax + object model | F10: P0 | G10: Not started | J10: =IF('Weekly Review'!$C$4="","",'Weekly Review'!$C$4+(X10-1)*7+6) -> 46300 | K10: Core | L10: 0.75 | M10: 0 | N10: 0 | O10: types, references, methods, packages, access modifiers OOP, collections, generics, exceptions, streams, records, sealed classes Write clean Java; primitives/references, methods, packages, exceptions | P10: 20 small Java drills Interview: primitive vs reference? pass-by-value? Implement a domain service and explain object/model choices Build Java kata + service layer Primary backend language Complete 20 Java coding drills | S10: =IF(R10="","",R10+'Weekly Review'!$C$5) | T10: AI-free first | U10: Merged | V10: Java + Spring Boot!5 Full-Stack Stack!5 Master Roadmap!80 | W10: S001 | X10: 1 | Y10: Java Core | AC10: W1 Review: W4 + W21–24 | AD10: =IF(G10="Done",IF(H10="","Add evidence",IF(R10="","Add completion date",IF(D10="Mock",IF(OR(Z10="",AA10="",AB10="",AB10="Not Attempted"),"Record mock results","Complete"),"Complete"))),"") | AE10: =C10&"|"&COUNTIFS($C$6:C10,C10) -> Java & Spring|1
A11: JA06 | B11: 1 | C11: Java & Spring | D11: Learn | E11: OOP | F11: P0 | G11: Not started | J11: =IF('Weekly Review'!$C$4="","",'Weekly Review'!$C$4+(X11-1)*7+6) -> 46307 | K11: Core | L11: 0.75 | M11: 0 | N11: 0 | O11: encapsulation, abstraction, inheritance, polymorphism, composition Explain each and when composition is preferable Apply principles without overengineering Encapsulation, composition, interfaces, SOLID trade-offs Model domains with classes/interfaces; composition, immutability, dependency boundaries | P11: model order/payment domain Interview: composition vs inheritance? Interview: Composition vs inheritance? Interview: Which SOLID principle is violated here? Refactor a service using composition | Q11: G02 | S11: =IF(R11="","",R11+'Weekly Review'!$C$5) | T11: AI-free first | U11: Merged | V11: Java + Spring Boot!6 CS Fundamentals!5 CS Fundamentals!6 Master Roadmap!21 Master Roadmap!81 | W11: S001 S019 | X11: 2 | Y11: Java Core | AC11: W1 Review: W4 + W21–24 W2 | AD11: =IF(G11="Done",IF(H11="","Add evidence",IF(R11="","Add completion date",IF(D11="Mock",IF(OR(Z11="",AA11="",AB11="",AB11="Not Attempted"),"Record mock results","Complete"),"Complete"))),"") | AE11: =C11&"|"&COUNTIFS($C$6:C11,C11) -> Java & Spring|2
A12: TS05 | B12: 1 | C12: TypeScript & UI | D12: Learn | E12: Scopes / closures | F12: P0 | G12: Not started | J12: =IF('Weekly Review'!$C$4="","",'Weekly Review'!$C$4+(X12-1)*7+6) -> 46300 | K12: Core | L12: 0.75 | M12: 0 | N12: 0 | O12: lexical scope, closure use and pitfalls | P12: closure/event handler drills Interview: explain a closure bug | S12: =IF(R12="","",R12+'Weekly Review'!$C$5) | T12: AI-free first | U12: Existing | V12: TypeScript Track!5 | W12: S014 | X12: 1 | Y12: JavaScript Core | AC12: W1 Review: W4 + W21–24 | AD12: =IF(G12="Done",IF(H12="","Add evidence",IF(R12="","Add completion date",IF(D12="Mock",IF(OR(Z12="",AA12="",AB12="",AB12="Not Attempted"),"Record mock results","Complete"),"Complete"))),"") | AE12: =C12&"|"&COUNTIFS($C$6:C12,C12) -> TypeScript & UI|1
A13: TS08 | B13: 1 | C13: TypeScript & UI | D13: Learn | E13: Strict types | F13: P0 | G13: Not started | J13: =IF('Weekly Review'!$C$4="","",'Weekly Review'!$C$4+(X13-1)*7+6) -> 46300 | K13: Core | L13: 0.75 | M13: 0 | N13: 0 | O13: strict mode, inference, annotations, nullability strict typing, generics, narrowing, unions, utility types, async, ESM Types, closures, event loop, promises, async/await, modules, errors strict mode, unions/intersections, generics, narrowing, utility types | P13: convert JS module to strict TS Interview: why avoid any? unknown vs any? Refactor unsafe JS into strict TypeScript Strict TS utility/API module Primary frontend/full-stack language Enable strict mode and remove unsafe any | S13: =IF(R13="","",R13+'Weekly Review'!$C$5) | T13: AI-free first | U13: Merged | V13: TypeScript Track!8 Full-Stack Stack!6 Master Roadmap!19 Master Roadmap!99 | W13: S015 S017 | X13: 1 | Y13: TypeScript Core | AC13: W1 Review: W4 + W21–24 | AD13: =IF(G13="Done",IF(H13="","Add evidence",IF(R13="","Add completion date",IF(D13="Mock",IF(OR(Z13="",AA13="",AB13="",AB13="Not Attempted"),"Record mock results","Complete"),"Complete"))),"") | AE13: =C13&"|"&COUNTIFS($C$6:C13,C13) -> TypeScript & UI|2
A14: TS26 | B14: 1 | C14: TypeScript & UI | D14: Learn | E14: pnpm/npm + lockfiles | F14: P1 | G14: Not started | J14: =IF('Weekly Review'!$C$4="","",'Weekly Review'!$C$4+(X14-1)*7+6) -> 46300 | K14: Core | L14: 0.75 | M14: 0 | N14: 0 | O14: scripts, dependency graph, lockfile reproducibility package.json, lockfiles, scripts, dependency hygiene | P14: clean build from fresh clone Interview: why commit lockfile? Explain reproducible frontend builds Clean TS build pipeline TypeScript tooling | S14: =IF(R14="","",R14+'Weekly Review'!$C$5) | T14: AI-free first | U14: Merged | V14: TypeScript Track!26 Full-Stack Stack!25 | W14: S015 | X14: 1 | Y14: Tooling | AC14: W1 Review: W4 + W21–24 | AD14: =IF(G14="Done",IF(H14="","Add evidence",IF(R14="","Add completion date",IF(D14="Mock",IF(OR(Z14="",AA14="",AB14="",AB14="Not Attempted"),"Record mock results","Complete"),"Complete"))),"") | AE14: =C14&"|"&COUNTIFS($C$6:C14,C14) -> TypeScript & UI|3
A15: EN26 | B15: 1 | C15: Engineering | D15: Build | E15: Git | F15: P1 | G15: Not started | J15: =IF('Weekly Review'!$C$4="","",'Weekly Review'!$C$4+(X15-1)*7+6) -> 46300 | K15: Core | L15: 1 | M15: 0 | N15: 0 | O15: branch, commit, merge/rebase, conflict, PR, bisect concept Branching, merge/rebase, conflicts, PR workflow | P15: Resolve a conflict and explain history PR-based practice Shared | S15: =IF(R15="","",R15+'Weekly Review'!$C$5) | T15: AI-free first | U15: Merged | V15: Full-Stack Stack!26 Master Roadmap!61 | W15: S024 | X15: 1 | Y15: Tooling | AC15: W1 + throughout Review: W4 + W21–24 | AD15: =IF(G15="Done",IF(H15="","Add evidence",IF(R15="","Add completion date",IF(D15="Mock",IF(OR(Z15="",AA15="",AB15="",AB15="Not Attempted"),"Record mock results","Complete"),"Complete"))),"") | AE15: =C15&"|"&COUNTIFS($C$6:C15,C15) -> Engineering|2
A16: B01 | B16: 1 | C16: Projects | D16: Build | E16: Set up Java/TS repo; Java domain kata; convert a small JS module to strict TS | F16: P1 | G16: Not started | J16: =IF('Weekly Review'!$C$4="","",'Weekly Review'!$C$4+(X16-1)*7+6) -> 46300 | K16: Core | L16: 2 | M16: 0 | N16: 0 | O16: Demonstrate the working output, relevant tests, and one design trade-off. | P16: CS/SQL: OOP pillars + basic SELECT/WHERE/JOIN Design: Requirements + simple API/data model AI practice: AI-free baseline; explain every line yourself Set up Java/TS repo; Java domain kata; convert a small JS module to strict TS Sketch a simple booking/order API and 3–4 core entities No-AI baseline: solve/explain without assistant | Q16: G02 | S16: =IF(R16="","",R16+'Weekly Review'!$C$5) | T16: AI-free first | U16: Merged | V16: 24-Week Plan!5 Weekly Task Navigator!5 | X16: 1 | Y16: Dual Foundations | AD16: =IF(G16="Done",IF(H16="","Add evidence",IF(R16="","Add completion date",IF(D16="Mock",IF(OR(Z16="",AA16="",AB16="",AB16="Not Attempted"),"Record mock results","Complete"),"Complete"))),"") | AE16: =C16&"|"&COUNTIFS($C$6:C16,C16) -> Projects|1
A17: DS01 | B17: 1 | C17: DSA | D17: Practice | E17: Solve 7 new DSA problems and revisit errors | F17: P0 | G17: Not started | J17: =IF('Weekly Review'!$C$4="","",'Weekly Review'!$C$4+(X17-1)*7+6) -> 46300 | K17: Core | L17: 3 | M17: 0 | N17: 0 | O17: Record 7 distinct new problem IDs, explain complexity, and retry one earlier mistake without hints. | P17: Complexity & arrays (bank target 8) Use Practice Bank for topic totals. Do not count repeat solutions as new problems. | S17: =IF(R17="","",R17+'Weekly Review'!$C$5) | T17: AI-free first | U17: Revised schedule | V17: 24-Week Plan!D5 Weekly Task Navigator!E5 | X17: 1 | Y17: Weekly problem set | AD17: =IF(G17="Done",IF(H17="","Add evidence",IF(R17="","Add completion date",IF(D17="Mock",IF(OR(Z17="",AA17="",AB17="",AB17="Not Attempted"),"Record mock results","Complete"),"Complete"))),"") | AE17: =C17&"|"&COUNTIFS($C$6:C17,C17) -> DSA|1
A18: RW20 | B18: 1 | C18: Engineering | D18: Practice | E18: Think-aloud communication | F18: P0 | G18: Not started | J18: =IF('Weekly Review'!$C$4="","",'Weekly Review'!$C$4+(X18-1)*7+6) -> 46300 | K18: Core | L18: 1 | M18: 0 | N18: 0 | O18: Clear reasoning without constant chatter Clarify, plan, narrate decisions without rambling | P18: Narrate plan, uncertainty, choices and validation Practice mode: AI-free Yes, AI-assisted Yes | S18: =IF(R18="","",R18+'Weekly Review'!$C$5) | T18: AI-free first | U18: Merged | V18: Real-World Eng!20 Master Roadmap!78 | W18: S021 | X18: 1 | Y18: Think-aloud communication | AC18: W1 + every mock Review: W4 + W21–24 W1 + throughout | AD18: =IF(G18="Done",IF(H18="","Add evidence",IF(R18="","Add completion date",IF(D18="Mock",IF(OR(Z18="",AA18="",AB18="",AB18="Not Attempted"),"Record mock results","Complete"),"Complete"))),"") | AE18: =C18&"|"&COUNTIFS($C$6:C18,C18) -> Engineering|3
A19: M01 | B19: 1 | C19: Mock interviews | D19: Mock | E19: Java Big-O/arrays/OOP + verbal reasoning | F19: P0 | G19: Not started | J19: =IF('Weekly Review'!$C$4="","",'Weekly Review'!$C$4+(X19-1)*7+6) -> 46300 | K19: Core | L19: 1 | M19: 0 | N19: 0 | O19: Complete the timed round. Record technical and communication scores, result, evidence, and one correction before the next mock. | S19: =IF(R19="","",R19+'Weekly Review'!$C$5) | T19: AI-Free | U19: Existing | V19: Mock Interviews!5 | X19: 1 | Y19: Foundations + Coding | AB19: Not Attempted | AD19: =IF(G19="Done",IF(H19="","Add evidence",IF(R19="","Add completion date",IF(D19="Mock",IF(OR(Z19="",AA19="",AB19="",AB19="Not Attempted"),"Record mock results","Complete"),"Complete"))),"") | AE19: =C19&"|"&COUNTIFS($C$6:C19,C19) -> Mock interviews|1
A20: RV01 | B20: 1 | C20: Review | D20: Review | E20: Review evidence, questions and next-week capacity | F20: P1 | G20: Not started | I20: Record weakest concept and the next practice date. | J20: =IF('Weekly Review'!$C$4="","",'Weekly Review'!$C$4+(X20-1)*7+6) -> 46300 | K20: Core | L20: 0.5 | M20: 0 | N20: 0 | O20: Revisit due topics, practice the questions introduced this week, capture mock feedback, and choose the next three priorities. Update Weekly Review outcome and adjustment. | S20: =IF(R20="","",R20+'Weekly Review'!$C$5) | T20: AI-free first | U20: New gap task | X20: 1 | Y20: Weekly review | AD20: =IF(G20="Done",IF(H20="","Add evidence",IF(R20="","Add completion date",IF(D20="Mock",IF(OR(Z20="",AA20="",AB20="",AB20="Not Attempted"),"Record mock results","Complete"),"Complete"))),"") | AE20: =C20&"|"&COUNTIFS($C$6:C20,C20) -> Review|2
A21: CS13 | B21: 2 | C21: CS & SQL | D21: Learn | E21: GROUP BY / HAVING | F21: P0 | G21: Not started | J21: =IF('Weekly Review'!$C$4="","",'Weekly Review'!$C$4+(X21-1)*7+6) -> 46307 | K21: Core | L21: 0.75 | M21: 0 | N21: 0 | O21: Aggregate correctly and filter grouped results | P21: Interview: Top customers over threshold | S21: =IF(R21="","",R21+'Weekly Review'!$C$5) | T21: AI-free first | U21: Existing | V21: CS Fundamentals!13 | W21: S020 | X21: 2 | Y21: SQL | AC21: W2 Review: W4 + W21–24 | AD21: =IF(G21="Done",IF(H21="","Add evidence",IF(R21="","Add completion date",IF(D21="Mock",IF(OR(Z21="",AA21="",AB21="",AB21="Not Attempted"),"Record mock results","Complete"),"Complete"))),"") | AE21: =C21&"|"&COUNTIFS($C$6:C21,C21) -> CS & SQL|2
A22: JA07 | B22: 2 | C22: Java & Spring | D22: Learn | E22: equals/hashCode/immutability | F22: P0 | G22: Not started | J22: =IF('Weekly Review'!$C$4="","",'Weekly Review'!$C$4+(X22-1)*7+6) -> 46307 | K22: Core | L22: 0.75 | M22: 0 | N22: 0 | O22: identity vs equality, hash contracts, immutable value objects | P22: value object kata Interview: why can HashMap fail with bad hashCode? | Q22: G02 | S22: =IF(R22="","",R22+'Weekly Review'!$C$5) | T22: AI-free first | U22: Existing | V22: Java + Spring Boot!7 | W22: S001 | X22: 2 | Y22: Java Core | AC22: W2 Review: W4 + W21–24 | AD22: =IF(G22="Done",IF(H22="","Add evidence",IF(R22="","Add completion date",IF(D22="Mock",IF(OR(Z22="",AA22="",AB22="",AB22="Not Attempted"),"Record mock results","Complete"),"Complete"))),"") | AE22: =C22&"|"&COUNTIFS($C$6:C22,C22) -> Java & Spring|3
A23: JA08 | B23: 2 | C23: Java & Spring | D23: Learn | E23: Collections | F23: P0 | G23: Not started | J23: =IF('Weekly Review'!$C$4="","",'Weekly Review'!$C$4+(X23-1)*7+6) -> 46307 | K23: Core | L23: 0.75 | M23: 0 | N23: 0 | O23: List/Set/Map/Queue, implementations, complexity Choose List/Set/Map/Queue; generics bounds; equality/hashCode | P23: collection selection drills Interview: ArrayList vs LinkedList? HashMap internals high level? Implement domain collections exercises | Q23: G02 | S23: =IF(R23="","",R23+'Weekly Review'!$C$5) | T23: AI-free first | U23: Merged | V23: Java + Spring Boot!8 Master Roadmap!82 | W23: S001 | X23: 2 | Y23: Java Core | AC23: W2 Review: W4 + W21–24 W3 | AD23: =IF(G23="Done",IF(H23="","Add evidence",IF(R23="","Add completion date",IF(D23="Mock",IF(OR(Z23="",AA23="",AB23="",AB23="Not Attempted"),"Record mock results","Complete"),"Complete"))),"") | AE23: =C23&"|"&COUNTIFS($C$6:C23,C23) -> Java & Spring|4
A24: TS06 | B24: 2 | C24: TypeScript & UI | D24: Learn | E24: Objects / prototypes | F24: P1 | G24: Not started | J24: =IF('Weekly Review'!$C$4="","",'Weekly Review'!$C$4+(X24-1)*7+6) -> 46307 | K24: Core | L24: 0.75 | M24: 0 | N24: 0 | O24: object semantics, prototype chain high level, this behavior | P24: object method drills Interview: arrow vs function this? | Q24: G02 | S24: =IF(R24="","",R24+'Weekly Review'!$C$5) | T24: AI-free first | U24: Existing | V24: TypeScript Track!6 | W24: S014 | X24: 2 | Y24: JavaScript Core | AC24: W2 Review: W4 + W21–24 | AD24: =IF(G24="Done",IF(H24="","Add evidence",IF(R24="","Add completion date",IF(D24="Mock",IF(OR(Z24="",AA24="",AB24="",AB24="Not Attempted"),"Record mock results","Complete"),"Complete"))),"") | AE24: =C24&"|"&COUNTIFS($C$6:C24,C24) -> TypeScript & UI|4
A25: TS09 | B25: 2 | C25: TypeScript & UI | D25: Learn | E25: Union/intersection/narrowing | F25: P0 | G25: Not started | J25: =IF('Weekly Review'!$C$4="","",'Weekly Review'!$C$4+(X25-1)*7+6) -> 46307 | K25: Core | L25: 0.75 | M25: 0 | N25: 0 | O25: discriminated unions, guards, exhaustive checks | P25: typed state machine Interview: how model API states safely? | Q25: G02 | S25: =IF(R25="","",R25+'Weekly Review'!$C$5) | T25: AI-free first | U25: Existing | V25: TypeScript Track!9 | W25: S015 | X25: 2 | Y25: TypeScript Core | AC25: W2 Review: W4 + W21–24 | AD25: =IF(G25="Done",IF(H25="","Add evidence",IF(R25="","Add completion date",IF(D25="Mock",IF(OR(Z25="",AA25="",AB25="",AB25="Not Attempted"),"Record mock results","Complete"),"Complete"))),"") | AE25: =C25&"|"&COUNTIFS($C$6:C25,C25) -> TypeScript & UI|5
A26: B02 | B26: 2 | C26: Projects | D26: Build | E26: Immutable Java value objects + typed TS API-state exercise | F26: P1 | G26: Not started | J26: =IF('Weekly Review'!$C$4="","",'Weekly Review'!$C$4+(X26-1)*7+6) -> 46307 | K26: Core | L26: 2 | M26: 0 | N26: 0 | O26: Demonstrate the working output, relevant tests, and one design trade-off. | P26: CS/SQL: SOLID basics + GROUP BY/HAVING Design: REST resources, methods, status codes AI practice: AI-free; compare your solution with AI only after completion Immutable Java value objects + typed TS API-state exercise Refine REST resources, methods and status-code choices No-AI first; compare with AI only after you finish | Q26: B01 | S26: =IF(R26="","",R26+'Weekly Review'!$C$5) | T26: AI-free first | U26: Merged | V26: 24-Week Plan!6 Weekly Task Navigator!6 | X26: 2 | Y26: Dual Foundations | AD26: =IF(G26="Done",IF(H26="","Add evidence",IF(R26="","Add completion date",IF(D26="Mock",IF(OR(Z26="",AA26="",AB26="",AB26="Not Attempted"),"Record mock results","Complete"),"Complete"))),"") | AE26: =C26&"|"&COUNTIFS($C$6:C26,C26) -> Projects|2
A27: DS02 | B27: 2 | C27: DSA | D27: Practice | E27: Solve 7 new DSA problems and revisit errors | F27: P0 | G27: Not started | J27: =IF('Weekly Review'!$C$4="","",'Weekly Review'!$C$4+(X27-1)*7+6) -> 46307 | K27: Core | L27: 3 | M27: 0 | N27: 0 | O27: Record 7 distinct new problem IDs, explain complexity, and retry one earlier mistake without hints. | P27: Strings (bank target 7) Hash map / set (bank target 10) Two pointers (bank target 8) Use Practice Bank for topic totals. Do not count repeat solutions as new problems. | S27: =IF(R27="","",R27+'Weekly Review'!$C$5) | T27: AI-free first | U27: Revised schedule | V27: 24-Week Plan!D6 Weekly Task Navigator!E6 | X27: 2 | Y27: Weekly problem set | AD27: =IF(G27="Done",IF(H27="","Add evidence",IF(R27="","Add completion date",IF(D27="Mock",IF(OR(Z27="",AA27="",AB27="",AB27="Not Attempted"),"Record mock results","Complete"),"Complete"))),"") | AE27: =C27&"|"&COUNTIFS($C$6:C27,C27) -> DSA|2
A28: G03 | B28: 2 | C28: Career | D28: Career | E28: Create a role shortlist and requirements checklist | F28: P1 | G28: Not started | J28: =IF('Weekly Review'!$C$4="","",'Weekly Review'!$C$4+(X28-1)*7+6) -> 46307 | K28: Core | L28: 0.75 | M28: 0 | N28: 0 | O28: Capture five relevant role descriptions, their required skills and permitted assessment tools. Select a primary role focus. | S28: =IF(R28="","",R28+'Weekly Review'!$C$5) | T28: AI-free first | U28: New gap task | X28: 2 | Y28: Gap closure | AD28: =IF(G28="Done",IF(H28="","Add evidence",IF(R28="","Add completion date",IF(D28="Mock",IF(OR(Z28="",AA28="",AB28="",AB28="Not Attempted"),"Record mock results","Complete"),"Complete"))),"") | AE28: =C28&"|"&COUNTIFS($C$6:C28,C28) -> Career|1
A29: M02 | B29: 2 | C29: Mock interviews | D29: Mock | E29: HashMap/two pointers + Java collections | F29: P0 | G29: Not started | J29: =IF('Weekly Review'!$C$4="","",'Weekly Review'!$C$4+(X29-1)*7+6) -> 46307 | K29: Core | L29: 1 | M29: 0 | N29: 0 | O29: Complete the timed round. Record technical and communication scores, result, evidence, and one correction before the next mock. | S29: =IF(R29="","",R29+'Weekly Review'!$C$5) | T29: AI-Free | U29: Existing | V29: Mock Interviews!6 | X29: 2 | Y29: Coding | AB29: Not Attempted | AD29: =IF(G29="Done",IF(H29="","Add evidence",IF(R29="","Add completion date",IF(D29="Mock",IF(OR(Z29="",AA29="",AB29="",AB29="Not Attempted"),"Record mock results","Complete"),"Complete"))),"") | AE29: =C29&"|"&COUNTIFS($C$6:C29,C29) -> Mock interviews|2
A30: RV02 | B30: 2 | C30: Review | D30: Review | E30: Review evidence, questions and next-week capacity | F30: P1 | G30: Not started | I30: Record weakest concept and the next practice date. | J30: =IF('Weekly Review'!$C$4="","",'Weekly Review'!$C$4+(X30-1)*7+6) -> 46307 | K30: Core | L30: 0.5 | M30: 0 | N30: 0 | O30: Revisit due topics, practice the questions introduced this week, capture mock feedback, and choose the next three priorities. Update Weekly Review outcome and adjustment. | S30: =IF(R30="","",R30+'Weekly Review'!$C$5) | T30: AI-free first | U30: New gap task | X30: 2 | Y30: Weekly review | AD30: =IF(G30="Done",IF(H30="","Add evidence",IF(R30="","Add completion date",IF(D30="Mock",IF(OR(Z30="",AA30="",AB30="",AB30="Not Attempted"),"Record mock results","Complete"),"Complete"))),"") | AE30: =C30&"|"&COUNTIFS($C$6:C30,C30) -> Review|3
A31: CS07 | B31: 3 | C31: CS & SQL | D31: Learn | E31: ACID | F31: P0 | G31: Not started | J31: =IF('Weekly Review'!$C$4="","",'Weekly Review'!$C$4+(X31-1)*7+6) -> 46314 | K31: Core | L31: 0.75 | M31: 0 | N31: 0 | O31: Explain each property using payment/order example | P31: Interview: Why do transactions matter? | S31: =IF(R31="","",R31+'Weekly Review'!$C$5) | T31: AI-free first | U31: Existing | V31: CS Fundamentals!7 | W31: S019 | X31: 3 | Y31: DBMS | AC31: W3 Review: W4 + W21–24 | AD31: =IF(G31="Done",IF(H31="","Add evidence",IF(R31="","Add completion date",IF(D31="Mock",IF(OR(Z31="",AA31="",AB31="",AB31="Not Attempted"),"Record mock results","Complete"),"Complete"))),"") | AE31: =C31&"|"&COUNTIFS($C$6:C31,C31) -> CS & SQL|3
A32: CS08 | B32: 3 | C32: CS & SQL | D32: Learn | E32: Normalization | F32: P1 | G32: Not started | J32: =IF('Weekly Review'!$C$4="","",'Weekly Review'!$C$4+(X32-1)*7+6) -> 46314 | K32: Core | L32: 0.75 | M32: 0 | N32: 0 | O32: 1NF/2NF/3NF and denormalization trade-offs DDL/DML, joins, constraints, indexes, transactions, isolation Schema, constraints, transactions, indexes, EXPLAIN basics 1NF–3NF reasoning, entities, cardinality, integrity | P32: Interview: Normalize this schema Design + query a commerce schema Schema + 20 SQL questions Shared database foundation | S32: =IF(R32="","",R32+'Weekly Review'!$C$5) | T32: AI-free first | U32: Merged | V32: CS Fundamentals!8 Full-Stack Stack!15 Master Roadmap!26 Master Roadmap!27 | W32: S019 S004 S020 | X32: 3 | Y32: DBMS | AC32: W3 Review: W4 + W21–24 W3–10 | AD32: =IF(G32="Done",IF(H32="","Add evidence",IF(R32="","Add completion date",IF(D32="Mock",IF(OR(Z32="",AA32="",AB32="",AB32="Not Attempted"),"Record mock results","Complete"),"Complete"))),"") | AE32: =C32&"|"&COUNTIFS($C$6:C32,C32) -> CS & SQL|4
A33: JA09 | B33: 3 | C33: Java & Spring | D33: Learn | E33: Generics | F33: P1 | G33: Not started | J33: =IF('Weekly Review'!$C$4="","",'Weekly Review'!$C$4+(X33-1)*7+6) -> 46314 | K33: Core | L33: 0.75 | M33: 0 | N33: 0 | O33: type parameters, bounds, invariance, wildcards basics | P33: generic repository/filter exercise Interview: ? extends vs ? super? | Q33: G02 | S33: =IF(R33="","",R33+'Weekly Review'!$C$5) | T33: AI-free first | U33: Existing | V33: Java + Spring Boot!9 | W33: S001 | X33: 3 | Y33: Java Core | AC33: W3 Review: W4 + W21–24 | AD33: =IF(G33="Done",IF(H33="","Add evidence",IF(R33="","Add completion date",IF(D33="Mock",IF(OR(Z33="",AA33="",AB33="",AB33="Not Attempted"),"Record mock results","Complete"),"Complete"))),"") | AE33: =C33&"|"&COUNTIFS($C$6:C33,C33) -> Java & Spring|5
A34: JA10 | B34: 3 | C34: Java & Spring | D34: Learn | E34: Exceptions | F34: P0 | G34: Not started | J34: =IF('Weekly Review'!$C$4="","",'Weekly Review'!$C$4+(X34-1)*7+6) -> 46314 | K34: Core | L34: 0.75 | M34: 0 | N34: 0 | O34: checked/unchecked, custom exceptions, try-with-resources Design error boundaries, retries, typed errors, failure paths | P34: API exception taxonomy Interview: when should you catch vs propagate? | Q34: G02 | S34: =IF(R34="","",R34+'Weekly Review'!$C$5) | T34: AI-free first | U34: Merged | V34: Java + Spring Boot!10 Master Roadmap!23 | W34: S001 S026 | X34: 3 | Y34: Java Core | AC34: W3 Review: W4 + W21–24 | AD34: =IF(G34="Done",IF(H34="","Add evidence",IF(R34="","Add completion date",IF(D34="Mock",IF(OR(Z34="",AA34="",AB34="",AB34="Not Attempted"),"Record mock results","Complete"),"Complete"))),"") | AE34: =C34&"|"&COUNTIFS($C$6:C34,C34) -> Java & Spring|6
A35: TS10 | B35: 3 | C35: TypeScript & UI | D35: Learn | E35: Generics | F35: P0 | G35: Not started | J35: =IF('Weekly Review'!$C$4="","",'Weekly Review'!$C$4+(X35-1)*7+6) -> 46314 | K35: Core | L35: 0.75 | M35: 0 | N35: 0 | O35: generic functions/types, constraints, inference | P35: generic table/API helper Interview: generic vs union? | Q35: G02 | S35: =IF(R35="","",R35+'Weekly Review'!$C$5) | T35: AI-free first | U35: Existing | V35: TypeScript Track!10 | W35: S016 | X35: 3 | Y35: TypeScript Core | AC35: W3 Review: W4 + W21–24 | AD35: =IF(G35="Done",IF(H35="","Add evidence",IF(R35="","Add completion date",IF(D35="Mock",IF(OR(Z35="",AA35="",AB35="",AB35="Not Attempted"),"Record mock results","Complete"),"Complete"))),"") | AE35: =C35&"|"&COUNTIFS($C$6:C35,C35) -> TypeScript & UI|6
A36: TS11 | B36: 3 | C36: TypeScript & UI | D36: Learn | E36: Utility / mapped types | F36: P1 | G36: Not started | J36: =IF('Weekly Review'!$C$4="","",'Weekly Review'!$C$4+(X36-1)*7+6) -> 46314 | K36: Core | L36: 0.75 | M36: 0 | N36: 0 | O36: Partial, Pick, Omit, Record; mapped/conditional concepts | P36: DTO transformation examples Interview: when are utility types useful/dangerous? | Q36: G02 | S36: =IF(R36="","",R36+'Weekly Review'!$C$5) | T36: AI-free first | U36: Existing | V36: TypeScript Track!11 | W36: S015 | X36: 3 | Y36: TypeScript Core | AC36: W3 Review: W4 + W21–24 | AD36: =IF(G36="Done",IF(H36="","Add evidence",IF(R36="","Add completion date",IF(D36="Mock",IF(OR(Z36="",AA36="",AB36="",AB36="Not Attempted"),"Record mock results","Complete"),"Complete"))),"") | AE36: =C36&"|"&COUNTIFS($C$6:C36,C36) -> TypeScript & UI|7
A37: TS12 | B37: 3 | C37: TypeScript & UI | D37: Learn | E37: Interfaces vs type aliases | F37: P1 | G37: Not started | J37: =IF('Weekly Review'!$C$4="","",'Weekly Review'!$C$4+(X37-1)*7+6) -> 46314 | K37: Core | L37: 0.75 | M37: 0 | N37: 0 | O37: extension, unions, declaration merging concept | P37: model API contracts both ways Interview: interface vs type? | Q37: G02 | S37: =IF(R37="","",R37+'Weekly Review'!$C$5) | T37: AI-free first | U37: Existing | V37: TypeScript Track!12 | W37: S016 | X37: 3 | Y37: TypeScript Core | AC37: W3 Review: W4 + W21–24 | AD37: =IF(G37="Done",IF(H37="","Add evidence",IF(R37="","Add completion date",IF(D37="Mock",IF(OR(Z37="",AA37="",AB37="",AB37="Not Attempted"),"Record mock results","Complete"),"Complete"))),"") | AE37: =C37&"|"&COUNTIFS($C$6:C37,C37) -> TypeScript & UI|8
A38: B03 | B38: 3 | C38: Projects | D38: Build | E38: Generic Java service + typed DTO transformations | F38: P1 | G38: Not started | J38: =IF('Weekly Review'!$C$4="","",'Weekly Review'!$C$4+(X38-1)*7+6) -> 46314 | K38: Core | L38: 2 | M38: 0 | N38: 0 | O38: Demonstrate the working output, relevant tests, and one design trade-off. | P38: CS/SQL: ACID + normalization + SQL aggregates Design: Schema, keys, constraints and relationships AI practice: AI-free first; use AI only for critique Generic Java service + typed DTO transformations Add keys, relationships, uniqueness and validation constraints Use AI only as a critic; keep implementation independent | Q38: B02 | S38: =IF(R38="","",R38+'Weekly Review'!$C$5) | T38: AI-free first | U38: Merged | V38: 24-Week Plan!7 Weekly Task Navigator!7 | X38: 3 | Y38: Dual Foundations | AD38: =IF(G38="Done",IF(H38="","Add evidence",IF(R38="","Add completion date",IF(D38="Mock",IF(OR(Z38="",AA38="",AB38="",AB38="Not Attempted"),"Record mock results","Complete"),"Complete"))),"") | AE38: =C38&"|"&COUNTIFS($C$6:C38,C38) -> Projects|3
A39: DS03 | B39: 3 | C39: DSA | D39: Practice | E39: Solve 7 new DSA problems and revisit errors | F39: P0 | G39: Not started | J39: =IF('Weekly Review'!$C$4="","",'Weekly Review'!$C$4+(X39-1)*7+6) -> 46314 | K39: Core | L39: 3 | M39: 0 | N39: 0 | O39: Record 7 distinct new problem IDs, explain complexity, and retry one earlier mistake without hints. | P39: Sliding window (bank target 9) Prefix sum (bank target 6) Use Practice Bank for topic totals. Do not count repeat solutions as new problems. | S39: =IF(R39="","",R39+'Weekly Review'!$C$5) | T39: AI-free first | U39: Revised schedule | V39: 24-Week Plan!D7 Weekly Task Navigator!E7 | X39: 3 | Y39: Weekly problem set | AD39: =IF(G39="Done",IF(H39="","Add evidence",IF(R39="","Add completion date",IF(D39="Mock",IF(OR(Z39="",AA39="",AB39="",AB39="Not Attempted"),"Record mock results","Complete"),"Complete"))),"") | AE39: =C39&"|"&COUNTIFS($C$6:C39,C39) -> DSA|3
A40: M03 | B40: 3 | C40: Mock interviews | D40: Mock | E40: Sliding window/prefix + generics + SQL | F40: P0 | G40: Not started | J40: =IF('Weekly Review'!$C$4="","",'Weekly Review'!$C$4+(X40-1)*7+6) -> 46314 | K40: Core | L40: 1 | M40: 0 | N40: 0 | O40: Complete the timed round. Record technical and communication scores, result, evidence, and one correction before the next mock. | S40: =IF(R40="","",R40+'Weekly Review'!$C$5) | T40: AI-Free | U40: Existing | V40: Mock Interviews!7 | X40: 3 | Y40: Coding + SQL | AB40: Not Attempted | AD40: =IF(G40="Done",IF(H40="","Add evidence",IF(R40="","Add completion date",IF(D40="Mock",IF(OR(Z40="",AA40="",AB40="",AB40="Not Attempted"),"Record mock results","Complete"),"Complete"))),"") | AE40: =C40&"|"&COUNTIFS($C$6:C40,C40) -> Mock interviews|3
A41: RV03 | B41: 3 | C41: Review | D41: Review | E41: Review evidence, questions and next-week capacity | F41: P1 | G41: Not started | I41: Record weakest concept and the next practice date. | J41: =IF('Weekly Review'!$C$4="","",'Weekly Review'!$C$4+(X41-1)*7+6) -> 46314 | K41: Core | L41: 0.5 | M41: 0 | N41: 0 | O41: Revisit due topics, practice the questions introduced this week, capture mock feedback, and choose the next three priorities. Update Weekly Review outcome and adjustment. | S41: =IF(R41="","",R41+'Weekly Review'!$C$5) | T41: AI-free first | U41: New gap task | X41: 3 | Y41: Weekly review | AD41: =IF(G41="Done",IF(H41="","Add evidence",IF(R41="","Add completion date",IF(D41="Mock",IF(OR(Z41="",AA41="",AB41="",AB41="Not Attempted"),"Record mock results","Complete"),"Complete"))),"") | AE41: =C41&"|"&COUNTIFS($C$6:C41,C41) -> Review|4
A42: CS15 | B42: 4 | C42: CS & SQL | D42: Learn | E42: Process vs thread | F42: P1 | G42: Not started | J42: =IF('Weekly Review'!$C$4="","",'Weekly Review'!$C$4+(X42-1)*7+6) -> 46321 | K42: Core | L42: 0.75 | M42: 0 | N42: 0 | O42: Address space, scheduling, shared state Process/thread, memory, scheduling, file/system basics | P42: Interview: Process vs thread? | S42: =IF(R42="","",R42+'Weekly Review'!$C$5) | T42: AI-free first | U42: Merged | V42: CS Fundamentals!15 Master Roadmap!50 | W42: S019 | X42: 4 | Y42: OS | AC42: W4 Review: W4 + W21–24 | AD42: =IF(G42="Done",IF(H42="","Add evidence",IF(R42="","Add completion date",IF(D42="Mock",IF(OR(Z42="",AA42="",AB42="",AB42="Not Attempted"),"Record mock results","Complete"),"Complete"))),"") | AE42: =C42&"|"&COUNTIFS($C$6:C42,C42) -> CS & SQL|5
A43: JA11 | B43: 4 | C43: Java & Spring | D43: Learn | E43: Streams/lambdas | F43: P1 | G43: Not started | J43: =IF('Weekly Review'!$C$4="","",'Weekly Review'!$C$4+(X43-1)*7+6) -> 46321 | K43: Core | L43: 0.75 | M43: 0 | N43: 0 | O43: map/filter/reduce/grouping, collectors, readability trade-offs Transform/filter/group safely; know when imperative code is clearer | P43: commerce aggregation drills Interview: stream vs loop? Solve collection transformations two ways | Q43: G02 | S43: =IF(R43="","",R43+'Weekly Review'!$C$5) | T43: AI-free first | U43: Merged | V43: Java + Spring Boot!11 Master Roadmap!83 | W43: S001 | X43: 4 | Y43: Modern Java | AC43: W4 Review: W4 + W21–24 | AD43: =IF(G43="Done",IF(H43="","Add evidence",IF(R43="","Add completion date",IF(D43="Mock",IF(OR(Z43="",AA43="",AB43="",AB43="Not Attempted"),"Record mock results","Complete"),"Complete"))),"") | AE43: =C43&"|"&COUNTIFS($C$6:C43,C43) -> Java & Spring|7
A44: JA12 | B44: 4 | C44: Java & Spring | D44: Learn | E44: Optional | F44: P2 | G44: Not started | J44: =IF('Weekly Review'!$C$4="","",'Weekly Review'!$C$4+(X44-1)*7+6) -> 46321 | K44: Core | L44: 0.75 | M44: 0 | N44: 0 | O44: safe absence modeling; avoid misuse | P44: repository/service examples Interview: when should Optional not be a field/parameter? | Q44: G02 | S44: =IF(R44="","",R44+'Weekly Review'!$C$5) | T44: AI-free first | U44: Existing | V44: Java + Spring Boot!12 | W44: S001 | X44: 4 | Y44: Modern Java | AC44: W4 Review: W4 + W21–24 | AD44: =IF(G44="Done",IF(H44="","Add evidence",IF(R44="","Add completion date",IF(D44="Mock",IF(OR(Z44="",AA44="",AB44="",AB44="Not Attempted"),"Record mock results","Complete"),"Complete"))),"") | AE44: =C44&"|"&COUNTIFS($C$6:C44,C44) -> Java & Spring|8
A45: JA13 | B45: 4 | C45: Java & Spring | D45: Learn | E45: Records / sealed classes | F45: P1 | G45: Not started | J45: =IF('Weekly Review'!$C$4="","",'Weekly Review'!$C$4+(X45-1)*7+6) -> 46321 | K45: Core | L45: 0.75 | M45: 0 | N45: 0 | O45: concise immutable carriers; constrained hierarchies records, sealed classes, pattern matching concepts, switch expressions | P45: DTO/value object refactor Interview: record vs class? Use records for DTO/value objects | Q45: G02 | S45: =IF(R45="","",R45+'Weekly Review'!$C$5) | T45: AI-free first | U45: Merged | V45: Java + Spring Boot!13 Master Roadmap!84 | W45: S001 | X45: 4 | Y45: Modern Java | AC45: W4 Review: W4 + W21–24 | AD45: =IF(G45="Done",IF(H45="","Add evidence",IF(R45="","Add completion date",IF(D45="Mock",IF(OR(Z45="",AA45="",AB45="",AB45="Not Attempted"),"Record mock results","Complete"),"Complete"))),"") | AE45: =C45&"|"&COUNTIFS($C$6:C45,C45) -> Java & Spring|9
A46: JA16 | B46: 4 | C46: Java & Spring | D46: Learn | E46: Memory / GC basics | F46: P1 | G46: Not started | J46: =IF('Weekly Review'!$C$4="","",'Weekly Review'!$C$4+(X46-1)*7+6) -> 46321 | K46: Core | L46: 0.75 | M46: 0 | N46: 0 | O46: heap/stack, references, GC, memory leak patterns Stack/heap, references, garbage collection concept Stack/heap concepts, references, mutation, GC heap/stack, GC concept, class loading, profiling mindset | P46: heap/GC explanation notes Interview: how can Java still leak memory? Interview: What causes a memory leak? Explain memory leak scenarios | Q46: G02 | S46: =IF(R46="","",R46+'Weekly Review'!$C$5) | T46: AI-free first | U46: Merged | V46: Java + Spring Boot!16 CS Fundamentals!17 Master Roadmap!53 Master Roadmap!86 | W46: S001 S019 | X46: 4 | Y46: JVM | AC46: W4 Review: W4 + W21–24 | AD46: =IF(G46="Done",IF(H46="","Add evidence",IF(R46="","Add completion date",IF(D46="Mock",IF(OR(Z46="",AA46="",AB46="",AB46="Not Attempted"),"Record mock results","Complete"),"Complete"))),"") | AE46: =C46&"|"&COUNTIFS($C$6:C46,C46) -> Java & Spring|10
A47: TS07 | B47: 4 | C47: TypeScript & UI | D47: Learn | E47: Event loop | F47: P0 | G47: Not started | J47: =IF('Weekly Review'!$C$4="","",'Weekly Review'!$C$4+(X47-1)*7+6) -> 46321 | K47: Core | L47: 0.75 | M47: 0 | N47: 0 | O47: call stack, microtasks, timers, promises closures, prototypes, event loop, promises, modules, errors | P47: 10 async ordering drills Interview: predict async execution order Explain async execution order and failure propagation Async/event-loop drills Needed beneath TypeScript | Q47: G02 | S47: =IF(R47="","",R47+'Weekly Review'!$C$5) | T47: AI-free first | U47: Merged | V47: TypeScript Track!7 Full-Stack Stack!7 | W47: S014 S017 | X47: 4 | Y47: JavaScript Core | AC47: W4 Review: W4 + W21–24 | AD47: =IF(G47="Done",IF(H47="","Add evidence",IF(R47="","Add completion date",IF(D47="Mock",IF(OR(Z47="",AA47="",AB47="",AB47="Not Attempted"),"Record mock results","Complete"),"Complete"))),"") | AE47: =C47&"|"&COUNTIFS($C$6:C47,C47) -> TypeScript & UI|9
A48: TS13 | B48: 4 | C48: TypeScript & UI | D48: Learn | E48: Modules / ESM | F48: P1 | G48: Not started | J48: =IF('Weekly Review'!$C$4="","",'Weekly Review'!$C$4+(X48-1)*7+6) -> 46321 | K48: Core | L48: 0.75 | M48: 0 | N48: 0 | O48: imports/exports, module resolution, package boundaries | P48: modern module setup Interview: ESM vs CommonJS? | Q48: G02 | S48: =IF(R48="","",R48+'Weekly Review'!$C$5) | T48: AI-free first | U48: Existing | V48: TypeScript Track!13 | W48: S015 | X48: 4 | Y48: TypeScript Core | AC48: W4 Review: W4 + W21–24 | AD48: =IF(G48="Done",IF(H48="","Add evidence",IF(R48="","Add completion date",IF(D48="Mock",IF(OR(Z48="",AA48="",AB48="",AB48="Not Attempted"),"Record mock results","Complete"),"Complete"))),"") | AE48: =C48&"|"&COUNTIFS($C$6:C48,C48) -> TypeScript & UI|10
A49: TS15 | B49: 4 | C49: TypeScript & UI | D49: Learn | E49: Async/await + errors | F49: P0 | G49: Not started | J49: =IF('Weekly Review'!$C$4="","",'Weekly Review'!$C$4+(X49-1)*7+6) -> 46321 | K49: Core | L49: 0.75 | M49: 0 | N49: 0 | O49: Promise composition, try/catch, cancellation concept, retries | P49: API retry/error lab Interview: Promise.all vs allSettled? | Q49: G02 | S49: =IF(R49="","",R49+'Weekly Review'!$C$5) | T49: AI-free first | U49: Existing | V49: TypeScript Track!15 | W49: S017 | X49: 4 | Y49: Runtime | AC49: W4 Review: W4 + W21–24 | AD49: =IF(G49="Done",IF(H49="","Add evidence",IF(R49="","Add completion date",IF(D49="Mock",IF(OR(Z49="",AA49="",AB49="",AB49="Not Attempted"),"Record mock results","Complete"),"Complete"))),"") | AE49: =C49&"|"&COUNTIFS($C$6:C49,C49) -> TypeScript & UI|11
A50: B04 | B50: 4 | C50: Projects | D50: Build | E50: Java aggregation kata + 10 JS async-order drills | F50: P1 | G50: Not started | J50: =IF('Weekly Review'!$C$4="","",'Weekly Review'!$C$4+(X50-1)*7+6) -> 46321 | K50: Core | L50: 2 | M50: 0 | N50: 0 | O50: Demonstrate the working output, relevant tests, and one design trade-off. | P50: CS/SQL: Process vs thread + memory + DNS/HTTP basics Design: Foundation design review AI practice: AI-free mixed assessment Java aggregation kata + 10 JS async-order drills 10-minute foundation design review: requirements to API to schema Run one fully AI-free mixed assessment | Q50: B03 | S50: =IF(R50="","",R50+'Weekly Review'!$C$5) | T50: AI-free first | U50: Merged | V50: 24-Week Plan!8 Weekly Task Navigator!8 | X50: 4 | Y50: Dual Foundations | AD50: =IF(G50="Done",IF(H50="","Add evidence",IF(R50="","Add completion date",IF(D50="Mock",IF(OR(Z50="",AA50="",AB50="",AB50="Not Attempted"),"Record mock results","Complete"),"Complete"))),"") | AE50: =C50&"|"&COUNTIFS($C$6:C50,C50) -> Projects|4
A51: DS04 | B51: 4 | C51: DSA | D51: Practice | E51: Solve 7 new DSA problems and revisit errors | F51: P0 | G51: Not started | J51: =IF('Weekly Review'!$C$4="","",'Weekly Review'!$C$4+(X51-1)*7+6) -> 46321 | K51: Core | L51: 3 | M51: 0 | N51: 0 | O51: Record 7 distinct new problem IDs, explain complexity, and retry one earlier mistake without hints. | P51: Binary search (bank target 8) Stack (bank target 7) Queue / deque (bank target 5) Use Practice Bank for topic totals. Do not count repeat solutions as new problems. | S51: =IF(R51="","",R51+'Weekly Review'!$C$5) | T51: AI-free first | U51: Revised schedule | V51: 24-Week Plan!D8 Weekly Task Navigator!E8 | X51: 4 | Y51: Weekly problem set | AD51: =IF(G51="Done",IF(H51="","Add evidence",IF(R51="","Add completion date",IF(D51="Mock",IF(OR(Z51="",AA51="",AB51="",AB51="Not Attempted"),"Record mock results","Complete"),"Complete"))),"") | AE51: =C51&"|"&COUNTIFS($C$6:C51,C51) -> DSA|4
A52: G04 | B52: 4 | C52: Career | D52: Career | E52: Draft a resume and verify portfolio links | F52: P1 | G52: Not started | J52: =IF('Weekly Review'!$C$4="","",'Weekly Review'!$C$4+(X52-1)*7+6) -> 46321 | K52: Core | L52: 1 | M52: 0 | N52: 0 | O52: Write truthful project bullets tied to your contribution and evidence. Test links and have one person review the draft. | Q52: G03 | S52: =IF(R52="","",R52+'Weekly Review'!$C$5) | T52: AI-free first | U52: New gap task | X52: 4 | Y52: Gap closure | AD52: =IF(G52="Done",IF(H52="","Add evidence",IF(R52="","Add completion date",IF(D52="Mock",IF(OR(Z52="",AA52="",AB52="",AB52="Not Attempted"),"Record mock results","Complete"),"Complete"))),"") | AE52: =C52&"|"&COUNTIFS($C$6:C52,C52) -> Career|2
A53: M04 | B53: 4 | C53: Mock interviews | D53: Mock | E53: Binary search/stack + event loop + CS basics | F53: P0 | G53: Not started | J53: =IF('Weekly Review'!$C$4="","",'Weekly Review'!$C$4+(X53-1)*7+6) -> 46321 | K53: Core | L53: 1 | M53: 0 | N53: 0 | O53: Complete the timed round. Record technical and communication scores, result, evidence, and one correction before the next mock. | S53: =IF(R53="","",R53+'Weekly Review'!$C$5) | T53: AI-Free | U53: Existing | V53: Mock Interviews!8 | X53: 4 | Y53: Mixed Fundamentals | AB53: Not Attempted | AD53: =IF(G53="Done",IF(H53="","Add evidence",IF(R53="","Add completion date",IF(D53="Mock",IF(OR(Z53="",AA53="",AB53="",AB53="Not Attempted"),"Record mock results","Complete"),"Complete"))),"") | AE53: =C53&"|"&COUNTIFS($C$6:C53,C53) -> Mock interviews|4
A54: RV04 | B54: 4 | C54: Review | D54: Review | E54: Review evidence, questions and next-week capacity | F54: P1 | G54: Not started | I54: Record weakest concept and the next practice date. | J54: =IF('Weekly Review'!$C$4="","",'Weekly Review'!$C$4+(X54-1)*7+6) -> 46321 | K54: Core | L54: 0.5 | M54: 0 | N54: 0 | O54: Revisit due topics, practice the questions introduced this week, capture mock feedback, and choose the next three priorities. Update Weekly Review outcome and adjustment. | S54: =IF(R54="","",R54+'Weekly Review'!$C$5) | T54: AI-free first | U54: New gap task | X54: 4 | Y54: Weekly review | AD54: =IF(G54="Done",IF(H54="","Add evidence",IF(R54="","Add completion date",IF(D54="Mock",IF(OR(Z54="",AA54="",AB54="",AB54="Not Attempted"),"Record mock results","Complete"),"Complete"))),"") | AE54: =C54&"|"&COUNTIFS($C$6:C54,C54) -> Review|5
A55: AI05 | B55: 5 | C55: AI Engineering | D55: Learn | E55: AI limitations, context and token budgets | F55: P1 | G55: Not started | J55: =IF('Weekly Review'!$C$4="","",'Weekly Review'!$C$4+(X55-1)*7+6) -> 46328 | K55: Core | L55: 0.75 | M55: 0 | N55: 0 | O55: Context limits, cost/latency, truncation Hallucination, stale assumptions, non-determinism Models, tokens, context, latency/cost, failure handling | P55: Estimate context needed for repo task Failure to test: Missing/irrelevant context Find unsupported claim/code assumption Failure to test: Blind trust | S55: =IF(R55="","",R55+'Weekly Review'!$C$5) | T55: AI-free first | U55: Merged | V55: AI Engineering!5 AI Engineering!6 Master Roadmap!68 | W55: S004 S023 | X55: 5 | Y55: Fundamentals | AC55: W5 Review: W8 + W17–24 W8 | AD55: =IF(G55="Done",IF(H55="","Add evidence",IF(R55="","Add completion date",IF(D55="Mock",IF(OR(Z55="",AA55="",AB55="",AB55="Not Attempted"),"Record mock results","Complete"),"Complete"))),"") | AE55: =C55&"|"&COUNTIFS($C$6:C55,C55) -> AI Engineering|2
A56: CS18 | B56: 5 | C56: CS & SQL | D56: Learn | E56: TCP vs UDP | F56: P1 | G56: Not started | J56: =IF('Weekly Review'!$C$4="","",'Weekly Review'!$C$4+(X56-1)*7+6) -> 46328 | K56: Core | L56: 0.75 | M56: 0 | N56: 0 | O56: Reliability/order vs lower overhead TCP/UDP, DNS, HTTP/HTTPS, latency | P56: Interview: When choose UDP? | S56: =IF(R56="","",R56+'Weekly Review'!$C$5) | T56: AI-free first | U56: Merged | V56: CS Fundamentals!18 Master Roadmap!51 | W56: S019 | X56: 5 | Y56: Networking | AC56: W5 Review: W8 + W17–24 | AD56: =IF(G56="Done",IF(H56="","Add evidence",IF(R56="","Add completion date",IF(D56="Mock",IF(OR(Z56="",AA56="",AB56="",AB56="Not Attempted"),"Record mock results","Complete"),"Complete"))),"") | AE56: =C56&"|"&COUNTIFS($C$6:C56,C56) -> CS & SQL|6
A57: CS19 | B57: 5 | C57: CS & SQL | D57: Learn | E57: DNS | F57: P1 | G57: Not started | J57: =IF('Weekly Review'!$C$4="","",'Weekly Review'!$C$4+(X57-1)*7+6) -> 46328 | K57: Core | L57: 0.75 | M57: 0 | N57: 0 | O57: Resolve name to IP, caching concept | P57: Interview: What happens after entering a URL? | S57: =IF(R57="","",R57+'Weekly Review'!$C$5) | T57: AI-free first | U57: Existing | V57: CS Fundamentals!19 | W57: S019 | X57: 5 | Y57: Networking | AC57: W5 Review: W8 + W17–24 | AD57: =IF(G57="Done",IF(H57="","Add evidence",IF(R57="","Add completion date",IF(D57="Mock",IF(OR(Z57="",AA57="",AB57="",AB57="Not Attempted"),"Record mock results","Complete"),"Complete"))),"") | AE57: =C57&"|"&COUNTIFS($C$6:C57,C57) -> CS & SQL|7
A58: CS20 | B58: 5 | C58: CS & SQL | D58: Learn | E58: HTTP | F58: P0 | G58: Not started | J58: =IF('Weekly Review'!$C$4="","",'Weekly Review'!$C$4+(X58-1)*7+6) -> 46328 | K58: Core | L58: 0.75 | M58: 0 | N58: 0 | O58: Methods, status codes, idempotency, headers Methods, headers, cookies, CORS, TLS, caching | P58: Interview: PUT vs PATCH? 401 vs 403? | S58: =IF(R58="","",R58+'Weekly Review'!$C$5) | T58: AI-free first | U58: Merged | V58: CS Fundamentals!20 Master Roadmap!52 | W58: S019 S022 | X58: 5 | Y58: Networking | AC58: W5 Review: W8 + W17–24 | AD58: =IF(G58="Done",IF(H58="","Add evidence",IF(R58="","Add completion date",IF(D58="Mock",IF(OR(Z58="",AA58="",AB58="",AB58="Not Attempted"),"Record mock results","Complete"),"Complete"))),"") | AE58: =C58&"|"&COUNTIFS($C$6:C58,C58) -> CS & SQL|8
A59: JA17 | B59: 5 | C59: Java & Spring | D59: Learn | E59: IoC / DI | F59: P0 | G59: Not started | J59: =IF('Weekly Review'!$C$4="","",'Weekly Review'!$C$4+(X59-1)*7+6) -> 46328 | K59: Core | L59: 0.75 | M59: 0 | N59: 0 | O59: beans, constructor injection, component scanning, configuration IoC/DI, beans, configuration, AOP concept, validation Explain beans, constructor injection, configuration and testability | P59: 3-layer service without field injection Interview: why constructor injection? Explain constructor injection and bean lifecycle at high level Small DI/service module Foundation for Spring Boot Build small layered service | Q59: JA06 | S59: =IF(R59="","",R59+'Weekly Review'!$C$5) | T59: AI-free first | U59: Merged | V59: Java + Spring Boot!17 Full-Stack Stack!10 Master Roadmap!87 | W59: S002 | X59: 5 | Y59: Spring Core | AC59: W5 Review: W8 + W17–24 | AD59: =IF(G59="Done",IF(H59="","Add evidence",IF(R59="","Add completion date",IF(D59="Mock",IF(OR(Z59="",AA59="",AB59="",AB59="Not Attempted"),"Record mock results","Complete"),"Complete"))),"") | AE59: =C59&"|"&COUNTIFS($C$6:C59,C59) -> Java & Spring|11
A60: JA18 | B60: 5 | C60: Java & Spring | D60: Learn | E60: Boot fundamentals | F60: P0 | G60: Not started | J60: =IF('Weekly Review'!$C$4="","",'Weekly Review'!$C$4+(X60-1)*7+6) -> 46328 | K60: Core | L60: 0.75 | M60: 0 | N60: 0 | O60: starters, auto-configuration, application startup auto-configuration, starters, profiles, config properties, lifecycle Understand starters, auto-config, profiles, config properties and app startup | P60: new Boot service from scratch Interview: what does auto-configuration do? Create/configure a production-style REST service Commerce REST service Current line supports Java 17–26 Create Boot app from scratch | Q60: JA17 | S60: =IF(R60="","",R60+'Weekly Review'!$C$5) | T60: AI-free first | U60: Merged | V60: Java + Spring Boot!18 Full-Stack Stack!11 Master Roadmap!88 | W60: S003 S004 | X60: 5 | Y60: Spring Boot | AC60: W5 Review: W8 + W17–24 | AD60: =IF(G60="Done",IF(H60="","Add evidence",IF(R60="","Add completion date",IF(D60="Mock",IF(OR(Z60="",AA60="",AB60="",AB60="Not Attempted"),"Record mock results","Complete"),"Complete"))),"") | AE60: =C60&"|"&COUNTIFS($C$6:C60,C60) -> Java & Spring|12
A61: FE32 | B61: 5 | C61: TypeScript & UI | D61: Learn | E61: HTML/CSS fundamentals | F61: P2 | G61: Not started | J61: =IF('Weekly Review'!$C$4="","",'Weekly Review'!$C$4+(X61-1)*7+6) -> 46328 | K61: Core | L61: 0.75 | M61: 0 | N61: 0 | O61: Semantic HTML, layout, responsive design, forms | S61: =IF(R61="","",R61+'Weekly Review'!$C$5) | T61: AI-free first | U61: Existing | V61: Master Roadmap!32 | W61: S030 | X61: 5 | Y61: Frontend | AC61: W5 Review: W8 + W17–24 | AD61: =IF(G61="Done",IF(H61="","Add evidence",IF(R61="","Add completion date",IF(D61="Mock",IF(OR(Z61="",AA61="",AB61="",AB61="Not Attempted"),"Record mock results","Complete"),"Complete"))),"") | AE61: =C61&"|"&COUNTIFS($C$6:C61,C61) -> TypeScript & UI|12
A62: TS17 | B62: 5 | C62: TypeScript & UI | D62: Learn | E62: Components / props | F62: P0 | G62: Not started | J62: =IF('Weekly Review'!$C$4="","",'Weekly Review'!$C$4+(X62-1)*7+6) -> 46328 | K62: Core | L62: 0.75 | M62: 0 | N62: 0 | O62: typed props, composition, controlled components hooks, state, forms, rendering, effects, memoization basics Components, hooks, state, forms, performance, error boundaries | P62: typed form components Interview: prop drilling vs composition? Fix stale-state / unnecessary rerender bug Typed React CRUD flow Primary UI | Q62: TS08 | S62: =IF(R62="","",R62+'Weekly Review'!$C$5) | T62: AI-free first | U62: Merged | V62: TypeScript Track!17 Full-Stack Stack!8 Master Roadmap!33 | W62: S004 | X62: 5 | Y62: React | AC62: W5 Review: W8 + W17–24 W5–6 | AD62: =IF(G62="Done",IF(H62="","Add evidence",IF(R62="","Add completion date",IF(D62="Mock",IF(OR(Z62="",AA62="",AB62="",AB62="Not Attempted"),"Record mock results","Complete"),"Complete"))),"") | AE62: =C62&"|"&COUNTIFS($C$6:C62,C62) -> TypeScript & UI|13
A63: B05 | B63: 5 | C63: Projects | D63: Build | E63: Create Spring Boot service skeleton + typed Next/React client shell | F63: P1 | G63: Not started | J63: =IF('Weekly Review'!$C$4="","",'Weekly Review'!$C$4+(X63-1)*7+6) -> 46328 | K63: Core | L63: 2 | M63: 0 | N63: 0 | O63: Demonstrate the working output, relevant tests, and one design trade-off. | P63: CS/SQL: TCP/UDP + HTTP request lifecycle Design: Requirements + API + data model AI practice: AI-assisted orientation only; verify generated setup Create Spring Boot service skeleton + typed Next/React client shell Requirements - Clarify a booking service API design - Order API Data model - POS order + inventory Tokens/context - Estimate context needed for repo task Model limitations - Find unsupported claim/code assumption | Q63: B04 | S63: =IF(R63="","",R63+'Weekly Review'!$C$5) | T63: AI-free first | U63: Merged | V63: 24-Week Plan!9 Weekly Task Navigator!9 | X63: 5 | Y63: API Core | AD63: =IF(G63="Done",IF(H63="","Add evidence",IF(R63="","Add completion date",IF(D63="Mock",IF(OR(Z63="",AA63="",AB63="",AB63="Not Attempted"),"Record mock results","Complete"),"Complete"))),"") | AE63: =C63&"|"&COUNTIFS($C$6:C63,C63) -> Projects|5
A64: DS05 | B64: 5 | C64: DSA | D64: Practice | E64: Solve 7 new DSA problems and revisit errors | F64: P0 | G64: Not started | J64: =IF('Weekly Review'!$C$4="","",'Weekly Review'!$C$4+(X64-1)*7+6) -> 46328 | K64: Core | L64: 3 | M64: 0 | N64: 0 | O64: Record 7 distinct new problem IDs, explain complexity, and retry one earlier mistake without hints. | P64: Linked list (bank target 7) Trees (bank target 12) Use Practice Bank for topic totals. Do not count repeat solutions as new problems. | S64: =IF(R64="","",R64+'Weekly Review'!$C$5) | T64: AI-free first | U64: Revised schedule | V64: 24-Week Plan!D9 Weekly Task Navigator!E9 | X64: 5 | Y64: Weekly problem set | AD64: =IF(G64="Done",IF(H64="","Add evidence",IF(R64="","Add completion date",IF(D64="Mock",IF(OR(Z64="",AA64="",AB64="",AB64="Not Attempted"),"Record mock results","Complete"),"Complete"))),"") | AE64: =C64&"|"&COUNTIFS($C$6:C64,C64) -> DSA|5
A65: RW05 | B65: 5 | C65: Engineering | D65: Practice | E65: Unfamiliar codebase orientation | F65: P0 | G65: Not started | J65: =IF('Weekly Review'!$C$4="","",'Weekly Review'!$C$4+(X65-1)*7+6) -> 46328 | K65: Core | L65: 1 | M65: 0 | N65: 0 | O65: Accurate mental model; identify entrypoints and tests | P65: Open a medium repo and find request to service to DB path in 10 minutes Practice mode: AI-free Yes, AI-assisted Yes | S65: =IF(R65="","",R65+'Weekly Review'!$C$5) | T65: AI-free first | U65: Existing | V65: Real-World Eng!5 | X65: 5 | Y65: Unfamiliar codebase orientation | AC65: W5 + W21–24 Review: W8 + W17–24 | AD65: =IF(G65="Done",IF(H65="","Add evidence",IF(R65="","Add completion date",IF(D65="Mock",IF(OR(Z65="",AA65="",AB65="",AB65="Not Attempted"),"Record mock results","Complete"),"Complete"))),"") | AE65: =C65&"|"&COUNTIFS($C$6:C65,C65) -> Engineering|4
A66: SD05 | B66: 5 | C66: System design | D66: Practice | E66: Requirements | F66: P0 | G66: Not started | J66: =IF('Weekly Review'!$C$4="","",'Weekly Review'!$C$4+(X66-1)*7+6) -> 46328 | K66: Core | L66: 1 | M66: 0 | N66: 0 | O66: Functional/non-functional, constraints, scale Functional/non-functional requirements and constraints | P66: Design: Clarify a booking service Trade-off: scope vs time | S66: =IF(R66="","",R66+'Weekly Review'!$C$5) | T66: AI-free first | U66: Merged | V66: System Design!5 Master Roadmap!54 | W66: S028 S022 | X66: 5 | Y66: Requirements | AC66: W5 + W17–24 Review: W8 + W17–24 W5 | AD66: =IF(G66="Done",IF(H66="","Add evidence",IF(R66="","Add completion date",IF(D66="Mock",IF(OR(Z66="",AA66="",AB66="",AB66="Not Attempted"),"Record mock results","Complete"),"Complete"))),"") | AE66: =C66&"|"&COUNTIFS($C$6:C66,C66) -> System design|1
A67: SD07 | B67: 5 | C67: System design | D67: Practice | E67: Data model | F67: P0 | G67: Not started | J67: =IF('Weekly Review'!$C$4="","",'Weekly Review'!$C$4+(X67-1)*7+6) -> 46328 | K67: Core | L67: 1 | M67: 0 | N67: 0 | O67: entities, keys, constraints Endpoints, entities, invariants, constraints | P67: Design: POS order + inventory Trade-off: normalization vs query speed | S67: =IF(R67="","",R67+'Weekly Review'!$C$5) | T67: AI-free first | U67: Merged | V67: System Design!7 Master Roadmap!55 | W67: S028 S019 | X67: 5 | Y67: Data model | AC67: W5 + W17–24 Review: W8 + W17–24 W5 | AD67: =IF(G67="Done",IF(H67="","Add evidence",IF(R67="","Add completion date",IF(D67="Mock",IF(OR(Z67="",AA67="",AB67="",AB67="Not Attempted"),"Record mock results","Complete"),"Complete"))),"") | AE67: =C67&"|"&COUNTIFS($C$6:C67,C67) -> System design|2
A68: M05 | B68: 5 | C68: Mock interviews | D68: Mock | E68: Spring DI/Boot + linked list/tree | F68: P0 | G68: Not started | J68: =IF('Weekly Review'!$C$4="","",'Weekly Review'!$C$4+(X68-1)*7+6) -> 46328 | K68: Core | L68: 1 | M68: 0 | N68: 0 | O68: Complete the timed round. Record technical and communication scores, result, evidence, and one correction before the next mock. | S68: =IF(R68="","",R68+'Weekly Review'!$C$5) | T68: AI-Free | U68: Existing | V68: Mock Interviews!9 | X68: 5 | Y68: Backend/API | AB68: Not Attempted | AD68: =IF(G68="Done",IF(H68="","Add evidence",IF(R68="","Add completion date",IF(D68="Mock",IF(OR(Z68="",AA68="",AB68="",AB68="Not Attempted"),"Record mock results","Complete"),"Complete"))),"") | AE68: =C68&"|"&COUNTIFS($C$6:C68,C68) -> Mock interviews|5
A69: RV05 | B69: 5 | C69: Review | D69: Review | E69: Review evidence, questions and next-week capacity | F69: P1 | G69: Not started | I69: Record weakest concept and the next practice date. | J69: =IF('Weekly Review'!$C$4="","",'Weekly Review'!$C$4+(X69-1)*7+6) -> 46328 | K69: Core | L69: 0.5 | M69: 0 | N69: 0 | O69: Revisit due topics, practice the questions introduced this week, capture mock feedback, and choose the next three priorities. Update Weekly Review outcome and adjustment. | S69: =IF(R69="","",R69+'Weekly Review'!$C$5) | T69: AI-free first | U69: New gap task | X69: 5 | Y69: Weekly review | AD69: =IF(G69="Done",IF(H69="","Add evidence",IF(R69="","Add completion date",IF(D69="Mock",IF(OR(Z69="",AA69="",AB69="",AB69="Not Attempted"),"Record mock results","Complete"),"Complete"))),"") | AE69: =C69&"|"&COUNTIFS($C$6:C69,C69) -> Review|6
A70: CS21 | B70: 6 | C70: CS & SQL | D70: Learn | E70: HTTPS/TLS | F70: P1 | G70: Not started | J70: =IF('Weekly Review'!$C$4="","",'Weekly Review'!$C$4+(X70-1)*7+6) -> 46335 | K70: Core | L70: 0.75 | M70: 0 | N70: 0 | O70: Encryption/authentication concept, certificates | P70: Interview: How does HTTPS protect traffic? | S70: =IF(R70="","",R70+'Weekly Review'!$C$5) | T70: AI-free first | U70: Existing | V70: CS Fundamentals!21 | W70: S022 | X70: 6 | Y70: Networking | AC70: W6 Review: W8 + W17–24 | AD70: =IF(G70="Done",IF(H70="","Add evidence",IF(R70="","Add completion date",IF(D70="Mock",IF(OR(Z70="",AA70="",AB70="",AB70="Not Attempted"),"Record mock results","Complete"),"Complete"))),"") | AE70: =C70&"|"&COUNTIFS($C$6:C70,C70) -> CS & SQL|9
A71: JA19 | B71: 6 | C71: Java & Spring | D71: Learn | E71: Configuration / profiles | F71: P1 | G71: Not started | J71: =IF('Weekly Review'!$C$4="","",'Weekly Review'!$C$4+(X71-1)*7+6) -> 46335 | K71: Core | L71: 0.75 | M71: 0 | N71: 0 | O71: application properties/yaml, env vars, profiles, config properties | P71: profile-specific app config Interview: how manage dev/test/prod config? | Q71: G02 | S71: =IF(R71="","",R71+'Weekly Review'!$C$5) | T71: AI-free first | U71: Existing | V71: Java + Spring Boot!19 | W71: S003 | X71: 6 | Y71: Spring Boot | AC71: W6 Review: W8 + W17–24 | AD71: =IF(G71="Done",IF(H71="","Add evidence",IF(R71="","Add completion date",IF(D71="Mock",IF(OR(Z71="",AA71="",AB71="",AB71="Not Attempted"),"Record mock results","Complete"),"Complete"))),"") | AE71: =C71&"|"&COUNTIFS($C$6:C71,C71) -> Java & Spring|13
A72: JA20 | B72: 6 | C72: Java & Spring | D72: Learn | E72: Spring MVC | F72: P0 | G72: Not started | J72: =IF('Weekly Review'!$C$4="","",'Weekly Review'!$C$4+(X72-1)*7+6) -> 46335 | K72: Core | L72: 0.75 | M72: 0 | N72: 0 | O72: controllers, request mapping, DTOs, serialization controllers, DTOs, status codes, pagination, exception handling DTOs, validation, status codes, pagination, exception handling | P72: CRUD/order endpoints Interview: controller vs service responsibility? Design and implement booking/order API REST API with OpenAPI contract Core backend interview area Build order/booking endpoints | Q72: JA18 | S72: =IF(R72="","",R72+'Weekly Review'!$C$5) | T72: AI-free first | U72: Merged | V72: Java + Spring Boot!20 Full-Stack Stack!12 Master Roadmap!89 | W72: S002 | X72: 6 | Y72: Web/API | AC72: W6 Review: W8 + W17–24 W6–7 | AD72: =IF(G72="Done",IF(H72="","Add evidence",IF(R72="","Add completion date",IF(D72="Mock",IF(OR(Z72="",AA72="",AB72="",AB72="Not Attempted"),"Record mock results","Complete"),"Complete"))),"") | AE72: =C72&"|"&COUNTIFS($C$6:C72,C72) -> Java & Spring|14
A73: TS18 | B73: 6 | C73: TypeScript & UI | D73: Learn | E73: State / hooks | F73: P0 | G73: Not started | J73: =IF('Weekly Review'!$C$4="","",'Weekly Review'!$C$4+(X73-1)*7+6) -> 46335 | K73: Core | L73: 0.75 | M73: 0 | N73: 0 | O73: useState/useReducer/useEffect, dependency correctness | P73: fix 5 hook bugs Interview: why stale closure/effect loop? | Q73: G02 | S73: =IF(R73="","",R73+'Weekly Review'!$C$5) | T73: AI-free first | U73: Existing | V73: TypeScript Track!18 | W73: S004 | X73: 6 | Y73: React | AC73: W6 Review: W8 + W17–24 | AD73: =IF(G73="Done",IF(H73="","Add evidence",IF(R73="","Add completion date",IF(D73="Mock",IF(OR(Z73="",AA73="",AB73="",AB73="Not Attempted"),"Record mock results","Complete"),"Complete"))),"") | AE73: =C73&"|"&COUNTIFS($C$6:C73,C73) -> TypeScript & UI|14
A74: TS19 | B74: 6 | C74: TypeScript & UI | D74: Learn | E74: Rendering / performance | F74: P1 | G74: Not started | J74: =IF('Weekly Review'!$C$4="","",'Weekly Review'!$C$4+(X74-1)*7+6) -> 46335 | K74: Core | L74: 0.75 | M74: 0 | N74: 0 | O74: keys, memoization basics, state placement Bundle/loading, caching, rendering, Core Web Vitals concepts | P74: profile rerender issue Interview: when does memo help/hurt? | Q74: G02 | S74: =IF(R74="","",R74+'Weekly Review'!$C$5) | T74: AI-free first | U74: Merged | V74: TypeScript Track!19 Master Roadmap!36 | W74: S004 S028 | X74: 6 | Y74: React | AC74: W6 Review: W8 + W17–24 W15 Review: W16 + W17–24 | AD74: =IF(G74="Done",IF(H74="","Add evidence",IF(R74="","Add completion date",IF(D74="Mock",IF(OR(Z74="",AA74="",AB74="",AB74="Not Attempted"),"Record mock results","Complete"),"Complete"))),"") | AE74: =C74&"|"&COUNTIFS($C$6:C74,C74) -> TypeScript & UI|15
A75: TS20 | B75: 6 | C75: TypeScript & UI | D75: Learn | E75: Routing / boundaries | F75: P0 | G75: Not started | J75: =IF('Weekly Review'!$C$4="","",'Weekly Review'!$C$4+(X75-1)*7+6) -> 46335 | K75: Core | L75: 0.75 | M75: 0 | N75: 0 | O75: server/client components concept, routing, data flow routing, server/client boundaries, data fetching, auth/BFF concepts Routing, server/client boundaries, data fetching, auth/BFF | P75: Next frontend for Boot API Interview: where should data fetching/auth live? Trace a request from page to Spring Boot API Next.js + Spring Boot integration Use as frontend/BFF when appropriate | Q75: TS17 | S75: =IF(R75="","",R75+'Weekly Review'!$C$5) | T75: AI-free first | U75: Merged | V75: TypeScript Track!20 Full-Stack Stack!9 Master Roadmap!34 | W75: S017 S020 | X75: 6 | Y75: Next.js | AC75: W6 Review: W8 + W17–24 W6–7 | AD75: =IF(G75="Done",IF(H75="","Add evidence",IF(R75="","Add completion date",IF(D75="Mock",IF(OR(Z75="",AA75="",AB75="",AB75="Not Attempted"),"Record mock results","Complete"),"Complete"))),"") | AE75: =C75&"|"&COUNTIFS($C$6:C75,C75) -> TypeScript & UI|16
A76: B06 | B76: 6 | C76: Projects | D76: Build | E76: Controller/service/DTO flow + typed React form and route | F76: P1 | G76: Not started | J76: =IF('Weekly Review'!$C$4="","",'Weekly Review'!$C$4+(X76-1)*7+6) -> 46335 | K76: Core | L76: 2 | M76: 0 | N76: 0 | O76: Demonstrate the working output, relevant tests, and one design trade-off. | P76: CS/SQL: HTTPS/TLS + browser/server request flow Design: Pagination + API error model AI practice: Small AI-assisted task with compile/typecheck review Controller/service/DTO flow + typed React form and route API errors + pagination mini-design Small assisted task: compile/typecheck and explain every change | Q76: B05 | S76: =IF(R76="","",R76+'Weekly Review'!$C$5) | T76: AI-free first | U76: Merged | V76: 24-Week Plan!10 Weekly Task Navigator!10 | X76: 6 | Y76: API Core | AD76: =IF(G76="Done",IF(H76="","Add evidence",IF(R76="","Add completion date",IF(D76="Mock",IF(OR(Z76="",AA76="",AB76="",AB76="Not Attempted"),"Record mock results","Complete"),"Complete"))),"") | AE76: =C76&"|"&COUNTIFS($C$6:C76,C76) -> Projects|6
A77: DS06 | B77: 6 | C77: DSA | D77: Practice | E77: Solve 7 new DSA problems and revisit errors | F77: P0 | G77: Not started | J77: =IF('Weekly Review'!$C$4="","",'Weekly Review'!$C$4+(X77-1)*7+6) -> 46335 | K77: Core | L77: 3 | M77: 0 | N77: 0 | O77: Record 7 distinct new problem IDs, explain complexity, and retry one earlier mistake without hints. | P77: BST (bank target 5) Use Practice Bank for topic totals. Do not count repeat solutions as new problems. | S77: =IF(R77="","",R77+'Weekly Review'!$C$5) | T77: AI-free first | U77: Revised schedule | V77: 24-Week Plan!D10 Weekly Task Navigator!E10 | X77: 6 | Y77: Weekly problem set | AD77: =IF(G77="Done",IF(H77="","Add evidence",IF(R77="","Add completion date",IF(D77="Mock",IF(OR(Z77="",AA77="",AB77="",AB77="Not Attempted"),"Record mock results","Complete"),"Complete"))),"") | AE77: =C77&"|"&COUNTIFS($C$6:C77,C77) -> DSA|6
A78: M06 | B78: 6 | C78: Mock interviews | D78: Mock | E78: Spring MVC + React/Next + trees/BST | F78: P0 | G78: Not started | J78: =IF('Weekly Review'!$C$4="","",'Weekly Review'!$C$4+(X78-1)*7+6) -> 46335 | K78: Core | L78: 1 | M78: 0 | N78: 0 | O78: Complete the timed round. Record technical and communication scores, result, evidence, and one correction before the next mock. | S78: =IF(R78="","",R78+'Weekly Review'!$C$5) | T78: AI-Free | U78: Existing | V78: Mock Interviews!10 | X78: 6 | Y78: Backend + Frontend | AB78: Not Attempted | AD78: =IF(G78="Done",IF(H78="","Add evidence",IF(R78="","Add completion date",IF(D78="Mock",IF(OR(Z78="",AA78="",AB78="",AB78="Not Attempted"),"Record mock results","Complete"),"Complete"))),"") | AE78: =C78&"|"&COUNTIFS($C$6:C78,C78) -> Mock interviews|6
A79: RV06 | B79: 6 | C79: Review | D79: Review | E79: Review evidence, questions and next-week capacity | F79: P1 | G79: Not started | I79: Record weakest concept and the next practice date. | J79: =IF('Weekly Review'!$C$4="","",'Weekly Review'!$C$4+(X79-1)*7+6) -> 46335 | K79: Core | L79: 0.5 | M79: 0 | N79: 0 | O79: Revisit due topics, practice the questions introduced this week, capture mock feedback, and choose the next three priorities. Update Weekly Review outcome and adjustment. | S79: =IF(R79="","",R79+'Weekly Review'!$C$5) | T79: AI-free first | U79: New gap task | X79: 6 | Y79: Weekly review | AD79: =IF(G79="Done",IF(H79="","Add evidence",IF(R79="","Add completion date",IF(D79="Mock",IF(OR(Z79="",AA79="",AB79="",AB79="Not Attempted"),"Record mock results","Complete"),"Complete"))),"") | AE79: =C79&"|"&COUNTIFS($C$6:C79,C79) -> Review|7
A80: CS14 | B80: 7 | C80: CS & SQL | D80: Learn | E80: CTEs/subqueries/window awareness | F80: P1 | G80: Not started | J80: =IF('Weekly Review'!$C$4="","",'Weekly Review'!$C$4+(X80-1)*7+6) -> 46342 | K80: Core | L80: 0.75 | M80: 0 | N80: 0 | O80: Break complex queries into understandable steps | P80: Interview: Latest order per customer? | S80: =IF(R80="","",R80+'Weekly Review'!$C$5) | T80: AI-free first | U80: Existing | V80: CS Fundamentals!14 | W80: S020 | X80: 7 | Y80: SQL | AC80: W7 Review: W8 + W17–24 | AD80: =IF(G80="Done",IF(H80="","Add evidence",IF(R80="","Add completion date",IF(D80="Mock",IF(OR(Z80="",AA80="",AB80="",AB80="Not Attempted"),"Record mock results","Complete"),"Complete"))),"") | AE80: =C80&"|"&COUNTIFS($C$6:C80,C80) -> CS & SQL|10
A81: JA21 | B81: 7 | C81: Java & Spring | D81: Learn | E81: Validation + errors | F81: P0 | G81: Not started | J81: =IF('Weekly Review'!$C$4="","",'Weekly Review'!$C$4+(X81-1)*7+6) -> 46342 | K81: Core | L81: 0.75 | M81: 0 | N81: 0 | O81: Bean Validation, global exception handling, stable error model | P81: validation + error response tests Interview: how validate API input? | Q81: G02 | S81: =IF(R81="","",R81+'Weekly Review'!$C$5) | T81: AI-free first | U81: Existing | V81: Java + Spring Boot!21 | W81: S002 | X81: 7 | Y81: Web/API | AC81: W7 Review: W8 + W17–24 | AD81: =IF(G81="Done",IF(H81="","Add evidence",IF(R81="","Add completion date",IF(D81="Mock",IF(OR(Z81="",AA81="",AB81="",AB81="Not Attempted"),"Record mock results","Complete"),"Complete"))),"") | AE81: =C81&"|"&COUNTIFS($C$6:C81,C81) -> Java & Spring|15
A82: JA22 | B82: 7 | C82: Java & Spring | D82: Learn | E82: REST correctness | F82: P0 | G82: Not started | J82: =IF('Weekly Review'!$C$4="","",'Weekly Review'!$C$4+(X82-1)*7+6) -> 46342 | K82: Core | L82: 0.75 | M82: 0 | N82: 0 | O82: methods, status codes, pagination, idempotency resources, methods, idempotency, errors offset vs cursor Resources, verbs, status codes, pagination, versioning, idempotency | P82: order + booking API Interview: PUT vs PATCH? 201 vs 204? Design: Order API Trade-off: simplicity vs flexibility Design: Large orders list Trade-off: simplicity vs consistency | Q82: G02 | S82: =IF(R82="","",R82+'Weekly Review'!$C$5) | T82: AI-free first | U82: Merged | V82: Java + Spring Boot!22 System Design!6 System Design!11 Master Roadmap!38 | W82: S004 S028 S019 | X82: 7 | Y82: Web/API | AC82: W7 Review: W8 + W17–24 W5 + W17–24 W7 + W17–24 | AD82: =IF(G82="Done",IF(H82="","Add evidence",IF(R82="","Add completion date",IF(D82="Mock",IF(OR(Z82="",AA82="",AB82="",AB82="Not Attempted"),"Record mock results","Complete"),"Complete"))),"") | AE82: =C82&"|"&COUNTIFS($C$6:C82,C82) -> Java & Spring|16
A83: TS16 | B83: 7 | C83: TypeScript & UI | D83: Learn | E83: Runtime validation | F83: P0 | G83: Not started | J83: =IF('Weekly Review'!$C$4="","",'Weekly Review'!$C$4+(X83-1)*7+6) -> 46342 | K83: Core | L83: 0.75 | M83: 0 | N83: 0 | O83: types disappear at runtime; validate external JSON Jakarta Bean Validation + DTO validation; Zod/runtime validation in TS Schema validation, typed DTOs, backward compatibility | P83: Zod schema for Spring API DTO Interview: why TS types do not secure API input? Reject malformed input consistently across both stacks Shared API contract examples Know compile-time vs runtime validation | Q83: G02 | S83: =IF(R83="","",R83+'Weekly Review'!$C$5) | T83: AI-free first | U83: Merged | V83: TypeScript Track!16 Full-Stack Stack!14 Master Roadmap!39 | W83: S016 S002 S021 | X83: 7 | Y83: Runtime | AC83: W7 Review: W8 + W17–24 | AD83: =IF(G83="Done",IF(H83="","Add evidence",IF(R83="","Add completion date",IF(D83="Mock",IF(OR(Z83="",AA83="",AB83="",AB83="Not Attempted"),"Record mock results","Complete"),"Complete"))),"") | AE83: =C83&"|"&COUNTIFS($C$6:C83,C83) -> TypeScript & UI|17
A84: TS21 | B84: 7 | C84: TypeScript & UI | D84: Learn | E84: API integration | F84: P0 | G84: Not started | J84: =IF('Weekly Review'!$C$4="","",'Weekly Review'!$C$4+(X84-1)*7+6) -> 46342 | K84: Core | L84: 0.75 | M84: 0 | N84: 0 | O84: typed fetch/client, loading/error states, caching concepts | P84: OpenAPI-generated or shared types experiment Interview: how prevent frontend/backend contract drift? | Q84: G02 | S84: =IF(R84="","",R84+'Weekly Review'!$C$5) | T84: AI-free first | U84: Existing | V84: TypeScript Track!21 | W84: S017 | X84: 7 | Y84: Next.js | AC84: W7 Review: W8 + W17–24 | AD84: =IF(G84="Done",IF(H84="","Add evidence",IF(R84="","Add completion date",IF(D84="Mock",IF(OR(Z84="",AA84="",AB84="",AB84="Not Attempted"),"Record mock results","Complete"),"Complete"))),"") | AE84: =C84&"|"&COUNTIFS($C$6:C84,C84) -> TypeScript & UI|18
A85: B07 | B85: 7 | C85: Projects | D85: Build | E85: Validated booking/order endpoint + Zod client contract | F85: P1 | G85: Not started | J85: =IF('Weekly Review'!$C$4="","",'Weekly Review'!$C$4+(X85-1)*7+6) -> 46342 | K85: Core | L85: 2 | M85: 0 | N85: 0 | O85: Demonstrate the working output, relevant tests, and one design trade-off. | P85: CS/SQL: CTEs/subqueries + advanced HTTP semantics Design: Idempotency + pagination trade-offs AI practice: AI-assisted small feature; write your own tests Validated booking/order endpoint + Zod client contract Pagination - Large orders list Small assisted feature: add your own tests before acceptance | Q85: B06 | S85: =IF(R85="","",R85+'Weekly Review'!$C$5) | T85: AI-free first | U85: Merged | V85: 24-Week Plan!11 Weekly Task Navigator!11 | X85: 7 | Y85: API Core | AD85: =IF(G85="Done",IF(H85="","Add evidence",IF(R85="","Add completion date",IF(D85="Mock",IF(OR(Z85="",AA85="",AB85="",AB85="Not Attempted"),"Record mock results","Complete"),"Complete"))),"") | AE85: =C85&"|"&COUNTIFS($C$6:C85,C85) -> Projects|7
A86: G05 | B86: 7 | C86: CS & SQL | D86: Practice | E86: Practice window functions, NULLs and duplicate-sensitive joins | F86: P1 | G86: Not started | J86: =IF('Weekly Review'!$C$4="","",'Weekly Review'!$C$4+(X86-1)*7+6) -> 46342 | K86: Core | L86: 1 | M86: 0 | N86: 0 | O86: Solve latest-row-per-group, ranking and running totals. Show how ties, NULLs and duplicate join keys affect the result. | Q86: CS12 | S86: =IF(R86="","",R86+'Weekly Review'!$C$5) | T86: AI-free first | U86: New gap task | W86: S031 | X86: 7 | Y86: Gap closure | AD86: =IF(G86="Done",IF(H86="","Add evidence",IF(R86="","Add completion date",IF(D86="Mock",IF(OR(Z86="",AA86="",AB86="",AB86="Not Attempted"),"Record mock results","Complete"),"Complete"))),"") | AE86: =C86&"|"&COUNTIFS($C$6:C86,C86) -> CS & SQL|11
A87: DS07 | B87: 7 | C87: DSA | D87: Practice | E87: Solve 7 new DSA problems and revisit errors | F87: P0 | G87: Not started | J87: =IF('Weekly Review'!$C$4="","",'Weekly Review'!$C$4+(X87-1)*7+6) -> 46342 | K87: Core | L87: 3 | M87: 0 | N87: 0 | O87: Record 7 distinct new problem IDs, explain complexity, and retry one earlier mistake without hints. | P87: Heap / priority queue (bank target 6) Sorting / intervals (bank target 6) Use Practice Bank for topic totals. Do not count repeat solutions as new problems. | S87: =IF(R87="","",R87+'Weekly Review'!$C$5) | T87: AI-free first | U87: Revised schedule | V87: 24-Week Plan!D11 Weekly Task Navigator!E11 | X87: 7 | Y87: Weekly problem set | AD87: =IF(G87="Done",IF(H87="","Add evidence",IF(R87="","Add completion date",IF(D87="Mock",IF(OR(Z87="",AA87="",AB87="",AB87="Not Attempted"),"Record mock results","Complete"),"Complete"))),"") | AE87: =C87&"|"&COUNTIFS($C$6:C87,C87) -> DSA|7
A88: M07 | B88: 7 | C88: Mock interviews | D88: Mock | E88: Validation/REST + heap/intervals + SQL | F88: P0 | G88: Not started | J88: =IF('Weekly Review'!$C$4="","",'Weekly Review'!$C$4+(X88-1)*7+6) -> 46342 | K88: Core | L88: 1 | M88: 0 | N88: 0 | O88: Complete the timed round. Record technical and communication scores, result, evidence, and one correction before the next mock. | S88: =IF(R88="","",R88+'Weekly Review'!$C$5) | T88: AI-Free | U88: Existing | V88: Mock Interviews!11 | X88: 7 | Y88: API + SQL | AB88: Not Attempted | AD88: =IF(G88="Done",IF(H88="","Add evidence",IF(R88="","Add completion date",IF(D88="Mock",IF(OR(Z88="",AA88="",AB88="",AB88="Not Attempted"),"Record mock results","Complete"),"Complete"))),"") | AE88: =C88&"|"&COUNTIFS($C$6:C88,C88) -> Mock interviews|7
A89: RV07 | B89: 7 | C89: Review | D89: Review | E89: Review evidence, questions and next-week capacity | F89: P1 | G89: Not started | I89: Record weakest concept and the next practice date. | J89: =IF('Weekly Review'!$C$4="","",'Weekly Review'!$C$4+(X89-1)*7+6) -> 46342 | K89: Core | L89: 0.5 | M89: 0 | N89: 0 | O89: Revisit due topics, practice the questions introduced this week, capture mock feedback, and choose the next three priorities. Update Weekly Review outcome and adjustment. | S89: =IF(R89="","",R89+'Weekly Review'!$C$5) | T89: AI-free first | U89: New gap task | X89: 7 | Y89: Weekly review | AD89: =IF(G89="Done",IF(H89="","Add evidence",IF(R89="","Add completion date",IF(D89="Mock",IF(OR(Z89="",AA89="",AB89="",AB89="Not Attempted"),"Record mock results","Complete"),"Complete"))),"") | AE89: =C89&"|"&COUNTIFS($C$6:C89,C89) -> Review|8
A90: AI07 | B90: 8 | C90: AI Engineering | D90: Learn | E90: LLM integration and validated structured output | F90: P1 | G90: Not started | J90: =IF('Weekly Review'!$C$4="","",'Weekly Review'!$C$4+(X90-1)*7+6) -> 46349 | K90: Optional | L90: 0.75 | M90: 0 | N90: 0 | O90: Requests, streaming, timeouts, retries, cost JSON schema / validation / retries Schemas/JSON validation, retries, deterministic handling | P90: Build a safe server-side call Failure to test: Secret leakage, retry storms Generate typed object and reject invalid Failure to test: Malformed output | S90: =IF(R90="","",R90+'Weekly Review'!$C$5) | T90: AI-free first | U90: Merged | V90: AI Engineering!7 AI Engineering!8 Master Roadmap!70 | W90: S004 S024 | X90: 8 | Y90: Integration | AC90: W8 Review: W8 + W17–24 | AD90: =IF(G90="Done",IF(H90="","Add evidence",IF(R90="","Add completion date",IF(D90="Mock",IF(OR(Z90="",AA90="",AB90="",AB90="Not Attempted"),"Record mock results","Complete"),"Complete"))),"") | AE90: =C90&"|"&COUNTIFS($C$6:C90,C90) -> AI Engineering|3
A91: JA23 | B91: 8 | C91: Java & Spring | D91: Learn | E91: JPA entities / repositories | F91: P0 | G91: Not started | J91: =IF('Weekly Review'!$C$4="","",'Weekly Review'!$C$4+(X91-1)*7+6) -> 46349 | K91: Core | L91: 0.75 | M91: 0 | N91: 0 | O91: mapping, IDs, relationships, repository abstraction entities, repositories, fetch strategy, N+1, query methods, pagination repositories, entity mapping, query methods, pagination, projections, N+1 awareness | P91: order/customer mapping Interview: entity vs DTO? Fix N+1/query bug and justify mapping JPA order/inventory module Critical Spring backend skill Implement inventory persistence layer | Q91: JA20 | S91: =IF(R91="","",R91+'Weekly Review'!$C$5) | T91: AI-free first | U91: Merged | V91: Java + Spring Boot!23 Full-Stack Stack!16 Master Roadmap!90 | W91: S005 | X91: 8 | Y91: Persistence | AC91: W8 Review: W8 + W17–24 W8–9 | AD91: =IF(G91="Done",IF(H91="","Add evidence",IF(R91="","Add completion date",IF(D91="Mock",IF(OR(Z91="",AA91="",AB91="",AB91="Not Attempted"),"Record mock results","Complete"),"Complete"))),"") | AE91: =C91&"|"&COUNTIFS($C$6:C91,C91) -> Java & Spring|17
A92: TS14 | B92: 8 | C92: TypeScript & UI | D92: Learn | E92: TypeScript configuration and migration awareness | F92: P2 | G92: Not started | J92: =IF('Weekly Review'!$C$4="","",'Weekly Review'!$C$4+(X92-1)*7+6) -> 46349 | K92: Core | L92: 0.75 | M92: 0 | N92: 0 | O92: deprecated tsconfig cleanup; native compiler direction ESM/bundler defaults, deprecated config cleanup, modern tsconfig | P92: upgrade sample config Interview: what changed in TS 6 at high level? Upgrade sample project to TS 6 | Q92: G02 | S92: =IF(R92="","",R92+'Weekly Review'!$C$5) | T92: AI-free first | U92: Merged | V92: TypeScript Track!14 Master Roadmap!100 | W92: S015 | X92: 8 | Y92: TypeScript Core | AC92: W8 Review: W8 + W17–24 | AD92: =IF(G92="Done",IF(H92="","Add evidence",IF(R92="","Add completion date",IF(D92="Mock",IF(OR(Z92="",AA92="",AB92="",AB92="Not Attempted"),"Record mock results","Complete"),"Complete"))),"") | AE92: =C92&"|"&COUNTIFS($C$6:C92,C92) -> TypeScript & UI|19
A93: TS27 | B93: 8 | C93: TypeScript & UI | D93: Learn | E93: Lint / format / typecheck | F93: P1 | G93: Not started | J93: =IF('Weekly Review'!$C$4="","",'Weekly Review'!$C$4+(X93-1)*7+6) -> 46349 | K93: Core | L93: 0.75 | M93: 0 | N93: 0 | O93: ESLint concepts, formatter, tsc --noEmit, CI gates | P93: CI quality gate Interview: lint vs typecheck vs tests? | Q93: G02 | S93: =IF(R93="","",R93+'Weekly Review'!$C$5) | T93: AI-free first | U93: Existing | V93: TypeScript Track!27 | W93: S015 | X93: 8 | Y93: Tooling | AC93: W8 Review: W8 + W17–24 | AD93: =IF(G93="Done",IF(H93="","Add evidence",IF(R93="","Add completion date",IF(D93="Mock",IF(OR(Z93="",AA93="",AB93="",AB93="Not Attempted"),"Record mock results","Complete"),"Complete"))),"") | AE93: =C93&"|"&COUNTIFS($C$6:C93,C93) -> TypeScript & UI|20
A94: G06 | B94: 8 | C94: Engineering | D94: Build | E94: Create and test a database migration | F94: P1 | G94: Not started | J94: =IF('Weekly Review'!$C$4="","",'Weekly Review'!$C$4+(X94-1)*7+6) -> 46349 | K94: Core | L94: 1.5 | M94: 0 | N94: 0 | O94: Use one migration tool, migrate an empty and populated database, and test recovery from a failed change. Keep schema history in version control. | Q94: JA23 | S94: =IF(R94="","",R94+'Weekly Review'!$C$5) | T94: AI-free first | U94: New gap task | W94: S032 | X94: 8 | Y94: Gap closure | AD94: =IF(G94="Done",IF(H94="","Add evidence",IF(R94="","Add completion date",IF(D94="Mock",IF(OR(Z94="",AA94="",AB94="",AB94="Not Attempted"),"Record mock results","Complete"),"Complete"))),"") | AE94: =C94&"|"&COUNTIFS($C$6:C94,C94) -> Engineering|5
A95: B08 | B95: 8 | C95: Projects | D95: Build | E95: Persist customer/order model + clean frontend build/typecheck pipeline | F95: P1 | G95: Not started | J95: =IF('Weekly Review'!$C$4="","",'Weekly Review'!$C$4+(X95-1)*7+6) -> 46349 | K95: Core | L95: 2 | M95: 0 | N95: 0 | O95: Demonstrate the working output, relevant tests, and one design trade-off. | P95: CS/SQL: Index fundamentals + DB modeling review Design: Database schema and query-path review AI practice: AI verification: inspect diff, tests and assumptions Persist customer/order model + clean frontend build/typecheck pipeline Review JPA schema and query path from API to DB LLM API - Build a safe server-side call Structured output - Generate typed object and reject invalid | Q95: B07 | S95: =IF(R95="","",R95+'Weekly Review'!$C$5) | T95: AI-free first | U95: Merged | V95: 24-Week Plan!12 Weekly Task Navigator!12 | X95: 8 | Y95: API Core | AD95: =IF(G95="Done",IF(H95="","Add evidence",IF(R95="","Add completion date",IF(D95="Mock",IF(OR(Z95="",AA95="",AB95="",AB95="Not Attempted"),"Record mock results","Complete"),"Complete"))),"") | AE95: =C95&"|"&COUNTIFS($C$6:C95,C95) -> Projects|8
A96: DS08 | B96: 8 | C96: DSA | D96: Practice | E96: Solve 7 new DSA problems and revisit errors | F96: P0 | G96: Not started | J96: =IF('Weekly Review'!$C$4="","",'Weekly Review'!$C$4+(X96-1)*7+6) -> 46349 | K96: Core | L96: 3 | M96: 0 | N96: 0 | O96: Record 7 distinct new problem IDs, explain complexity, and retry one earlier mistake without hints. | P96: Mixed review: trees + binary search + stacks (6 problems) Use Practice Bank for topic totals. Do not count repeat solutions as new problems. | S96: =IF(R96="","",R96+'Weekly Review'!$C$5) | T96: AI-free first | U96: Revised schedule | V96: 24-Week Plan!D12 Weekly Task Navigator!E12 | X96: 8 | Y96: Weekly problem set | AD96: =IF(G96="Done",IF(H96="","Add evidence",IF(R96="","Add completion date",IF(D96="Mock",IF(OR(Z96="",AA96="",AB96="",AB96="Not Attempted"),"Record mock results","Complete"),"Complete"))),"") | AE96: =C96&"|"&COUNTIFS($C$6:C96,C96) -> DSA|8
A97: M08 | B97: 8 | C97: Mock interviews | D97: Mock | E97: JPA entity/repository + TS tooling in existing repo | F97: P0 | G97: Not started | J97: =IF('Weekly Review'!$C$4="","",'Weekly Review'!$C$4+(X97-1)*7+6) -> 46349 | K97: Core | L97: 1 | M97: 0 | N97: 0 | O97: Complete the timed round. Record technical and communication scores, result, evidence, and one correction before the next mock. | S97: =IF(R97="","",R97+'Weekly Review'!$C$5) | T97: AI-Assisted (constrained) | U97: Existing | V97: Mock Interviews!12 | X97: 8 | Y97: Repository Mini Task | AB97: Not Attempted | AD97: =IF(G97="Done",IF(H97="","Add evidence",IF(R97="","Add completion date",IF(D97="Mock",IF(OR(Z97="",AA97="",AB97="",AB97="Not Attempted"),"Record mock results","Complete"),"Complete"))),"") | AE97: =C97&"|"&COUNTIFS($C$6:C97,C97) -> Mock interviews|8
A98: RV08 | B98: 8 | C98: Review | D98: Review | E98: Review evidence, questions and next-week capacity | F98: P1 | G98: Not started | I98: Record weakest concept and the next practice date. | J98: =IF('Weekly Review'!$C$4="","",'Weekly Review'!$C$4+(X98-1)*7+6) -> 46349 | K98: Core | L98: 0.5 | M98: 0 | N98: 0 | O98: Revisit due topics, practice the questions introduced this week, capture mock feedback, and choose the next three priorities. Update Weekly Review outcome and adjustment. | S98: =IF(R98="","",R98+'Weekly Review'!$C$5) | T98: AI-free first | U98: New gap task | X98: 8 | Y98: Weekly review | AD98: =IF(G98="Done",IF(H98="","Add evidence",IF(R98="","Add completion date",IF(D98="Mock",IF(OR(Z98="",AA98="",AB98="",AB98="Not Attempted"),"Record mock results","Complete"),"Complete"))),"") | AE98: =C98&"|"&COUNTIFS($C$6:C98,C98) -> Review|9
A99: CS09 | B99: 9 | C99: CS & SQL | D99: Learn | E99: Indexes | F99: P0 | G99: Not started | J99: =IF('Weekly Review'!$C$4="","",'Weekly Review'!$C$4+(X99-1)*7+6) -> 46356 | K99: Core | L99: 0.75 | M99: 0 | N99: 0 | O99: B-tree concept, selectivity, composite order Choose indexes, composite order, scan trade-offs | P99: Interview: Why is this query slow? | S99: =IF(R99="","",R99+'Weekly Review'!$C$5) | T99: AI-free first | U99: Merged | V99: CS Fundamentals!9 Master Roadmap!28 | W99: S020 S026 | X99: 9 | Y99: DBMS | AC99: W9 Review: W12 + W17–24 | AD99: =IF(G99="Done",IF(H99="","Add evidence",IF(R99="","Add completion date",IF(D99="Mock",IF(OR(Z99="",AA99="",AB99="",AB99="Not Attempted"),"Record mock results","Complete"),"Complete"))),"") | AE99: =C99&"|"&COUNTIFS($C$6:C99,C99) -> CS & SQL|12
A100: JA24 | B100: 9 | C100: Java & Spring | D100: Learn | E100: Queries / N+1 | F100: P0 | G100: Not started | J100: =IF('Weekly Review'!$C$4="","",'Weekly Review'!$C$4+(X100-1)*7+6) -> 46356 | K100: Core | L100: 0.75 | M100: 0 | N100: 0 | O100: query methods, JPQL concept, projections, fetch strategy | P100: catalogue query profiling Interview: what is N+1 and how detect/fix it? | Q100: G02 | S100: =IF(R100="","",R100+'Weekly Review'!$C$5) | T100: AI-free first | U100: Existing | V100: Java + Spring Boot!24 | W100: S006 | X100: 9 | Y100: Persistence | AC100: W9 Review: W12 + W17–24 | AD100: =IF(G100="Done",IF(H100="","Add evidence",IF(R100="","Add completion date",IF(D100="Mock",IF(OR(Z100="",AA100="",AB100="",AB100="Not Attempted"),"Record mock results","Complete"),"Complete"))),"") | AE100: =C100&"|"&COUNTIFS($C$6:C100,C100) -> Java & Spring|18
A101: TS23 | B101: 9 | C101: TypeScript & UI | D101: Learn | E101: Vitest / Jest concepts | F101: P0 | G101: Not started | J101: =IF('Weekly Review'!$C$4="","",'Weekly Review'!$C$4+(X101-1)*7+6) -> 46356 | K101: Core | L101: 0.75 | M101: 0 | N101: 0 | O101: unit tests, mocks, timers, async tests unit/component behavior, async UI, mocking boundaries | P101: utility/service test suite Interview: what should be mocked? Test typed form + API failure states Frontend regression suite TypeScript test competency | Q101: G02 | S101: =IF(R101="","",R101+'Weekly Review'!$C$5) | T101: AI-free first | U101: Merged | V101: TypeScript Track!23 Full-Stack Stack!23 | W101: S004 | X101: 9 | Y101: Testing | AC101: W9 Review: W12 + W17–24 W12 | AD101: =IF(G101="Done",IF(H101="","Add evidence",IF(R101="","Add completion date",IF(D101="Mock",IF(OR(Z101="",AA101="",AB101="",AB101="Not Attempted"),"Record mock results","Complete"),"Complete"))),"") | AE101: =C101&"|"&COUNTIFS($C$6:C101,C101) -> TypeScript & UI|21
...

Sheet AI Engineering
A2: AI Engineering tasks
A4: Category | C4: AI Engineering | D4: Tasks | E4: =COUNTIFS(PlanTasks[Category],$C$4) -> 7 | F4: Complete | G4: =COUNTIFS(PlanTasks[Category],$C$4,PlanTasks[Completion check],"Complete") -> 0 | H4: Progress | I4: =IF(E4=0,"",G4/E4) -> 0
A5: Linked view. Edit the Master Plan; changes appear here automatically. Use Task ID to find the original row.
A6: =IF(E4>300,"More than 300 tasks: copy the last view row downward to show the remaining tasks.","Shows up to 300 tasks. Order follows the Master Plan.") -> Shows up to 300 tasks. Order follows the Master Plan.
A8: Task ID | B8: Start week | C8: Task / deliverable | D8: Status | E8: Priority | F8: Scope | G8: Estimate (h) | H8: Actual (h) | I8: Due date | J8: Completion check | K8: Next action / blocker | L8: Done when | M8: Exercise / interview prompt | N8: Prerequisite IDs | O8: Plan section | P8: Category | Q8: Evidence / result | R8: Completed on | S8: Review due | T8: AI practice mode | U8: Source IDs | V8: Source position
A9: {=IF($V9="","",INDEX(PlanTasks[Task ID],$V9))} -> AI18 | B9: {=IF($V9="","",IF(INDEX(PlanTasks[Start week],$V9)="","",INDEX(PlanTasks[Start week],$V9)))} -> 1 | C9: {=IF($V9="","",IF(INDEX(PlanTasks[Task / deliverable],$V9)="","",INDEX(PlanTasks[Task / deliverable],$V9)))} -> Confirm round policy and rehearse AI-free fallback | D9: {=IF($V9="","",IF(INDEX(PlanTasks[Status],$V9)="","",INDEX(PlanTasks[Status],$V9)))} -> In progress | E9: {=IF($V9="","",IF(INDEX(PlanTasks[Priority],$V9)="","",INDEX(PlanTasks[Priority],$V9)))} -> P0 | F9: {=IF($V9="","",IF(INDEX(PlanTasks[Scope],$V9)="","",INDEX(PlanTasks[Scope],$V9)))} -> Core | G9: {=IF($V9="","",IF(INDEX(PlanTasks[Estimate (h)],$V9)="","",INDEX(PlanTasks[Estimate (h)],$V9)))} -> 0.75 | H9: {=IF($V9="","",IF(INDEX(PlanTasks[Actual (h)],$V9)="","",INDEX(PlanTasks[Actual (h)],$V9)))} -> 0 | I9: {=IF($V9="","",IF(INDEX(PlanTasks[Due date],$V9)="","",INDEX(PlanTasks[Due date],$V9)))} -> 46300 | J9: {=IF($V9="","",IF(INDEX(PlanTasks[Completion check],$V9)="","",INDEX(PlanTasks[Completion check],$V9)))} | K9: {=IF($V9="","",IF(INDEX(PlanTasks[Next action / blocker],$V9)="","",INDEX(PlanTasks[Next action / blocker],$V9)))} | L9: {=IF($V9="","",IF(INDEX(PlanTasks[Done when],$V9)="","",INDEX(PlanTasks[Done when],$V9)))} -> Confirm exact permitted tools and boundaries Code/debug/explain with no assistant Implement and explain independently Solve/debug/explain without AI when required | M9: {=IF($V9="","",IF(INDEX(PlanTasks[Exercise / interview prompt],$V9)="","",INDEX(PlanTasks[Exercise / interview prompt],$V9)))} -> Transparent AI-assisted session Failure to test: Policy violation 60-min unaided mock Failure to test: Dependency on tools Redo representative task without any assistant Practice mode: AI-free Yes, AI-assisted No | N9: {=IF($V9="","",IF(INDEX(PlanTasks[Prerequisite IDs],$V9)="","",INDEX(PlanTasks[Prerequisite IDs],$V9)))} | O9: {=IF($V9="","",IF(INDEX(PlanTasks[Plan section],$V9)="","",INDEX(PlanTasks[Plan section],$V9)))} -> Interview Policy | P9: {=IF($V9="","",IF(INDEX(PlanTasks[Category],$V9)="","",INDEX(PlanTasks[Category],$V9)))} -> AI Engineering | Q9: {=IF($V9="","",IF(INDEX(PlanTasks[Evidence / result],$V9)="","",INDEX(PlanTasks[Evidence / result],$V9)))} | R9: {=IF($V9="","",IF(INDEX(PlanTasks[Completed on],$V9)="","",INDEX(PlanTasks[Completed on],$V9)))} | S9: {=IF($V9="","",IF(INDEX(PlanTasks[Review due],$V9)="","",INDEX(PlanTasks[Review due],$V9)))} | T9: {=IF($V9="","",IF(INDEX(PlanTasks[AI practice mode],$V9)="","",INDEX(PlanTasks[AI practice mode],$V9)))} -> AI-free first | U9: {=IF($V9="","",IF(INDEX(PlanTasks[Source IDs],$V9)="","",INDEX(PlanTasks[Source IDs],$V9)))} -> S026 S027 S025 | V9: =IF(ROW()-8>$E$4,"",MATCH($C$4&"|"&(ROW()-8),PlanTasks[Category key],0)) -> 3
A10: {=IF($V10="","",INDEX(PlanTasks[Task ID],$V10))} -> AI05 | B10: {=IF($V10="","",IF(INDEX(PlanTasks[Start week],$V10)="","",INDEX(PlanTasks[Start week],$V10)))} -> 5 | C10: {=IF($V10="","",IF(INDEX(PlanTasks[Task / deliverable],$V10)="","",INDEX(PlanTasks[Task / deliverable],$V10)))} -> AI limitations, context and token budgets | D10: {=IF($V10="","",IF(INDEX(PlanTasks[Status],$V10)="","",INDEX(PlanTasks[Status],$V10)))} -> Not started | E10: {=IF($V10="","",IF(INDEX(PlanTasks[Priority],$V10)="","",INDEX(PlanTasks[Priority],$V10)))} -> P1 | F10: {=IF($V10="","",IF(INDEX(PlanTasks[Scope],$V10)="","",INDEX(PlanTasks[Scope],$V10)))} -> Core | G10: {=IF($V10="","",IF(INDEX(PlanTasks[Estimate (h)],$V10)="","",INDEX(PlanTasks[Estimate (h)],$V10)))} -> 0.75 | H10: {=IF($V10="","",IF(INDEX(PlanTasks[Actual (h)],$V10)="","",INDEX(PlanTasks[Actual (h)],$V10)))} -> 0 | I10: {=IF($V10="","",IF(INDEX(PlanTasks[Due date],$V10)="","",INDEX(PlanTasks[Due date],$V10)))} -> 46328 | J10: {=IF($V10="","",IF(INDEX(PlanTasks[Completion check],$V10)="","",INDEX(PlanTasks[Completion check],$V10)))} | K10: {=IF($V10="","",IF(INDEX(PlanTasks[Next action / blocker],$V10)="","",INDEX(PlanTasks[Next action / blocker],$V10)))} | L10: {=IF($V10="","",IF(INDEX(PlanTasks[Done when],$V10)="","",INDEX(PlanTasks[Done when],$V10)))} -> Context limits, cost/latency, truncation Hallucination, stale assumptions, non-determinism Models, tokens, context, latency/cost, failure handling | M10: {=IF($V10="","",IF(INDEX(PlanTasks[Exercise / interview prompt],$V10)="","",INDEX(PlanTasks[Exercise / interview prompt],$V10)))} -> Estimate context needed for repo task Failure to test: Missing/irrelevant context Find unsupported claim/code assumption Failure to test: Blind trust | N10: {=IF($V10="","",IF(INDEX(PlanTasks[Prerequisite IDs],$V10)="","",INDEX(PlanTasks[Prerequisite IDs],$V10)))} | O10: {=IF($V10="","",IF(INDEX(PlanTasks[Plan section],$V10)="","",INDEX(PlanTasks[Plan section],$V10)))} -> Fundamentals | P10: {=IF($V10="","",IF(INDEX(PlanTasks[Category],$V10)="","",INDEX(PlanTasks[Category],$V10)))} -> AI Engineering | Q10: {=IF($V10="","",IF(INDEX(PlanTasks[Evidence / result],$V10)="","",INDEX(PlanTasks[Evidence / result],$V10)))} | R10: {=IF($V10="","",IF(INDEX(PlanTasks[Completed on],$V10)="","",INDEX(PlanTasks[Completed on],$V10)))} | S10: {=IF($V10="","",IF(INDEX(PlanTasks[Review due],$V10)="","",INDEX(PlanTasks[Review due],$V10)))} | T10: {=IF($V10="","",IF(INDEX(PlanTasks[AI practice mode],$V10)="","",INDEX(PlanTasks[AI practice mode],$V10)))} -> AI-free first | U10: {=IF($V10="","",IF(INDEX(PlanTasks[Source IDs],$V10)="","",INDEX(PlanTasks[Source IDs],$V10)))} -> S004 S023 | V10: =IF(ROW()-8>$E$4,"",MATCH($C$4&"|"&(ROW()-8),PlanTasks[Category key],0)) -> 50
A11: {=IF($V11="","",INDEX(PlanTasks[Task ID],$V11))} -> AI07 | B11: {=IF($V11="","",IF(INDEX(PlanTasks[Start week],$V11)="","",INDEX(PlanTasks[Start week],$V11)))} -> 8 | C11: {=IF($V11="","",IF(INDEX(PlanTasks[Task / deliverable],$V11)="","",INDEX(PlanTasks[Task / deliverable],$V11)))} -> LLM integration and validated structured output | D11: {=IF($V11="","",IF(INDEX(PlanTasks[Status],$V11)="","",INDEX(PlanTasks[Status],$V11)))} -> Not started | E11: {=IF($V11="","",IF(INDEX(PlanTasks[Priority],$V11)="","",INDEX(PlanTasks[Priority],$V11)))} -> P1 | F11: {=IF($V11="","",IF(INDEX(PlanTasks[Scope],$V11)="","",INDEX(PlanTasks[Scope],$V11)))} -> Optional | G11: {=IF($V11="","",IF(INDEX(PlanTasks[Estimate (h)],$V11)="","",INDEX(PlanTasks[Estimate (h)],$V11)))} -> 0.75 | H11: {=IF($V11="","",IF(INDEX(PlanTasks[Actual (h)],$V11)="","",INDEX(PlanTasks[Actual (h)],$V11)))} -> 0 | I11: {=IF($V11="","",IF(INDEX(PlanTasks[Due date],$V11)="","",INDEX(PlanTasks[Due date],$V11)))} -> 46349 | J11: {=IF($V11="","",IF(INDEX(PlanTasks[Completion check],$V11)="","",INDEX(PlanTasks[Completion check],$V11)))} | K11: {=IF($V11="","",IF(INDEX(PlanTasks[Next action / blocker],$V11)="","",INDEX(PlanTasks[Next action / blocker],$V11)))} | L11: {=IF($V11="","",IF(INDEX(PlanTasks[Done when],$V11)="","",INDEX(PlanTasks[Done when],$V11)))} -> Requests, streaming, timeouts, retries, cost JSON schema / validation / retries Schemas/JSON validation, retries, deterministic handling | M11: {=IF($V11="","",IF(INDEX(PlanTasks[Exercise / interview prompt],$V11)="","",INDEX(PlanTasks[Exercise / interview prompt],$V11)))} -> Build a safe server-side call Failure to test: Secret leakage, retry storms Generate typed object and reject invalid Failure to test: Malformed output | N11: {=IF($V11="","",IF(INDEX(PlanTasks[Prerequisite IDs],$V11)="","",INDEX(PlanTasks[Prerequisite IDs],$V11)))} | O11: {=IF($V11="","",IF(INDEX(PlanTasks[Plan section],$V11)="","",INDEX(PlanTasks[Plan section],$V11)))} -> Integration | P11: {=IF($V11="","",IF(INDEX(PlanTasks[Category],$V11)="","",INDEX(PlanTasks[Category],$V11)))} -> AI Engineering | Q11: {=IF($V11="","",IF(INDEX(PlanTasks[Evidence / result],$V11)="","",INDEX(PlanTasks[Evidence / result],$V11)))} | R11: {=IF($V11="","",IF(INDEX(PlanTasks[Completed on],$V11)="","",INDEX(PlanTasks[Completed on],$V11)))} | S11: {=IF($V11="","",IF(INDEX(PlanTasks[Review due],$V11)="","",INDEX(PlanTasks[Review due],$V11)))} | T11: {=IF($V11="","",IF(INDEX(PlanTasks[AI practice mode],$V11)="","",INDEX(PlanTasks[AI practice mode],$V11)))} -> AI-free first | U11: {=IF($V11="","",IF(INDEX(PlanTasks[Source IDs],$V11)="","",INDEX(PlanTasks[Source IDs],$V11)))} -> S004 S024 | V11: =IF(ROW()-8>$E$4,"",MATCH($C$4&"|"&(ROW()-8),PlanTasks[Category key],0)) -> 85
A12: {=IF($V12="","",INDEX(PlanTasks[Task ID],$V12))} -> AI17 | B12: {=IF($V12="","",IF(INDEX(PlanTasks[Start week],$V12)="","",INDEX(PlanTasks[Start week],$V12)))} -> 11 | C12: {=IF($V12="","",IF(INDEX(PlanTasks[Task / deliverable],$V12)="","",INDEX(PlanTasks[Task / deliverable],$V12)))} -> Secrets/privacy | D12: {=IF($V12="","",IF(INDEX(PlanTasks[Status],$V12)="","",INDEX(PlanTasks[Status],$V12)))} -> Not started | E12: {=IF($V12="","",IF(INDEX(PlanTasks[Priority],$V12)="","",INDEX(PlanTasks[Priority],$V12)))} -> P1 | F12: {=IF($V12="","",IF(INDEX(PlanTasks[Scope],$V12)="","",INDEX(PlanTasks[Scope],$V12)))} -> Core | G12: {=IF($V12="","",IF(INDEX(PlanTasks[Estimate (h)],$V12)="","",INDEX(PlanTasks[Estimate (h)],$V12)))} -> 0.75 | H12: {=IF($V12="","",IF(INDEX(PlanTasks[Actual (h)],$V12)="","",INDEX(PlanTasks[Actual (h)],$V12)))} -> 0 | I12: {=IF($V12="","",IF(INDEX(PlanTasks[Due date],$V12)="","",INDEX(PlanTasks[Due date],$V12)))} -> 46370 | J12: {=IF($V12="","",IF(INDEX(PlanTasks[Completion check],$V12)="","",INDEX(PlanTasks[Completion check],$V12)))} | K12: {=IF($V12="","",IF(INDEX(PlanTasks[Next action / blocker],$V12)="","",INDEX(PlanTasks[Next action / blocker],$V12)))} | L12: {=IF($V12="","",IF(INDEX(PlanTasks[Done when],$V12)="","",INDEX(PlanTasks[Done when],$V12)))} -> Do not expose sensitive secrets/data without authorization Env vars, secret managers, rotation, least privilege | M12: {=IF($V12="","",IF(INDEX(PlanTasks[Exercise / interview prompt],$V12)="","",INDEX(PlanTasks[Exercise / interview prompt],$V12)))} -> Identify sensitive context boundaries Failure to test: Data leakage | N12: {=IF($V12="","",IF(INDEX(PlanTasks[Prerequisite IDs],$V12)="","",INDEX(PlanTasks[Prerequisite IDs],$V12)))} | O12: {=IF($V12="","",IF(INDEX(PlanTasks[Plan section],$V12)="","",INDEX(PlanTasks[Plan section],$V12)))} -> Safety | P12: {=IF($V12="","",IF(INDEX(PlanTasks[Category],$V12)="","",INDEX(PlanTasks[Category],$V12)))} -> AI Engineering | Q12: {=IF($V12="","",IF(INDEX(PlanTasks[Evidence / result],$V12)="","",INDEX(PlanTasks[Evidence / result],$V12)))} | R12: {=IF($V12="","",IF(INDEX(PlanTasks[Completed on],$V12)="","",INDEX(PlanTasks[Completed on],$V12)))} | S12: {=IF($V12="","",IF(INDEX(PlanTasks[Review due],$V12)="","",INDEX(PlanTasks[Review due],$V12)))} | T12: {=IF($V12="","",IF(INDEX(PlanTasks[AI practice mode],$V12)="","",INDEX(PlanTasks[AI practice mode],$V12)))} -> AI-free first | U12: {=IF($V12="","",IF(INDEX(PlanTasks[Source IDs],$V12)="","",INDEX(PlanTasks[Source IDs],$V12)))} -> S025 S022 | V12: =IF(ROW()-8>$E$4,"",MATCH($C$4&"|"&(ROW()-8),PlanTasks[Category key],0)) -> 113
A13: {=IF($V13="","",INDEX(PlanTasks[Task ID],$V13))} -> AI09 | B13: {=IF($V13="","",IF(INDEX(PlanTasks[Start week],$V13)="","",INDEX(PlanTasks[Start week],$V13)))} -> 16 | C13: {=IF($V13="","",IF(INDEX(PlanTasks[Task / deliverable],$V13)="","",INDEX(PlanTasks[Task / deliverable],$V13)))} -> Bounded agents, tool calls and context | D13: {=IF($V13="","",IF(INDEX(PlanTasks[Status],$V13)="","",INDEX(PlanTasks[Status],$V13)))} -> Not started | E13: {=IF($V13="","",IF(INDEX(PlanTasks[Priority],$V13)="","",INDEX(PlanTasks[Priority],$V13)))} -> P1 | F13: {=IF($V13="","",IF(INDEX(PlanTasks[Scope],$V13)="","",INDEX(PlanTasks[Scope],$V13)))} -> Optional | G13: {=IF($V13="","",IF(INDEX(PlanTasks[Estimate (h)],$V13)="","",INDEX(PlanTasks[Estimate (h)],$V13)))} -> 0.75 | H13: {=IF($V13="","",IF(INDEX(PlanTasks[Actual (h)],$V13)="","",INDEX(PlanTasks[Actual (h)],$V13)))} -> 0 | I13: {=IF($V13="","",IF(INDEX(PlanTasks[Due date],$V13)="","",INDEX(PlanTasks[Due date],$V13)))} -> 46405 | J13: {=IF($V13="","",IF(INDEX(PlanTasks[Completion check],$V13)="","",INDEX(PlanTasks[Completion check],$V13)))} | K13: {=IF($V13="","",IF(INDEX(PlanTasks[Next action / blocker],$V13)="","",INDEX(PlanTasks[Next action / blocker],$V13)))} | L13: {=IF($V13="","",IF(INDEX(PlanTasks[Done when],$V13)="","",INDEX(PlanTasks[Done when],$V13)))} -> Schema, permissions, tool-result loop Plan/act/observe, stop conditions Repo map, acceptance criteria, constraints Clear plan, controlled scope Task, constraints, examples, context boundaries Define tools, permissions, validation, error loops Plan/act/observe, tool use, boundaries, human review | M13: {=IF($V13="","",IF(INDEX(PlanTasks[Exercise / interview prompt],$V13)="","",INDEX(PlanTasks[Exercise / interview prompt],$V13)))} -> Agent can read but not mutate unsafe resources Failure to test: Over-privileged tools Give bounded repo ticket Failure to test: Infinite/unsafe loops Improve agent output without overprompting Failure to test: Ambiguous scope Give agent bounded ticket with context + acceptance criteria Practice mode: AI-free No, AI-assisted Yes | N13: {=IF($V13="","",IF(INDEX(PlanTasks[Prerequisite IDs],$V13)="","",INDEX(PlanTasks[Prerequisite IDs],$V13)))} | O13: {=IF($V13="","",IF(INDEX(PlanTasks[Plan section],$V13)="","",INDEX(PlanTasks[Plan section],$V13)))} -> Integration | P13: {=IF($V13="","",IF(INDEX(PlanTasks[Category],$V13)="","",INDEX(PlanTasks[Category],$V13)))} -> AI Engineering | Q13: {=IF($V13="","",IF(INDEX(PlanTasks[Evidence / result],$V13)="","",INDEX(PlanTasks[Evidence / result],$V13)))} | R13: {=IF($V13="","",IF(INDEX(PlanTasks[Completed on],$V13)="","",INDEX(PlanTasks[Completed on],$V13)))} | S13: {=IF($V13="","",IF(INDEX(PlanTasks[Review due],$V13)="","",INDEX(PlanTasks[Review due],$V13)))} | T13: {=IF($V13="","",IF(INDEX(PlanTasks[AI practice mode],$V13)="","",INDEX(PlanTasks[AI practice mode],$V13)))} -> AI-free first | U13: {=IF($V13="","",IF(INDEX(PlanTasks[Source IDs],$V13)="","",INDEX(PlanTasks[Source IDs],$V13)))} -> S024 S021 | V13: =IF(ROW()-8>$E$4,"",MATCH($C$4&"|"&(ROW()-8),PlanTasks[Category key],0)) -> 161
A14: {=IF($V14="","",INDEX(PlanTasks[Task ID],$V14))} -> AI14 | B14: {=IF($V14="","",IF(INDEX(PlanTasks[Start week],$V14)="","",INDEX(PlanTasks[Start week],$V14)))} -> 16 | C14: {=IF($V14="","",IF(INDEX(PlanTasks[Task / deliverable],$V14)="","",INDEX(PlanTasks[Task / deliverable],$V14)))} -> Verify generated code with tests and diff review | D14: {=IF($V14="","",IF(INDEX(PlanTasks[Status],$V14)="","",INDEX(PlanTasks[Status],$V14)))} -> Not started | E14: {=IF($V14="","",IF(INDEX(PlanTasks[Priority],$V14)="","",INDEX(PlanTasks[Priority],$V14)))} -> P0 | F14: {=IF($V14="","",IF(INDEX(PlanTasks[Scope],$V14)="","",INDEX(PlanTasks[Scope],$V14)))} -> Core | G14: {=IF($V14="","",IF(INDEX(PlanTasks[Estimate (h)],$V14)="","",INDEX(PlanTasks[Estimate (h)],$V14)))} -> 0.75 | H14: {=IF($V14="","",IF(INDEX(PlanTasks[Actual (h)],$V14)="","",INDEX(PlanTasks[Actual (h)],$V14)))} -> 0 | I14: {=IF($V14="","",IF(INDEX(PlanTasks[Due date],$V14)="","",INDEX(PlanTasks[Due date],$V14)))} -> 46405 | J14: {=IF($V14="","",IF(INDEX(PlanTasks[Completion check],$V14)="","",INDEX(PlanTasks[Completion check],$V14)))} | K14: {=IF($V14="","",IF(INDEX(PlanTasks[Next action / blocker],$V14)="","",INDEX(PlanTasks[Next action / blocker],$V14)))} | L14: {=IF($V14="","",IF(INDEX(PlanTasks[Done when],$V14)="","",INDEX(PlanTasks[Done when],$V14)))} -> Correctness, edge cases, security, perf Use targeted tests to prove AI fix Small diffs, inspect changed files, revert noise Catch correctness/security/test gaps agent context, small diffs, tests, compile/type checks, security review Review generated code, test security/perf/correctness | M14: {=IF($V14="","",IF(INDEX(PlanTasks[Exercise / interview prompt],$V14)="","",INDEX(PlanTasks[Exercise / interview prompt],$V14)))} -> Review AI PR line-by-line Failure to test: Almost-right code Write regression before acceptance Failure to test: False confidence Reduce an over-broad AI change Failure to test: Unnecessary rewrites Ask an agent to implement, then independently review it Practice mode: AI-free No, AI-assisted Yes Use AI on repo task then independently verify Java + TS changes 5 timed agentic tickets Use AI only when interview policy permits | N14: {=IF($V14="","",IF(INDEX(PlanTasks[Prerequisite IDs],$V14)="","",INDEX(PlanTasks[Prerequisite IDs],$V14)))} | O14: {=IF($V14="","",IF(INDEX(PlanTasks[Plan section],$V14)="","",INDEX(PlanTasks[Plan section],$V14)))} -> Verification | P14: {=IF($V14="","",IF(INDEX(PlanTasks[Category],$V14)="","",INDEX(PlanTasks[Category],$V14)))} -> AI Engineering | Q14: {=IF($V14="","",IF(INDEX(PlanTasks[Evidence / result],$V14)="","",INDEX(PlanTasks[Evidence / result],$V14)))} | R14: {=IF($V14="","",IF(INDEX(PlanTasks[Completed on],$V14)="","",INDEX(PlanTasks[Completed on],$V14)))} | S14: {=IF($V14="","",IF(INDEX(PlanTasks[Review due],$V14)="","",INDEX(PlanTasks[Review due],$V14)))} | T14: {=IF($V14="","",IF(INDEX(PlanTasks[AI practice mode],$V14)="","",INDEX(PlanTasks[AI practice mode],$V14)))} -> AI-free first | U14: {=IF($V14="","",IF(INDEX(PlanTasks[Source IDs],$V14)="","",INDEX(PlanTasks[Source IDs],$V14)))} -> S023 S021 S018 | V14: =IF(ROW()-8>$E$4,"",MATCH($C$4&"|"&(ROW()-8),PlanTasks[Category key],0)) -> 162
A15: {=IF($V15="","",INDEX(PlanTasks[Task ID],$V15))} -> AI10 | B15: {=IF($V15="","",IF(INDEX(PlanTasks[Start week],$V15)="","",INDEX(PlanTasks[Start week],$V15)))} -> 19 | C15: {=IF($V15="","",IF(INDEX(PlanTasks[Task / deliverable],$V15)="","",INDEX(PlanTasks[Task / deliverable],$V15)))} -> Retrieval, grounding and citations | D15: {=IF($V15="","",IF(INDEX(PlanTasks[Status],$V15)="","",INDEX(PlanTasks[Status],$V15)))} -> Not started | E15: {=IF($V15="","",IF(INDEX(PlanTasks[Priority],$V15)="","",INDEX(PlanTasks[Priority],$V15)))} -> P2 | F15: {=IF($V15="","",IF(INDEX(PlanTasks[Scope],$V15)="","",INDEX(PlanTasks[Scope],$V15)))} -> Optional | G15: {=IF($V15="","",IF(INDEX(PlanTasks[Estimate (h)],$V15)="","",INDEX(PlanTasks[Estimate (h)],$V15)))} -> 0.75 | H15: {=IF($V15="","",IF(INDEX(PlanTasks[Actual (h)],$V15)="","",INDEX(PlanTasks[Actual (h)],$V15)))} -> 0 | I15: {=IF($V15="","",IF(INDEX(PlanTasks[Due date],$V15)="","",INDEX(PlanTasks[Due date],$V15)))} -> 46426 | J15: {=IF($V15="","",IF(INDEX(PlanTasks[Completion check],$V15)="","",INDEX(PlanTasks[Completion check],$V15)))} | K15: {=IF($V15="","",IF(INDEX(PlanTasks[Next action / blocker],$V15)="","",INDEX(PlanTasks[Next action / blocker],$V15)))} | L15: {=IF($V15="","",IF(INDEX(PlanTasks[Done when],$V15)="","",INDEX(PlanTasks[Done when],$V15)))} -> Chunking, similarity, metadata filters Answer only from retrieved evidence Chunking, retrieval, grounding, citations, evaluation | M15: {=IF($V15="","",IF(INDEX(PlanTasks[Exercise / interview prompt],$V15)="","",INDEX(PlanTasks[Exercise / interview prompt],$V15)))} -> Build mini knowledge search Failure to test: Wrong retrieval Return evidence with answer Failure to test: Confident hallucination | N15: {=IF($V15="","",IF(INDEX(PlanTasks[Prerequisite IDs],$V15)="","",INDEX(PlanTasks[Prerequisite IDs],$V15)))} | O15: {=IF($V15="","",IF(INDEX(PlanTasks[Plan section],$V15)="","",INDEX(PlanTasks[Plan section],$V15)))} -> RAG | P15: {=IF($V15="","",IF(INDEX(PlanTasks[Category],$V15)="","",INDEX(PlanTasks[Category],$V15)))} -> AI Engineering | Q15: {=IF($V15="","",IF(INDEX(PlanTasks[Evidence / result],$V15)="","",INDEX(PlanTasks[Evidence / result],$V15)))} | R15: {=IF($V15="","",IF(INDEX(PlanTasks[Completed on],$V15)="","",INDEX(PlanTasks[Completed on],$V15)))} | S15: {=IF($V15="","",IF(INDEX(PlanTasks[Review due],$V15)="","",INDEX(PlanTasks[Review due],$V15)))} | T15: {=IF($V15="","",IF(INDEX(PlanTasks[AI practice mode],$V15)="","",INDEX(PlanTasks[AI practice mode],$V15)))} -> AI-free first | U15: {=IF($V15="","",IF(INDEX(PlanTasks[Source IDs],$V15)="","",INDEX(PlanTasks[Source IDs],$V15)))} -> S004 S023 | V15: =IF(ROW()-8>$E$4,"",MATCH($C$4&"|"&(ROW()-8),PlanTasks[Category key],0)) -> 190
A16: {=IF($V16="","",INDEX(PlanTasks[Task ID],$V16))} | B16: {=IF($V16="","",IF(INDEX(PlanTasks[Start week],$V16)="","",INDEX(PlanTasks[Start week],$V16)))} | C16: {=IF($V16="","",IF(INDEX(PlanTasks[Task / deliverable],$V16)="","",INDEX(PlanTasks[Task / deliverable],$V16)))} | D16: {=IF($V16="","",IF(INDEX(PlanTasks[Status],$V16)="","",INDEX(PlanTasks[Status],$V16)))} | E16: {=IF($V16="","",IF(INDEX(PlanTasks[Priority],$V16)="","",INDEX(PlanTasks[Priority],$V16)))} | F16: {=IF($V16="","",IF(INDEX(PlanTasks[Scope],$V16)="","",INDEX(PlanTasks[Scope],$V16)))} | G16: {=IF($V16="","",IF(INDEX(PlanTasks[Estimate (h)],$V16)="","",INDEX(PlanTasks[Estimate (h)],$V16)))} | H16: {=IF($V16="","",IF(INDEX(PlanTasks[Actual (h)],$V16)="","",INDEX(PlanTasks[Actual (h)],$V16)))} | I16: {=IF($V16="","",IF(INDEX(PlanTasks[Due date],$V16)="","",INDEX(PlanTasks[Due date],$V16)))} | J16: {=IF($V16="","",IF(INDEX(PlanTasks[Completion check],$V16)="","",INDEX(PlanTasks[Completion check],$V16)))} | K16: {=IF($V16="","",IF(INDEX(PlanTasks[Next action / blocker],$V16)="","",INDEX(PlanTasks[Next action / blocker],$V16)))} | L16: {=IF($V16="","",IF(INDEX(PlanTasks[Done when],$V16)="","",INDEX(PlanTasks[Done when],$V16)))} | M16: {=IF($V16="","",IF(INDEX(PlanTasks[Exercise / interview prompt],$V16)="","",INDEX(PlanTasks[Exercise / interview prompt],$V16)))} | N16: {=IF($V16="","",IF(INDEX(PlanTasks[Prerequisite IDs],$V16)="","",INDEX(PlanTasks[Prerequisite IDs],$V16)))} | O16: {=IF($V16="","",IF(INDEX(PlanTasks[Plan section],$V16)="","",INDEX(PlanTasks[Plan section],$V16)))} | P16: {=IF($V16="","",IF(INDEX(PlanTasks[Category],$V16)="","",INDEX(PlanTasks[Category],$V16)))} | Q16: {=IF($V16="","",IF(INDEX(PlanTasks[Evidence / result],$V16)="","",INDEX(PlanTasks[Evidence / result],$V16)))} | R16: {=IF($V16="","",IF(INDEX(PlanTasks[Completed on],$V16)="","",INDEX(PlanTasks[Completed on],$V16)))} | S16: {=IF($V16="","",IF(INDEX(PlanTasks[Review due],$V16)="","",INDEX(PlanTasks[Review due],$V16)))} | T16: {=IF($V16="","",IF(INDEX(PlanTasks[AI practice mode],$V16)="","",INDEX(PlanTasks[AI practice mode],$V16)))} | U16: {=IF($V16="","",IF(INDEX(PlanTasks[Source IDs],$V16)="","",INDEX(PlanTasks[Source IDs],$V16)))} | V16: =IF(ROW()-8>$E$4,"",MATCH($C$4&"|"&(ROW()-8),PlanTasks[Category key],0))
A17: {=IF($V17="","",INDEX(PlanTasks[Task ID],$V17))} | B17: {=IF($V17="","",IF(INDEX(PlanTasks[Start week],$V17)="","",INDEX(PlanTasks[Start week],$V17)))} | C17: {=IF($V17="","",IF(INDEX(PlanTasks[Task / deliverable],$V17)="","",INDEX(PlanTasks[Task / deliverable],$V17)))} | D17: {=IF($V17="","",IF(INDEX(PlanTasks[Status],$V17)="","",INDEX(PlanTasks[Status],$V17)))} | E17: {=IF($V17="","",IF(INDEX(PlanTasks[Priority],$V17)="","",INDEX(PlanTasks[Priority],$V17)))} | F17: {=IF($V17="","",IF(INDEX(PlanTasks[Scope],$V17)="","",INDEX(PlanTasks[Scope],$V17)))} | G17: {=IF($V17="","",IF(INDEX(PlanTasks[Estimate (h)],$V17)="","",INDEX(PlanTasks[Estimate (h)],$V17)))} | H17: {=IF($V17="","",IF(INDEX(PlanTasks[Actual (h)],$V17)="","",INDEX(PlanTasks[Actual (h)],$V17)))} | I17: {=IF($V17="","",IF(INDEX(PlanTasks[Due date],$V17)="","",INDEX(PlanTasks[Due date],$V17)))} | J17: {=IF($V17="","",IF(INDEX(PlanTasks[Completion check],$V17)="","",INDEX(PlanTasks[Completion check],$V17)))} | K17: {=IF($V17="","",IF(INDEX(PlanTasks[Next action / blocker],$V17)="","",INDEX(PlanTasks[Next action / blocker],$V17)))} | L17: {=IF($V17="","",IF(INDEX(PlanTasks[Done when],$V17)="","",INDEX(PlanTasks[Done when],$V17)))} | M17: {=IF($V17="","",IF(INDEX(PlanTasks[Exercise / interview prompt],$V17)="","",INDEX(PlanTasks[Exercise / interview prompt],$V17)))} | N17: {=IF($V17="","",IF(INDEX(PlanTasks[Prerequisite IDs],$V17)="","",INDEX(PlanTasks[Prerequisite IDs],$V17)))} | O17: {=IF($V17="","",IF(INDEX(PlanTasks[Plan section],$V17)="","",INDEX(PlanTasks[Plan section],$V17)))} | P17: {=IF($V17="","",IF(INDEX(PlanTasks[Category],$V17)="","",INDEX(PlanTasks[Category],$V17)))} | Q17: {=IF($V17="","",IF(INDEX(PlanTasks[Evidence / result],$V17)="","",INDEX(PlanTasks[Evidence / result],$V17)))} | R17: {=IF($V17="","",IF(INDEX(PlanTasks[Completed on],$V17)="","",INDEX(PlanTasks[Completed on],$V17)))} | S17: {=IF($V17="","",IF(INDEX(PlanTasks[Review due],$V17)="","",INDEX(PlanTasks[Review due],$V17)))} | T17: {=IF($V17="","",IF(INDEX(PlanTasks[AI practice mode],$V17)="","",INDEX(PlanTasks[AI practice mode],$V17)))} | U17: {=IF($V17="","",IF(INDEX(PlanTasks[Source IDs],$V17)="","",INDEX(PlanTasks[Source IDs],$V17)))} | V17: =IF(ROW()-8>$E$4,"",MATCH($C$4&"|"&(ROW()-8),PlanTasks[Category key],0))
A18: {=IF($V18="","",INDEX(PlanTasks[Task ID],$V18))} | B18: {=IF($V18="","",IF(INDEX(PlanTasks[Start week],$V18)="","",INDEX(PlanTasks[Start week],$V18)))} | C18: {=IF($V18="","",IF(INDEX(PlanTasks[Task / deliverable],$V18)="","",INDEX(PlanTasks[Task / deliverable],$V18)))} | D18: {=IF($V18="","",IF(INDEX(PlanTasks[Status],$V18)="","",INDEX(PlanTasks[Status],$V18)))} | E18: {=IF($V18="","",IF(INDEX(PlanTasks[Priority],$V18)="","",INDEX(PlanTasks[Priority],$V18)))} | F18: {=IF($V18="","",IF(INDEX(PlanTasks[Scope],$V18)="","",INDEX(PlanTasks[Scope],$V18)))} | G18: {=IF($V18="","",IF(INDEX(PlanTasks[Estimate (h)],$V18)="","",INDEX(PlanTasks[Estimate (h)],$V18)))} | H18: {=IF($V18="","",IF(INDEX(PlanTasks[Actual (h)],$V18)="","",INDEX(PlanTasks[Actual (h)],$V18)))} | I18: {=IF($V18="","",IF(INDEX(PlanTasks[Due date],$V18)="","",INDEX(PlanTasks[Due date],$V18)))} | J18: {=IF($V18="","",IF(INDEX(PlanTasks[Completion check],$V18)="","",INDEX(PlanTasks[Completion check],$V18)))} | K18: {=IF($V18="","",IF(INDEX(PlanTasks[Next action / blocker],$V18)="","",INDEX(PlanTasks[Next action / blocker],$V18)))} | L18: {=IF($V18="","",IF(INDEX(PlanTasks[Done when],$V18)="","",INDEX(PlanTasks[Done when],$V18)))} | M18: {=IF($V18="","",IF(INDEX(PlanTasks[Exercise / interview prompt],$V18)="","",INDEX(PlanTasks[Exercise / interview prompt],$V18)))} | N18: {=IF($V18="","",IF(INDEX(PlanTasks[Prerequisite IDs],$V18)="","",INDEX(PlanTasks[Prerequisite IDs],$V18)))} | O18: {=IF($V18="","",IF(INDEX(PlanTasks[Plan section],$V18)="","",INDEX(PlanTasks[Plan section],$V18)))} | P18: {=IF($V18="","",IF(INDEX(PlanTasks[Category],$V18)="","",INDEX(PlanTasks[Category],$V18)))} | Q18: {=IF($V18="","",IF(INDEX(PlanTasks[Evidence / result],$V18)="","",INDEX(PlanTasks[Evidence / result],$V18)))} | R18: {=IF($V18="","",IF(INDEX(PlanTasks[Completed on],$V18)="","",INDEX(PlanTasks[Completed on],$V18)))} | S18: {=IF($V18="","",IF(INDEX(PlanTasks[Review due],$V18)="","",INDEX(PlanTasks[Review due],$V18)))} | T18: {=IF($V18="","",IF(INDEX(PlanTasks[AI practice mode],$V18)="","",INDEX(PlanTasks[AI practice mode],$V18)))} | U18: {=IF($V18="","",IF(INDEX(PlanTasks[Source IDs],$V18)="","",INDEX(PlanTasks[Source IDs],$V18)))} | V18: =IF(ROW()-8>$E$4,"",MATCH($C$4&"|"&(ROW()-8),PlanTasks[Category key],0))
A19: {=IF($V19="","",INDEX(PlanTasks[Task ID],$V19))} | B19: {=IF($V19="","",IF(INDEX(PlanTasks[Start week],$V19)="","",INDEX(PlanTasks[Start week],$V19)))} | C19: {=IF($V19="","",IF(INDEX(PlanTasks[Task / deliverable],$V19)="","",INDEX(PlanTasks[Task / deliverable],$V19)))} | D19: {=IF($V19="","",IF(INDEX(PlanTasks[Status],$V19)="","",INDEX(PlanTasks[Status],$V19)))} | E19: {=IF($V19="","",IF(INDEX(PlanTasks[Priority],$V19)="","",INDEX(PlanTasks[Priority],$V19)))} | F19: {=IF($V19="","",IF(INDEX(PlanTasks[Scope],$V19)="","",INDEX(PlanTasks[Scope],$V19)))} | G19: {=IF($V19="","",IF(INDEX(PlanTasks[Estimate (h)],$V19)="","",INDEX(PlanTasks[Estimate (h)],$V19)))} | H19: {=IF($V19="","",IF(INDEX(PlanTasks[Actual (h)],$V19)="","",INDEX(PlanTasks[Actual (h)],$V19)))} | I19: {=IF($V19="","",IF(INDEX(PlanTasks[Due date],$V19)="","",INDEX(PlanTasks[Due date],$V19)))} | J19: {=IF($V19="","",IF(INDEX(PlanTasks[Completion check],$V19)="","",INDEX(PlanTasks[Completion check],$V19)))} | K19: {=IF($V19="","",IF(INDEX(PlanTasks[Next action / blocker],$V19)="","",INDEX(PlanTasks[Next action / blocker],$V19)))} | L19: {=IF($V19="","",IF(INDEX(PlanTasks[Done when],$V19)="","",INDEX(PlanTasks[Done when],$V19)))} | M19: {=IF($V19="","",IF(INDEX(PlanTasks[Exercise / interview prompt],$V19)="","",INDEX(PlanTasks[Exercise / interview prompt],$V19)))} | N19: {=IF($V19="","",IF(INDEX(PlanTasks[Prerequisite IDs],$V19)="","",INDEX(PlanTasks[Prerequisite IDs],$V19)))} | O19: {=IF($V19="","",IF(INDEX(PlanTasks[Plan section],$V19)="","",INDEX(PlanTasks[Plan section],$V19)))} | P19: {=IF($V19="","",IF(INDEX(PlanTasks[Category],$V19)="","",INDEX(PlanTasks[Category],$V19)))} | Q19: {=IF($V19="","",IF(INDEX(PlanTasks[Evidence / result],$V19)="","",INDEX(PlanTasks[Evidence / result],$V19)))} | R19: {=IF($V19="","",IF(INDEX(PlanTasks[Completed on],$V19)="","",INDEX(PlanTasks[Completed on],$V19)))} | S19: {=IF($V19="","",IF(INDEX(PlanTasks[Review due],$V19)="","",INDEX(PlanTasks[Review due],$V19)))} | T19: {=IF($V19="","",IF(INDEX(PlanTasks[AI practice mode],$V19)="","",INDEX(PlanTasks[AI practice mode],$V19)))} | U19: {=IF($V19="","",IF(INDEX(PlanTasks[Source IDs],$V19)="","",INDEX(PlanTasks[Source IDs],$V19)))} | V19: =IF(ROW()-8>$E$4,"",MATCH($C$4&"|"&(ROW()-8),PlanTasks[Category key],0))
A20: {=IF($V20="","",INDEX(PlanTasks[Task ID],$V20))} | B20: {=IF($V20="","",IF(INDEX(PlanTasks[Start week],$V20)="","",INDEX(PlanTasks[Start week],$V20)))} | C20: {=IF($V20="","",IF(INDEX(PlanTasks[Task / deliverable],$V20)="","",INDEX(PlanTasks[Task / deliverable],$V20)))} | D20: {=IF($V20="","",IF(INDEX(PlanTasks[Status],$V20)="","",INDEX(PlanTasks[Status],$V20)))} | E20: {=IF($V20="","",IF(INDEX(PlanTasks[Priority],$V20)="","",INDEX(PlanTasks[Priority],$V20)))} | F20: {=IF($V20="","",IF(INDEX(PlanTasks[Scope],$V20)="","",INDEX(PlanTasks[Scope],$V20)))} | G20: {=IF($V20="","",IF(INDEX(PlanTasks[Estimate (h)],$V20)="","",INDEX(PlanTasks[Estimate (h)],$V20)))} | H20: {=IF($V20="","",IF(INDEX(PlanTasks[Actual (h)],$V20)="","",INDEX(PlanTasks[Actual (h)],$V20)))} | I20: {=IF($V20="","",IF(INDEX(PlanTasks[Due date],$V20)="","",INDEX(PlanTasks[Due date],$V20)))} | J20: {=IF($V20="","",IF(INDEX(PlanTasks[Completion check],$V20)="","",INDEX(PlanTasks[Completion check],$V20)))} | K20: {=IF($V20="","",IF(INDEX(PlanTasks[Next action / blocker],$V20)="","",INDEX(PlanTasks[Next action / blocker],$V20)))} | L20: {=IF($V20="","",IF(INDEX(PlanTasks[Done when],$V20)="","",INDEX(PlanTasks[Done when],$V20)))} | M20: {=IF($V20="","",IF(INDEX(PlanTasks[Exercise / interview prompt],$V20)="","",INDEX(PlanTasks[Exercise / interview prompt],$V20)))} | N20: {=IF($V20="","",IF(INDEX(PlanTasks[Prerequisite IDs],$V20)="","",INDEX(PlanTasks[Prerequisite IDs],$V20)))} | O20: {=IF($V20="","",IF(INDEX(PlanTasks[Plan section],$V20)="","",INDEX(PlanTasks[Plan section],$V20)))} | P20: {=IF($V20="","",IF(INDEX(PlanTasks[Category],$V20)="","",INDEX(PlanTasks[Category],$V20)))} | Q20: {=IF($V20="","",IF(INDEX(PlanTasks[Evidence / result],$V20)="","",INDEX(PlanTasks[Evidence / result],$V20)))} | R20: {=IF($V20="","",IF(INDEX(PlanTasks[Completed on],$V20)="","",INDEX(PlanTasks[Completed on],$V20)))} | S20: {=IF($V20="","",IF(INDEX(PlanTasks[Review due],$V20)="","",INDEX(PlanTasks[Review due],$V20)))} | T20: {=IF($V20="","",IF(INDEX(PlanTasks[AI practice mode],$V20)="","",INDEX(PlanTasks[AI practice mode],$V20)))} | U20: {=IF($V20="","",IF(INDEX(PlanTasks[Source IDs],$V20)="","",INDEX(PlanTasks[Source IDs],$V20)))} | V20: =IF(ROW()-8>$E$4,"",MATCH($C$4&"|"&(ROW()-8),PlanTasks[Category key],0))
... A308: {=IF($V308="","",INDEX(PlanTasks[Task ID],$V308))} | B308: {=IF($V308="","",IF(INDEX(PlanTasks[Start week],$V308)="","",INDEX(PlanTasks[Start week],$V308)))} | C308: {=IF($V308="","",IF(INDEX(PlanTasks[Task / deliverable],$V308)="","",INDEX(PlanTasks[Task / deliverable],$V308)))} | D308: {=IF($V308="","",IF(INDEX(PlanTasks[Status],$V308)="","",INDEX(PlanTasks[Status],$V308)))} | E308: {=IF($V308="","",IF(INDEX(PlanTasks[Priority],$V308)="","",INDEX(PlanTasks[Priority],$V308)))} | F308: {=IF($V308="","",IF(INDEX(PlanTasks[Scope],$V308)="","",INDEX(PlanTasks[Scope],$V308)))} | G308: {=IF($V308="","",IF(INDEX(PlanTasks[Estimate (h)],$V308)="","",INDEX(PlanTasks[Estimate (h)],$V308)))} | H308: {=IF($V308="","",IF(INDEX(PlanTasks[Actual (h)],$V308)="","",INDEX(PlanTasks[Actual (h)],$V308)))} | I308: {=IF($V308="","",IF(INDEX(PlanTasks[Due date],$V308)="","",INDEX(PlanTasks[Due date],$V308)))} | J308: {=IF($V308="","",IF(INDEX(PlanTasks[Completion check],$V308)="","",INDEX(PlanTasks[Completion check],$V308)))} | K308: {=IF($V308="","",IF(INDEX(PlanTasks[Next action / blocker],$V308)="","",INDEX(PlanTasks[Next action / blocker],$V308)))} | L308: {=IF($V308="","",IF(INDEX(PlanTasks[Done when],$V308)="","",INDEX(PlanTasks[Done when],$V308)))} | M308: {=IF($V308="","",IF(INDEX(PlanTasks[Exercise / interview prompt],$V308)="","",INDEX(PlanTasks[Exercise / interview prompt],$V308)))} | N308: {=IF($V308="","",IF(INDEX(PlanTasks[Prerequisite IDs],$V308)="","",INDEX(PlanTasks[Prerequisite IDs],$V308)))} | O308: {=IF($V308="","",IF(INDEX(PlanTasks[Plan section],$V308)="","",INDEX(PlanTasks[Plan section],$V308)))} | P308: {=IF($V308="","",IF(INDEX(PlanTasks[Category],$V308)="","",INDEX(PlanTasks[Category],$V308)))} | Q308: {=IF($V308="","",IF(INDEX(PlanTasks[Evidence / result],$V308)="","",INDEX(PlanTasks[Evidence / result],$V308)))} | R308: {=IF($V308="","",IF(INDEX(PlanTasks[Completed on],$V308)="","",INDEX(PlanTasks[Completed on],$V308)))} | S308: {=IF($V308="","",IF(INDEX(PlanTasks[Review due],$V308)="","",INDEX(PlanTasks[Review due],$V308)))} | T308: {=IF($V308="","",IF(INDEX(PlanTasks[AI practice mode],$V308)="","",INDEX(PlanTasks[AI practice mode],$V308)))} | U308: {=IF($V308="","",IF(INDEX(PlanTasks[Source IDs],$V308)="","",INDEX(PlanTasks[Source IDs],$V308)))} | V308: =IF(ROW()-8>$E$4,"",MATCH($C$4&"|"&(ROW()-8),PlanTasks[Category key],0))

Sheet CS & SQL
A2: CS & SQL tasks
A4: Category | C4: CS & SQL | D4: Tasks | E4: =COUNTIFS(PlanTasks[Category],$C$4) -> 15 | F4: Complete | G4: =COUNTIFS(PlanTasks[Category],$C$4,PlanTasks[Completion check],"Complete") -> 0 | H4: Progress | I4: =IF(E4=0,"",G4/E4) -> 0
A5: Linked view. Edit the Master Plan; changes appear here automatically. Use Task ID to find the original row.
A6: =IF(E4>300,"More than 300 tasks: copy the last view row downward to show the remaining tasks.","Shows up to 300 tasks. Order follows the Master Plan.") -> Shows up to 300 tasks. Order follows the Master Plan.
A8: Task ID | B8: Start week | C8: Task / deliverable | D8: Status | E8: Priority | F8: Scope | G8: Estimate (h) | H8: Actual (h) | I8: Due date | J8: Completion check | K8: Next action / blocker | L8: Done when | M8: Exercise / interview prompt | N8: Prerequisite IDs | O8: Plan section | P8: Category | Q8: Evidence / result | R8: Completed on | S8: Review due | T8: AI practice mode | U8: Source IDs | V8: Source position
A9: {=IF($V9="","",INDEX(PlanTasks[Task ID],$V9))} -> CS12 | B9: {=IF($V9="","",IF(INDEX(PlanTasks[Start week],$V9)="","",INDEX(PlanTasks[Start week],$V9)))} -> 1 | C9: {=IF($V9="","",IF(INDEX(PlanTasks[Task / deliverable],$V9)="","",INDEX(PlanTasks[Task / deliverable],$V9)))} -> JOINs | D9: {=IF($V9="","",IF(INDEX(PlanTasks[Status],$V9)="","",INDEX(PlanTasks[Status],$V9)))} -> Not started | E9: {=IF($V9="","",IF(INDEX(PlanTasks[Priority],$V9)="","",INDEX(PlanTasks[Priority],$V9)))} -> P0 | F9: {=IF($V9="","",IF(INDEX(PlanTasks[Scope],$V9)="","",INDEX(PlanTasks[Scope],$V9)))} -> Core | G9: {=IF($V9="","",IF(INDEX(PlanTasks[Estimate (h)],$V9)="","",INDEX(PlanTasks[Estimate (h)],$V9)))} -> 0.75 | H9: {=IF($V9="","",IF(INDEX(PlanTasks[Actual (h)],$V9)="","",INDEX(PlanTasks[Actual (h)],$V9)))} -> 0 | I9: {=IF($V9="","",IF(INDEX(PlanTasks[Due date],$V9)="","",INDEX(PlanTasks[Due date],$V9)))} -> 46300 | J9: {=IF($V9="","",IF(INDEX(PlanTasks[Completion check],$V9)="","",INDEX(PlanTasks[Completion check],$V9)))} | K9: {=IF($V9="","",IF(INDEX(PlanTasks[Next action / blocker],$V9)="","",INDEX(PlanTasks[Next action / blocker],$V9)))} | L9: {=IF($V9="","",IF(INDEX(PlanTasks[Done when],$V9)="","",INDEX(PlanTasks[Done when],$V9)))} -> INNER/LEFT and multi-table reasoning JOINs, GROUP BY, HAVING, subqueries, CTEs, CASE, aggregates | M9: {=IF($V9="","",IF(INDEX(PlanTasks[Exercise / interview prompt],$V9)="","",INDEX(PlanTasks[Exercise / interview prompt],$V9)))} -> Interview: Return customers with/without orders | N9: {=IF($V9="","",IF(INDEX(PlanTasks[Prerequisite IDs],$V9)="","",INDEX(PlanTasks[Prerequisite IDs],$V9)))} | O9: {=IF($V9="","",IF(INDEX(PlanTasks[Plan section],$V9)="","",INDEX(PlanTasks[Plan section],$V9)))} -> SQL | P9: {=IF($V9="","",IF(INDEX(PlanTasks[Category],$V9)="","",INDEX(PlanTasks[Category],$V9)))} -> CS & SQL | Q9: {=IF($V9="","",IF(INDEX(PlanTasks[Evidence / result],$V9)="","",INDEX(PlanTasks[Evidence / result],$V9)))} | R9: {=IF($V9="","",IF(INDEX(PlanTasks[Completed on],$V9)="","",INDEX(PlanTasks[Completed on],$V9)))} | S9: {=IF($V9="","",IF(INDEX(PlanTasks[Review due],$V9)="","",INDEX(PlanTasks[Review due],$V9)))} | T9: {=IF($V9="","",IF(INDEX(PlanTasks[AI practice mode],$V9)="","",INDEX(PlanTasks[AI practice mode],$V9)))} -> AI-free first | U9: {=IF($V9="","",IF(INDEX(PlanTasks[Source IDs],$V9)="","",INDEX(PlanTasks[Source IDs],$V9)))} -> S020 | V9: =IF(ROW()-8>$E$4,"",MATCH($C$4&"|"&(ROW()-8),PlanTasks[Category key],0)) -> 4
A10: {=IF($V10="","",INDEX(PlanTasks[Task ID],$V10))} -> CS13 | B10: {=IF($V10="","",IF(INDEX(PlanTasks[Start week],$V10)="","",INDEX(PlanTasks[Start week],$V10)))} -> 2 | C10: {=IF($V10="","",IF(INDEX(PlanTasks[Task / deliverable],$V10)="","",INDEX(PlanTasks[Task / deliverable],$V10)))} -> GROUP BY / HAVING | D10: {=IF($V10="","",IF(INDEX(PlanTasks[Status],$V10)="","",INDEX(PlanTasks[Status],$V10)))} -> Not started | E10: {=IF($V10="","",IF(INDEX(PlanTasks[Priority],$V10)="","",INDEX(PlanTasks[Priority],$V10)))} -> P0 | F10: {=IF($V10="","",IF(INDEX(PlanTasks[Scope],$V10)="","",INDEX(PlanTasks[Scope],$V10)))} -> Core | G10: {=IF($V10="","",IF(INDEX(PlanTasks[Estimate (h)],$V10)="","",INDEX(PlanTasks[Estimate (h)],$V10)))} -> 0.75 | H10: {=IF($V10="","",IF(INDEX(PlanTasks[Actual (h)],$V10)="","",INDEX(PlanTasks[Actual (h)],$V10)))} -> 0 | I10: {=IF($V10="","",IF(INDEX(PlanTasks[Due date],$V10)="","",INDEX(PlanTasks[Due date],$V10)))} -> 46307 | J10: {=IF($V10="","",IF(INDEX(PlanTasks[Completion check],$V10)="","",INDEX(PlanTasks[Completion check],$V10)))} | K10: {=IF($V10="","",IF(INDEX(PlanTasks[Next action / blocker],$V10)="","",INDEX(PlanTasks[Next action / blocker],$V10)))} | L10: {=IF($V10="","",IF(INDEX(PlanTasks[Done when],$V10)="","",INDEX(PlanTasks[Done when],$V10)))} -> Aggregate correctly and filter grouped results | M10: {=IF($V10="","",IF(INDEX(PlanTasks[Exercise / interview prompt],$V10)="","",INDEX(PlanTasks[Exercise / interview prompt],$V10)))} -> Interview: Top customers over threshold | N10: {=IF($V10="","",IF(INDEX(PlanTasks[Prerequisite IDs],$V10)="","",INDEX(PlanTasks[Prerequisite IDs],$V10)))} | O10: {=IF($V10="","",IF(INDEX(PlanTasks[Plan section],$V10)="","",INDEX(PlanTasks[Plan section],$V10)))} -> SQL | P10: {=IF($V10="","",IF(INDEX(PlanTasks[Category],$V10)="","",INDEX(PlanTasks[Category],$V10)))} -> CS & SQL | Q10: {=IF($V10="","",IF(INDEX(PlanTasks[Evidence / result],$V10)="","",INDEX(PlanTasks[Evidence / result],$V10)))} | R10: {=IF($V10="","",IF(INDEX(PlanTasks[Completed on],$V10)="","",INDEX(PlanTasks[Completed on],$V10)))} | S10: {=IF($V10="","",IF(INDEX(PlanTasks[Review due],$V10)="","",INDEX(PlanTasks[Review due],$V10)))} | T10: {=IF($V10="","",IF(INDEX(PlanTasks[AI practice mode],$V10)="","",INDEX(PlanTasks[AI practice mode],$V10)))} -> AI-free first | U10: {=IF($V10="","",IF(INDEX(PlanTasks[Source IDs],$V10)="","",INDEX(PlanTasks[Source IDs],$V10)))} -> S020 | V10: =IF(ROW()-8>$E$4,"",MATCH($C$4&"|"&(ROW()-8),PlanTasks[Category key],0)) -> 16
A11: {=IF($V11="","",INDEX(PlanTasks[Task ID],$V11))} -> CS07 | B11: {=IF($V11="","",IF(INDEX(PlanTasks[Start week],$V11)="","",INDEX(PlanTasks[Start week],$V11)))} -> 3 | C11: {=IF($V11="","",IF(INDEX(PlanTasks[Task / deliverable],$V11)="","",INDEX(PlanTasks[Task / deliverable],$V11)))} -> ACID | D11: {=IF($V11="","",IF(INDEX(PlanTasks[Status],$V11)="","",INDEX(PlanTasks[Status],$V11)))} -> Not started | E11: {=IF($V11="","",IF(INDEX(PlanTasks[Priority],$V11)="","",INDEX(PlanTasks[Priority],$V11)))} -> P0 | F11: {=IF($V11="","",IF(INDEX(PlanTasks[Scope],$V11)="","",INDEX(PlanTasks[Scope],$V11)))} -> Core | G11: {=IF($V11="","",IF(INDEX(PlanTasks[Estimate (h)],$V11)="","",INDEX(PlanTasks[Estimate (h)],$V11)))} -> 0.75 | H11: {=IF($V11="","",IF(INDEX(PlanTasks[Actual (h)],$V11)="","",INDEX(PlanTasks[Actual (h)],$V11)))} -> 0 | I11: {=IF($V11="","",IF(INDEX(PlanTasks[Due date],$V11)="","",INDEX(PlanTasks[Due date],$V11)))} -> 46314 | J11: {=IF($V11="","",IF(INDEX(PlanTasks[Completion check],$V11)="","",INDEX(PlanTasks[Completion check],$V11)))} | K11: {=IF($V11="","",IF(INDEX(PlanTasks[Next action / blocker],$V11)="","",INDEX(PlanTasks[Next action / blocker],$V11)))} | L11: {=IF($V11="","",IF(INDEX(PlanTasks[Done when],$V11)="","",INDEX(PlanTasks[Done when],$V11)))} -> Explain each property using payment/order example | M11: {=IF($V11="","",IF(INDEX(PlanTasks[Exercise / interview prompt],$V11)="","",INDEX(PlanTasks[Exercise / interview prompt],$V11)))} -> Interview: Why do transactions matter? | N11: {=IF($V11="","",IF(INDEX(PlanTasks[Prerequisite IDs],$V11)="","",INDEX(PlanTasks[Prerequisite IDs],$V11)))} | O11: {=IF($V11="","",IF(INDEX(PlanTasks[Plan section],$V11)="","",INDEX(PlanTasks[Plan section],$V11)))} -> DBMS | P11: {=IF($V11="","",IF(INDEX(PlanTasks[Category],$V11)="","",INDEX(PlanTasks[Category],$V11)))} -> CS & SQL | Q11: {=IF($V11="","",IF(INDEX(PlanTasks[Evidence / result],$V11)="","",INDEX(PlanTasks[Evidence / result],$V11)))} | R11: {=IF($V11="","",IF(INDEX(PlanTasks[Completed on],$V11)="","",INDEX(PlanTasks[Completed on],$V11)))} | S11: {=IF($V11="","",IF(INDEX(PlanTasks[Review due],$V11)="","",INDEX(PlanTasks[Review due],$V11)))} | T11: {=IF($V11="","",IF(INDEX(PlanTasks[AI practice mode],$V11)="","",INDEX(PlanTasks[AI practice mode],$V11)))} -> AI-free first | U11: {=IF($V11="","",IF(INDEX(PlanTasks[Source IDs],$V11)="","",INDEX(PlanTasks[Source IDs],$V11)))} -> S019 | V11: =IF(ROW()-8>$E$4,"",MATCH($C$4&"|"&(ROW()-8),PlanTasks[Category key],0)) -> 26
A12: {=IF($V12="","",INDEX(PlanTasks[Task ID],$V12))} -> CS08 | B12: {=IF($V12="","",IF(INDEX(PlanTasks[Start week],$V12)="","",INDEX(PlanTasks[Start week],$V12)))} -> 3 | C12: {=IF($V12="","",IF(INDEX(PlanTasks[Task / deliverable],$V12)="","",INDEX(PlanTasks[Task / deliverable],$V12)))} -> Normalization | D12: {=IF($V12="","",IF(INDEX(PlanTasks[Status],$V12)="","",INDEX(PlanTasks[Status],$V12)))} -> Not started | E12: {=IF($V12="","",IF(INDEX(PlanTasks[Priority],$V12)="","",INDEX(PlanTasks[Priority],$V12)))} -> P1 | F12: {=IF($V12="","",IF(INDEX(PlanTasks[Scope],$V12)="","",INDEX(PlanTasks[Scope],$V12)))} -> Core | G12: {=IF($V12="","",IF(INDEX(PlanTasks[Estimate (h)],$V12)="","",INDEX(PlanTasks[Estimate (h)],$V12)))} -> 0.75 | H12: {=IF($V12="","",IF(INDEX(PlanTasks[Actual (h)],$V12)="","",INDEX(PlanTasks[Actual (h)],$V12)))} -> 0 | I12: {=IF($V12="","",IF(INDEX(PlanTasks[Due date],$V12)="","",INDEX(PlanTasks[Due date],$V12)))} -> 46314 | J12: {=IF($V12="","",IF(INDEX(PlanTasks[Completion check],$V12)="","",INDEX(PlanTasks[Completion check],$V12)))} | K12: {=IF($V12="","",IF(INDEX(PlanTasks[Next action / blocker],$V12)="","",INDEX(PlanTasks[Next action / blocker],$V12)))} | L12: {=IF($V12="","",IF(INDEX(PlanTasks[Done when],$V12)="","",INDEX(PlanTasks[Done when],$V12)))} -> 1NF/2NF/3NF and denormalization trade-offs DDL/DML, joins, constraints, indexes, transactions, isolation Schema, constraints, transactions, indexes, EXPLAIN basics 1NF–3NF reasoning, entities, cardinality, integrity | M12: {=IF($V12="","",IF(INDEX(PlanTasks[Exercise / interview prompt],$V12)="","",INDEX(PlanTasks[Exercise / interview prompt],$V12)))} -> Interview: Normalize this schema Design + query a commerce schema Schema + 20 SQL questions Shared database foundation | N12: {=IF($V12="","",IF(INDEX(PlanTasks[Prerequisite IDs],$V12)="","",INDEX(PlanTasks[Prerequisite IDs],$V12)))} | O12: {=IF($V12="","",IF(INDEX(PlanTasks[Plan section],$V12)="","",INDEX(PlanTasks[Plan section],$V12)))} -> DBMS | P12: {=IF($V12="","",IF(INDEX(PlanTasks[Category],$V12)="","",INDEX(PlanTasks[Category],$V12)))} -> CS & SQL | Q12: {=IF($V12="","",IF(INDEX(PlanTasks[Evidence / result],$V12)="","",INDEX(PlanTasks[Evidence / result],$V12)))} | R12: {=IF($V12="","",IF(INDEX(PlanTasks[Completed on],$V12)="","",INDEX(PlanTasks[Completed on],$V12)))} | S12: {=IF($V12="","",IF(INDEX(PlanTasks[Review due],$V12)="","",INDEX(PlanTasks[Review due],$V12)))} | T12: {=IF($V12="","",IF(INDEX(PlanTasks[AI practice mode],$V12)="","",INDEX(PlanTasks[AI practice mode],$V12)))} -> AI-free first | U12: {=IF($V12="","",IF(INDEX(PlanTasks[Source IDs],$V12)="","",INDEX(PlanTasks[Source IDs],$V12)))} -> S019 S004 S020 | V12: =IF(ROW()-8>$E$4,"",MATCH($C$4&"|"&(ROW()-8),PlanTasks[Category key],0)) -> 27
A13: {=IF($V13="","",INDEX(PlanTasks[Task ID],$V13))} -> CS15 | B13: {=IF($V13="","",IF(INDEX(PlanTasks[Start week],$V13)="","",INDEX(PlanTasks[Start week],$V13)))} -> 4 | C13: {=IF($V13="","",IF(INDEX(PlanTasks[Task / deliverable],$V13)="","",INDEX(PlanTasks[Task / deliverable],$V13)))} -> Process vs thread | D13: {=IF($V13="","",IF(INDEX(PlanTasks[Status],$V13)="","",INDEX(PlanTasks[Status],$V13)))} -> Not started | E13: {=IF($V13="","",IF(INDEX(PlanTasks[Priority],$V13)="","",INDEX(PlanTasks[Priority],$V13)))} -> P1 | F13: {=IF($V13="","",IF(INDEX(PlanTasks[Scope],$V13)="","",INDEX(PlanTasks[Scope],$V13)))} -> Core | G13: {=IF($V13="","",IF(INDEX(PlanTasks[Estimate (h)],$V13)="","",INDEX(PlanTasks[Estimate (h)],$V13)))} -> 0.75 | H13: {=IF($V13="","",IF(INDEX(PlanTasks[Actual (h)],$V13)="","",INDEX(PlanTasks[Actual (h)],$V13)))} -> 0 | I13: {=IF($V13="","",IF(INDEX(PlanTasks[Due date],$V13)="","",INDEX(PlanTasks[Due date],$V13)))} -> 46321 | J13: {=IF($V13="","",IF(INDEX(PlanTasks[Completion check],$V13)="","",INDEX(PlanTasks[Completion check],$V13)))} | K13: {=IF($V13="","",IF(INDEX(PlanTasks[Next action / blocker],$V13)="","",INDEX(PlanTasks[Next action / blocker],$V13)))} | L13: {=IF($V13="","",IF(INDEX(PlanTasks[Done when],$V13)="","",INDEX(PlanTasks[Done when],$V13)))} -> Address space, scheduling, shared state Process/thread, memory, scheduling, file/system basics | M13: {=IF($V13="","",IF(INDEX(PlanTasks[Exercise / interview prompt],$V13)="","",INDEX(PlanTasks[Exercise / interview prompt],$V13)))} -> Interview: Process vs thread? | N13: {=IF($V13="","",IF(INDEX(PlanTasks[Prerequisite IDs],$V13)="","",INDEX(PlanTasks[Prerequisite IDs],$V13)))} | O13: {=IF($V13="","",IF(INDEX(PlanTasks[Plan section],$V13)="","",INDEX(PlanTasks[Plan section],$V13)))} -> OS | P13: {=IF($V13="","",IF(INDEX(PlanTasks[Category],$V13)="","",INDEX(PlanTasks[Category],$V13)))} -> CS & SQL | Q13: {=IF($V13="","",IF(INDEX(PlanTasks[Evidence / result],$V13)="","",INDEX(PlanTasks[Evidence / result],$V13)))} | R13: {=IF($V13="","",IF(INDEX(PlanTasks[Completed on],$V13)="","",INDEX(PlanTasks[Completed on],$V13)))} | S13: {=IF($V13="","",IF(INDEX(PlanTasks[Review due],$V13)="","",INDEX(PlanTasks[Review due],$V13)))} | T13: {=IF($V13="","",IF(INDEX(PlanTasks[AI practice mode],$V13)="","",INDEX(PlanTasks[AI practice mode],$V13)))} -> AI-free first | U13: {=IF($V13="","",IF(INDEX(PlanTasks[Source IDs],$V13)="","",INDEX(PlanTasks[Source IDs],$V13)))} -> S019 | V13: =IF(ROW()-8>$E$4,"",MATCH($C$4&"|"&(ROW()-8),PlanTasks[Category key],0)) -> 37
A14: {=IF($V14="","",INDEX(PlanTasks[Task ID],$V14))} -> CS18 | B14: {=IF($V14="","",IF(INDEX(PlanTasks[Start week],$V14)="","",INDEX(PlanTasks[Start week],$V14)))} -> 5 | C14: {=IF($V14="","",IF(INDEX(PlanTasks[Task / deliverable],$V14)="","",INDEX(PlanTasks[Task / deliverable],$V14)))} -> TCP vs UDP | D14: {=IF($V14="","",IF(INDEX(PlanTasks[Status],$V14)="","",INDEX(PlanTasks[Status],$V14)))} -> Not started | E14: {=IF($V14="","",IF(INDEX(PlanTasks[Priority],$V14)="","",INDEX(PlanTasks[Priority],$V14)))} -> P1 | F14: {=IF($V14="","",IF(INDEX(PlanTasks[Scope],$V14)="","",INDEX(PlanTasks[Scope],$V14)))} -> Core | G14: {=IF($V14="","",IF(INDEX(PlanTasks[Estimate (h)],$V14)="","",INDEX(PlanTasks[Estimate (h)],$V14)))} -> 0.75 | H14: {=IF($V14="","",IF(INDEX(PlanTasks[Actual (h)],$V14)="","",INDEX(PlanTasks[Actual (h)],$V14)))} -> 0 | I14: {=IF($V14="","",IF(INDEX(PlanTasks[Due date],$V14)="","",INDEX(PlanTasks[Due date],$V14)))} -> 46328 | J14: {=IF($V14="","",IF(INDEX(PlanTasks[Completion check],$V14)="","",INDEX(PlanTasks[Completion check],$V14)))} | K14: {=IF($V14="","",IF(INDEX(PlanTasks[Next action / blocker],$V14)="","",INDEX(PlanTasks[Next action / blocker],$V14)))} | L14: {=IF($V14="","",IF(INDEX(PlanTasks[Done when],$V14)="","",INDEX(PlanTasks[Done when],$V14)))} -> Reliability/order vs lower overhead TCP/UDP, DNS, HTTP/HTTPS, latency | M14: {=IF($V14="","",IF(INDEX(PlanTasks[Exercise / interview prompt],$V14)="","",INDEX(PlanTasks[Exercise / interview prompt],$V14)))} -> Interview: When choose UDP? | N14: {=IF($V14="","",IF(INDEX(PlanTasks[Prerequisite IDs],$V14)="","",INDEX(PlanTasks[Prerequisite IDs],$V14)))} | O14: {=IF($V14="","",IF(INDEX(PlanTasks[Plan section],$V14)="","",INDEX(PlanTasks[Plan section],$V14)))} -> Networking | P14: {=IF($V14="","",IF(INDEX(PlanTasks[Category],$V14)="","",INDEX(PlanTasks[Category],$V14)))} -> CS & SQL | Q14: {=IF($V14="","",IF(INDEX(PlanTasks[Evidence / result],$V14)="","",INDEX(PlanTasks[Evidence / result],$V14)))} | R14: {=IF($V14="","",IF(INDEX(PlanTasks[Completed on],$V14)="","",INDEX(PlanTasks[Completed on],$V14)))} | S14: {=IF($V14="","",IF(INDEX(PlanTasks[Review due],$V14)="","",INDEX(PlanTasks[Review due],$V14)))} | T14: {=IF($V14="","",IF(INDEX(PlanTasks[AI practice mode],$V14)="","",INDEX(PlanTasks[AI practice mode],$V14)))} -> AI-free first | U14: {=IF($V14="","",IF(INDEX(PlanTasks[Source IDs],$V14)="","",INDEX(PlanTasks[Source IDs],$V14)))} -> S019 | V14: =IF(ROW()-8>$E$4,"",MATCH($C$4&"|"&(ROW()-8),PlanTasks[Category key],0)) -> 51
A15: {=IF($V15="","",INDEX(PlanTasks[Task ID],$V15))} -> CS19 | B15: {=IF($V15="","",IF(INDEX(PlanTasks[Start week],$V15)="","",INDEX(PlanTasks[Start week],$V15)))} -> 5 | C15: {=IF($V15="","",IF(INDEX(PlanTasks[Task / deliverable],$V15)="","",INDEX(PlanTasks[Task / deliverable],$V15)))} -> DNS | D15: {=IF($V15="","",IF(INDEX(PlanTasks[Status],$V15)="","",INDEX(PlanTasks[Status],$V15)))} -> Not started | E15: {=IF($V15="","",IF(INDEX(PlanTasks[Priority],$V15)="","",INDEX(PlanTasks[Priority],$V15)))} -> P1 | F15: {=IF($V15="","",IF(INDEX(PlanTasks[Scope],$V15)="","",INDEX(PlanTasks[Scope],$V15)))} -> Core | G15: {=IF($V15="","",IF(INDEX(PlanTasks[Estimate (h)],$V15)="","",INDEX(PlanTasks[Estimate (h)],$V15)))} -> 0.75 | H15: {=IF($V15="","",IF(INDEX(PlanTasks[Actual (h)],$V15)="","",INDEX(PlanTasks[Actual (h)],$V15)))} -> 0 | I15: {=IF($V15="","",IF(INDEX(PlanTasks[Due date],$V15)="","",INDEX(PlanTasks[Due date],$V15)))} -> 46328 | J15: {=IF($V15="","",IF(INDEX(PlanTasks[Completion check],$V15)="","",INDEX(PlanTasks[Completion check],$V15)))} | K15: {=IF($V15="","",IF(INDEX(PlanTasks[Next action / blocker],$V15)="","",INDEX(PlanTasks[Next action / blocker],$V15)))} | L15: {=IF($V15="","",IF(INDEX(PlanTasks[Done when],$V15)="","",INDEX(PlanTasks[Done when],$V15)))} -> Resolve name to IP, caching concept | M15: {=IF($V15="","",IF(INDEX(PlanTasks[Exercise / interview prompt],$V15)="","",INDEX(PlanTasks[Exercise / interview prompt],$V15)))} -> Interview: What happens after entering a URL? | N15: {=IF($V15="","",IF(INDEX(PlanTasks[Prerequisite IDs],$V15)="","",INDEX(PlanTasks[Prerequisite IDs],$V15)))} | O15: {=IF($V15="","",IF(INDEX(PlanTasks[Plan section],$V15)="","",INDEX(PlanTasks[Plan section],$V15)))} -> Networking | P15: {=IF($V15="","",IF(INDEX(PlanTasks[Category],$V15)="","",INDEX(PlanTasks[Category],$V15)))} -> CS & SQL | Q15: {=IF($V15="","",IF(INDEX(PlanTasks[Evidence / result],$V15)="","",INDEX(PlanTasks[Evidence / result],$V15)))} | R15: {=IF($V15="","",IF(INDEX(PlanTasks[Completed on],$V15)="","",INDEX(PlanTasks[Completed on],$V15)))} | S15: {=IF($V15="","",IF(INDEX(PlanTasks[Review due],$V15)="","",INDEX(PlanTasks[Review due],$V15)))} | T15: {=IF($V15="","",IF(INDEX(PlanTasks[AI practice mode],$V15)="","",INDEX(PlanTasks[AI practice mode],$V15)))} -> AI-free first | U15: {=IF($V15="","",IF(INDEX(PlanTasks[Source IDs],$V15)="","",INDEX(PlanTasks[Source IDs],$V15)))} -> S019 | V15: =IF(ROW()-8>$E$4,"",MATCH($C$4&"|"&(ROW()-8),PlanTasks[Category key],0)) -> 52
A16: {=IF($V16="","",INDEX(PlanTasks[Task ID],$V16))} -> CS20 | B16: {=IF($V16="","",IF(INDEX(PlanTasks[Start week],$V16)="","",INDEX(PlanTasks[Start week],$V16)))} -> 5 | C16: {=IF($V16="","",IF(INDEX(PlanTasks[Task / deliverable],$V16)="","",INDEX(PlanTasks[Task / deliverable],$V16)))} -> HTTP | D16: {=IF($V16="","",IF(INDEX(PlanTasks[Status],$V16)="","",INDEX(PlanTasks[Status],$V16)))} -> Not started | E16: {=IF($V16="","",IF(INDEX(PlanTasks[Priority],$V16)="","",INDEX(PlanTasks[Priority],$V16)))} -> P0 | F16: {=IF($V16="","",IF(INDEX(PlanTasks[Scope],$V16)="","",INDEX(PlanTasks[Scope],$V16)))} -> Core | G16: {=IF($V16="","",IF(INDEX(PlanTasks[Estimate (h)],$V16)="","",INDEX(PlanTasks[Estimate (h)],$V16)))} -> 0.75 | H16: {=IF($V16="","",IF(INDEX(PlanTasks[Actual (h)],$V16)="","",INDEX(PlanTasks[Actual (h)],$V16)))} -> 0 | I16: {=IF($V16="","",IF(INDEX(PlanTasks[Due date],$V16)="","",INDEX(PlanTasks[Due date],$V16)))} -> 46328 | J16: {=IF($V16="","",IF(INDEX(PlanTasks[Completion check],$V16)="","",INDEX(PlanTasks[Completion check],$V16)))} | K16: {=IF($V16="","",IF(INDEX(PlanTasks[Next action / blocker],$V16)="","",INDEX(PlanTasks[Next action / blocker],$V16)))} | L16: {=IF($V16="","",IF(INDEX(PlanTasks[Done when],$V16)="","",INDEX(PlanTasks[Done when],$V16)))} -> Methods, status codes, idempotency, headers Methods, headers, cookies, CORS, TLS, caching | M16: {=IF($V16="","",IF(INDEX(PlanTasks[Exercise / interview prompt],$V16)="","",INDEX(PlanTasks[Exercise / interview prompt],$V16)))} -> Interview: PUT vs PATCH? 401 vs 403? | N16: {=IF($V16="","",IF(INDEX(PlanTasks[Prerequisite IDs],$V16)="","",INDEX(PlanTasks[Prerequisite IDs],$V16)))} | O16: {=IF($V16="","",IF(INDEX(PlanTasks[Plan section],$V16)="","",INDEX(PlanTasks[Plan section],$V16)))} -> Networking | P16: {=IF($V16="","",IF(INDEX(PlanTasks[Category],$V16)="","",INDEX(PlanTasks[Category],$V16)))} -> CS & SQL | Q16: {=IF($V16="","",IF(INDEX(PlanTasks[Evidence / result],$V16)="","",INDEX(PlanTasks[Evidence / result],$V16)))} | R16: {=IF($V16="","",IF(INDEX(PlanTasks[Completed on],$V16)="","",INDEX(PlanTasks[Completed on],$V16)))} | S16: {=IF($V16="","",IF(INDEX(PlanTasks[Review due],$V16)="","",INDEX(PlanTasks[Review due],$V16)))} | T16: {=IF($V16="","",IF(INDEX(PlanTasks[AI practice mode],$V16)="","",INDEX(PlanTasks[AI practice mode],$V16)))} -> AI-free first | U16: {=IF($V16="","",IF(INDEX(PlanTasks[Source IDs],$V16)="","",INDEX(PlanTasks[Source IDs],$V16)))} -> S019 S022 | V16: =IF(ROW()-8>$E$4,"",MATCH($C$4&"|"&(ROW()-8),PlanTasks[Category key],0)) -> 53
A17: {=IF($V17="","",INDEX(PlanTasks[Task ID],$V17))} -> CS21 | B17: {=IF($V17="","",IF(INDEX(PlanTasks[Start week],$V17)="","",INDEX(PlanTasks[Start week],$V17)))} -> 6 | C17: {=IF($V17="","",IF(INDEX(PlanTasks[Task / deliverable],$V17)="","",INDEX(PlanTasks[Task / deliverable],$V17)))} -> HTTPS/TLS | D17: {=IF($V17="","",IF(INDEX(PlanTasks[Status],$V17)="","",INDEX(PlanTasks[Status],$V17)))} -> Not started | E17: {=IF($V17="","",IF(INDEX(PlanTasks[Priority],$V17)="","",INDEX(PlanTasks[Priority],$V17)))} -> P1 | F17: {=IF($V17="","",IF(INDEX(PlanTasks[Scope],$V17)="","",INDEX(PlanTasks[Scope],$V17)))} -> Core | G17: {=IF($V17="","",IF(INDEX(PlanTasks[Estimate (h)],$V17)="","",INDEX(PlanTasks[Estimate (h)],$V17)))} -> 0.75 | H17: {=IF($V17="","",IF(INDEX(PlanTasks[Actual (h)],$V17)="","",INDEX(PlanTasks[Actual (h)],$V17)))} -> 0 | I17: {=IF($V17="","",IF(INDEX(PlanTasks[Due date],$V17)="","",INDEX(PlanTasks[Due date],$V17)))} -> 46335 | J17: {=IF($V17="","",IF(INDEX(PlanTasks[Completion check],$V17)="","",INDEX(PlanTasks[Completion check],$V17)))} | K17: {=IF($V17="","",IF(INDEX(PlanTasks[Next action / blocker],$V17)="","",INDEX(PlanTasks[Next action / blocker],$V17)))} | L17: {=IF($V17="","",IF(INDEX(PlanTasks[Done when],$V17)="","",INDEX(PlanTasks[Done when],$V17)))} -> Encryption/authentication concept, certificates | M17: {=IF($V17="","",IF(INDEX(PlanTasks[Exercise / interview prompt],$V17)="","",INDEX(PlanTasks[Exercise / interview prompt],$V17)))} -> Interview: How does HTTPS protect traffic? | N17: {=IF($V17="","",IF(INDEX(PlanTasks[Prerequisite IDs],$V17)="","",INDEX(PlanTasks[Prerequisite IDs],$V17)))} | O17: {=IF($V17="","",IF(INDEX(PlanTasks[Plan section],$V17)="","",INDEX(PlanTasks[Plan section],$V17)))} -> Networking | P17: {=IF($V17="","",IF(INDEX(PlanTasks[Category],$V17)="","",INDEX(PlanTasks[Category],$V17)))} -> CS & SQL | Q17: {=IF($V17="","",IF(INDEX(PlanTasks[Evidence / result],$V17)="","",INDEX(PlanTasks[Evidence / result],$V17)))} | R17: {=IF($V17="","",IF(INDEX(PlanTasks[Completed on],$V17)="","",INDEX(PlanTasks[Completed on],$V17)))} | S17: {=IF($V17="","",IF(INDEX(PlanTasks[Review due],$V17)="","",INDEX(PlanTasks[Review due],$V17)))} | T17: {=IF($V17="","",IF(INDEX(PlanTasks[AI practice mode],$V17)="","",INDEX(PlanTasks[AI practice mode],$V17)))} -> AI-free first | U17: {=IF($V17="","",IF(INDEX(PlanTasks[Source IDs],$V17)="","",INDEX(PlanTasks[Source IDs],$V17)))} -> S022 | V17: =IF(ROW()-8>$E$4,"",MATCH($C$4&"|"&(ROW()-8),PlanTasks[Category key],0)) -> 65
A18: {=IF($V18="","",INDEX(PlanTasks[Task ID],$V18))} -> CS14 | B18: {=IF($V18="","",IF(INDEX(PlanTasks[Start week],$V18)="","",INDEX(PlanTasks[Start week],$V18)))} -> 7 | C18: {=IF($V18="","",IF(INDEX(PlanTasks[Task / deliverable],$V18)="","",INDEX(PlanTasks[Task / deliverable],$V18)))} -> CTEs/subqueries/window awareness | D18: {=IF($V18="","",IF(INDEX(PlanTasks[Status],$V18)="","",INDEX(PlanTasks[Status],$V18)))} -> Not started | E18: {=IF($V18="","",IF(INDEX(PlanTasks[Priority],$V18)="","",INDEX(PlanTasks[Priority],$V18)))} -> P1 | F18: {=IF($V18="","",IF(INDEX(PlanTasks[Scope],$V18)="","",INDEX(PlanTasks[Scope],$V18)))} -> Core | G18: {=IF($V18="","",IF(INDEX(PlanTasks[Estimate (h)],$V18)="","",INDEX(PlanTasks[Estimate (h)],$V18)))} -> 0.75 | H18: {=IF($V18="","",IF(INDEX(PlanTasks[Actual (h)],$V18)="","",INDEX(PlanTasks[Actual (h)],$V18)))} -> 0 | I18: {=IF($V18="","",IF(INDEX(PlanTasks[Due date],$V18)="","",INDEX(PlanTasks[Due date],$V18)))} -> 46342 | J18: {=IF($V18="","",IF(INDEX(PlanTasks[Completion check],$V18)="","",INDEX(PlanTasks[Completion check],$V18)))} | K18: {=IF($V18="","",IF(INDEX(PlanTasks[Next action / blocker],$V18)="","",INDEX(PlanTasks[Next action / blocker],$V18)))} | L18: {=IF($V18="","",IF(INDEX(PlanTasks[Done when],$V18)="","",INDEX(PlanTasks[Done when],$V18)))} -> Break complex queries into understandable steps | M18: {=IF($V18="","",IF(INDEX(PlanTasks[Exercise / interview prompt],$V18)="","",INDEX(PlanTasks[Exercise / interview prompt],$V18)))} -> Interview: Latest order per customer? | N18: {=IF($V18="","",IF(INDEX(PlanTasks[Prerequisite IDs],$V18)="","",INDEX(PlanTasks[Prerequisite IDs],$V18)))} | O18: {=IF($V18="","",IF(INDEX(PlanTasks[Plan section],$V18)="","",INDEX(PlanTasks[Plan section],$V18)))} -> SQL | P18: {=IF($V18="","",IF(INDEX(PlanTasks[Category],$V18)="","",INDEX(PlanTasks[Category],$V18)))} -> CS & SQL | Q18: {=IF($V18="","",IF(INDEX(PlanTasks[Evidence / result],$V18)="","",INDEX(PlanTasks[Evidence / result],$V18)))} | R18: {=IF($V18="","",IF(INDEX(PlanTasks[Completed on],$V18)="","",INDEX(PlanTasks[Completed on],$V18)))} | S18: {=IF($V18="","",IF(INDEX(PlanTasks[Review due],$V18)="","",INDEX(PlanTasks[Review due],$V18)))} | T18: {=IF($V18="","",IF(INDEX(PlanTasks[AI practice mode],$V18)="","",INDEX(PlanTasks[AI practice mode],$V18)))} -> AI-free first | U18: {=IF($V18="","",IF(INDEX(PlanTasks[Source IDs],$V18)="","",INDEX(PlanTasks[Source IDs],$V18)))} -> S020 | V18: =IF(ROW()-8>$E$4,"",MATCH($C$4&"|"&(ROW()-8),PlanTasks[Category key],0)) -> 75
A19: {=IF($V19="","",INDEX(PlanTasks[Task ID],$V19))} -> G05 | B19: {=IF($V19="","",IF(INDEX(PlanTasks[Start week],$V19)="","",INDEX(PlanTasks[Start week],$V19)))} -> 7 | C19: {=IF($V19="","",IF(INDEX(PlanTasks[Task / deliverable],$V19)="","",INDEX(PlanTasks[Task / deliverable],$V19)))} -> Practice window functions, NULLs and duplicate-sensitive joins | D19: {=IF($V19="","",IF(INDEX(PlanTasks[Status],$V19)="","",INDEX(PlanTasks[Status],$V19)))} -> Not started | E19: {=IF($V19="","",IF(INDEX(PlanTasks[Priority],$V19)="","",INDEX(PlanTasks[Priority],$V19)))} -> P1 | F19: {=IF($V19="","",IF(INDEX(PlanTasks[Scope],$V19)="","",INDEX(PlanTasks[Scope],$V19)))} -> Core | G19: {=IF($V19="","",IF(INDEX(PlanTasks[Estimate (h)],$V19)="","",INDEX(PlanTasks[Estimate (h)],$V19)))} -> 1 | H19: {=IF($V19="","",IF(INDEX(PlanTasks[Actual (h)],$V19)="","",INDEX(PlanTasks[Actual (h)],$V19)))} -> 0 | I19: {=IF($V19="","",IF(INDEX(PlanTasks[Due date],$V19)="","",INDEX(PlanTasks[Due date],$V19)))} -> 46342 | J19: {=IF($V19="","",IF(INDEX(PlanTasks[Completion check],$V19)="","",INDEX(PlanTasks[Completion check],$V19)))} | K19: {=IF($V19="","",IF(INDEX(PlanTasks[Next action / blocker],$V19)="","",INDEX(PlanTasks[Next action / blocker],$V19)))} | L19: {=IF($V19="","",IF(INDEX(PlanTasks[Done when],$V19)="","",INDEX(PlanTasks[Done when],$V19)))} -> Solve latest-row-per-group, ranking and running totals. Show how ties, NULLs and duplicate join keys affect the result. | M19: {=IF($V19="","",IF(INDEX(PlanTasks[Exercise / interview prompt],$V19)="","",INDEX(PlanTasks[Exercise / interview prompt],$V19)))} | N19: {=IF($V19="","",IF(INDEX(PlanTasks[Prerequisite IDs],$V19)="","",INDEX(PlanTasks[Prerequisite IDs],$V19)))} -> CS12 | O19: {=IF($V19="","",IF(INDEX(PlanTasks[Plan section],$V19)="","",INDEX(PlanTasks[Plan section],$V19)))} -> Gap closure | P19: {=IF($V19="","",IF(INDEX(PlanTasks[Category],$V19)="","",INDEX(PlanTasks[Category],$V19)))} -> CS & SQL | Q19: {=IF($V19="","",IF(INDEX(PlanTasks[Evidence / result],$V19)="","",INDEX(PlanTasks[Evidence / result],$V19)))} | R19: {=IF($V19="","",IF(INDEX(PlanTasks[Completed on],$V19)="","",INDEX(PlanTasks[Completed on],$V19)))} | S19: {=IF($V19="","",IF(INDEX(PlanTasks[Review due],$V19)="","",INDEX(PlanTasks[Review due],$V19)))} | T19: {=IF($V19="","",IF(INDEX(PlanTasks[AI practice mode],$V19)="","",INDEX(PlanTasks[AI practice mode],$V19)))} -> AI-free first | U19: {=IF($V19="","",IF(INDEX(PlanTasks[Source IDs],$V19)="","",INDEX(PlanTasks[Source IDs],$V19)))} -> S031 | V19: =IF(ROW()-8>$E$4,"",MATCH($C$4&"|"&(ROW()-8),PlanTasks[Category key],0)) -> 81
A20: {=IF($V20="","",INDEX(PlanTasks[Task ID],$V20))} -> CS09 | B20: {=IF($V20="","",IF(INDEX(PlanTasks[Start week],$V20)="","",INDEX(PlanTasks[Start week],$V20)))} -> 9 | C20: {=IF($V20="","",IF(INDEX(PlanTasks[Task / deliverable],$V20)="","",INDEX(PlanTasks[Task / deliverable],$V20)))} -> Indexes | D20: {=IF($V20="","",IF(INDEX(PlanTasks[Status],$V20)="","",INDEX(PlanTasks[Status],$V20)))} -> Not started | E20: {=IF($V20="","",IF(INDEX(PlanTasks[Priority],$V20)="","",INDEX(PlanTasks[Priority],$V20)))} -> P0 | F20: {=IF($V20="","",IF(INDEX(PlanTasks[Scope],$V20)="","",INDEX(PlanTasks[Scope],$V20)))} -> Core | G20: {=IF($V20="","",IF(INDEX(PlanTasks[Estimate (h)],$V20)="","",INDEX(PlanTasks[Estimate (h)],$V20)))} -> 0.75 | H20: {=IF($V20="","",IF(INDEX(PlanTasks[Actual (h)],$V20)="","",INDEX(PlanTasks[Actual (h)],$V20)))} -> 0 | I20: {=IF($V20="","",IF(INDEX(PlanTasks[Due date],$V20)="","",INDEX(PlanTasks[Due date],$V20)))} -> 46356 | J20: {=IF($V20="","",IF(INDEX(PlanTasks[Completion check],$V20)="","",INDEX(PlanTasks[Completion check],$V20)))} | K20: {=IF($V20="","",IF(INDEX(PlanTasks[Next action / blocker],$V20)="","",INDEX(PlanTasks[Next action / blocker],$V20)))} | L20: {=IF($V20="","",IF(INDEX(PlanTasks[Done when],$V20)="","",INDEX(PlanTasks[Done when],$V20)))} -> B-tree concept, selectivity, composite order Choose indexes, composite order, scan trade-offs | M20: {=IF($V20="","",IF(INDEX(PlanTasks[Exercise / interview prompt],$V20)="","",INDEX(PlanTasks[Exercise / interview prompt],$V20)))} -> Interview: Why is this query slow? | N20: {=IF($V20="","",IF(INDEX(PlanTasks[Prerequisite IDs],$V20)="","",INDEX(PlanTasks[Prerequisite IDs],$V20)))} | O20: {=IF($V20="","",IF(INDEX(PlanTasks[Plan section],$V20)="","",INDEX(PlanTasks[Plan section],$V20)))} -> DBMS | P20: {=IF($V20="","",IF(INDEX(PlanTasks[Category],$V20)="","",INDEX(PlanTasks[Category],$V20)))} -> CS & SQL | Q20: {=IF($V20="","",IF(INDEX(PlanTasks[Evidence / result],$V20)="","",INDEX(PlanTasks[Evidence / result],$V20)))} | R20: {=IF($V20="","",IF(INDEX(PlanTasks[Completed on],$V20)="","",INDEX(PlanTasks[Completed on],$V20)))} | S20: {=IF($V20="","",IF(INDEX(PlanTasks[Review due],$V20)="","",INDEX(PlanTasks[Review due],$V20)))} | T20: {=IF($V20="","",IF(INDEX(PlanTasks[AI practice mode],$V20)="","",INDEX(PlanTasks[AI practice mode],$V20)))} -> AI-free first | U20: {=IF($V20="","",IF(INDEX(PlanTasks[Source IDs],$V20)="","",INDEX(PlanTasks[Source IDs],$V20)))} -> S020 S026 | V20: =IF(ROW()-8>$E$4,"",MATCH($C$4&"|"&(ROW()-8),PlanTasks[Category key],0)) -> 94
... A308: {=IF($V308="","",INDEX(PlanTasks[Task ID],$V308))} | B308: {=IF($V308="","",IF(INDEX(PlanTasks[Start week],$V308)="","",INDEX(PlanTasks[Start week],$V308)))} | C308: {=IF($V308="","",IF(INDEX(PlanTasks[Task / deliverable],$V308)="","",INDEX(PlanTasks[Task / deliverable],$V308)))} | D308: {=IF($V308="","",IF(INDEX(PlanTasks[Status],$V308)="","",INDEX(PlanTasks[Status],$V308)))} | E308: {=IF($V308="","",IF(INDEX(PlanTasks[Priority],$V308)="","",INDEX(PlanTasks[Priority],$V308)))} | F308: {=IF($V308="","",IF(INDEX(PlanTasks[Scope],$V308)="","",INDEX(PlanTasks[Scope],$V308)))} | G308: {=IF($V308="","",IF(INDEX(PlanTasks[Estimate (h)],$V308)="","",INDEX(PlanTasks[Estimate (h)],$V308)))} | H308: {=IF($V308="","",IF(INDEX(PlanTasks[Actual (h)],$V308)="","",INDEX(PlanTasks[Actual (h)],$V308)))} | I308: {=IF($V308="","",IF(INDEX(PlanTasks[Due date],$V308)="","",INDEX(PlanTasks[Due date],$V308)))} | J308: {=IF($V308="","",IF(INDEX(PlanTasks[Completion check],$V308)="","",INDEX(PlanTasks[Completion check],$V308)))} | K308: {=IF($V308="","",IF(INDEX(PlanTasks[Next action / blocker],$V308)="","",INDEX(PlanTasks[Next action / blocker],$V308)))} | L308: {=IF($V308="","",IF(INDEX(PlanTasks[Done when],$V308)="","",INDEX(PlanTasks[Done when],$V308)))} | M308: {=IF($V308="","",IF(INDEX(PlanTasks[Exercise / interview prompt],$V308)="","",INDEX(PlanTasks[Exercise / interview prompt],$V308)))} | N308: {=IF($V308="","",IF(INDEX(PlanTasks[Prerequisite IDs],$V308)="","",INDEX(PlanTasks[Prerequisite IDs],$V308)))} | O308: {=IF($V308="","",IF(INDEX(PlanTasks[Plan section],$V308)="","",INDEX(PlanTasks[Plan section],$V308)))} | P308: {=IF($V308="","",IF(INDEX(PlanTasks[Category],$V308)="","",INDEX(PlanTasks[Category],$V308)))} | Q308: {=IF($V308="","",IF(INDEX(PlanTasks[Evidence / result],$V308)="","",INDEX(PlanTasks[Evidence / result],$V308)))} | R308: {=IF($V308="","",IF(INDEX(PlanTasks[Completed on],$V308)="","",INDEX(PlanTasks[Completed on],$V308)))} | S308: {=IF($V308="","",IF(INDEX(PlanTasks[Review due],$V308)="","",INDEX(PlanTasks[Review due],$V308)))} | T308: {=IF($V308="","",IF(INDEX(PlanTasks[AI practice mode],$V308)="","",INDEX(PlanTasks[AI practice mode],$V308)))} | U308: {=IF($V308="","",IF(INDEX(PlanTasks[Source IDs],$V308)="","",INDEX(PlanTasks[Source IDs],$V308)))} | V308: =IF(ROW()-8>$E$4,"",MATCH($C$4&"|"&(ROW()-8),PlanTasks[Category key],0))

Sheet Java & Spring
A2: Java & Spring tasks
A4: Category | C4: Java & Spring | D4: Tasks | E4: =COUNTIFS(PlanTasks[Category],$C$4) -> 31 | F4: Complete | G4: =COUNTIFS(PlanTasks[Category],$C$4,PlanTasks[Completion check],"Complete") -> 0 | H4: Progress | I4: =IF(E4=0,"",G4/E4) -> 0
A5: Linked view. Edit the Master Plan; changes appear here automatically. Use Task ID to find the original row.
A6: =IF(E4>300,"More than 300 tasks: copy the last view row downward to show the remaining tasks.","Shows up to 300 tasks. Order follows the Master Plan.") -> Shows up to 300 tasks. Order follows the Master Plan.
A8: Task ID | B8: Start week | C8: Task / deliverable | D8: Status | E8: Priority | F8: Scope | G8: Estimate (h) | H8: Actual (h) | I8: Due date | J8: Completion check | K8: Next action / blocker | L8: Done when | M8: Exercise / interview prompt | N8: Prerequisite IDs | O8: Plan section | P8: Category | Q8: Evidence / result | R8: Completed on | S8: Review due | T8: AI practice mode | U8: Source IDs | V8: Source position
A9: {=IF($V9="","",INDEX(PlanTasks[Task ID],$V9))} -> JA05 | B9: {=IF($V9="","",IF(INDEX(PlanTasks[Start week],$V9)="","",INDEX(PlanTasks[Start week],$V9)))} -> 1 | C9: {=IF($V9="","",IF(INDEX(PlanTasks[Task / deliverable],$V9)="","",INDEX(PlanTasks[Task / deliverable],$V9)))} -> Syntax + object model | D9: {=IF($V9="","",IF(INDEX(PlanTasks[Status],$V9)="","",INDEX(PlanTasks[Status],$V9)))} -> Not started | E9: {=IF($V9="","",IF(INDEX(PlanTasks[Priority],$V9)="","",INDEX(PlanTasks[Priority],$V9)))} -> P0 | F9: {=IF($V9="","",IF(INDEX(PlanTasks[Scope],$V9)="","",INDEX(PlanTasks[Scope],$V9)))} -> Core | G9: {=IF($V9="","",IF(INDEX(PlanTasks[Estimate (h)],$V9)="","",INDEX(PlanTasks[Estimate (h)],$V9)))} -> 0.75 | H9: {=IF($V9="","",IF(INDEX(PlanTasks[Actual (h)],$V9)="","",INDEX(PlanTasks[Actual (h)],$V9)))} -> 0 | I9: {=IF($V9="","",IF(INDEX(PlanTasks[Due date],$V9)="","",INDEX(PlanTasks[Due date],$V9)))} -> 46300 | J9: {=IF($V9="","",IF(INDEX(PlanTasks[Completion check],$V9)="","",INDEX(PlanTasks[Completion check],$V9)))} | K9: {=IF($V9="","",IF(INDEX(PlanTasks[Next action / blocker],$V9)="","",INDEX(PlanTasks[Next action / blocker],$V9)))} | L9: {=IF($V9="","",IF(INDEX(PlanTasks[Done when],$V9)="","",INDEX(PlanTasks[Done when],$V9)))} -> types, references, methods, packages, access modifiers OOP, collections, generics, exceptions, streams, records, sealed classes Write clean Java; primitives/references, methods, packages, exceptions | M9: {=IF($V9="","",IF(INDEX(PlanTasks[Exercise / interview prompt],$V9)="","",INDEX(PlanTasks[Exercise / interview prompt],$V9)))} -> 20 small Java drills Interview: primitive vs reference? pass-by-value? Implement a domain service and explain object/model choices Build Java kata + service layer Primary backend language Complete 20 Java coding drills | N9: {=IF($V9="","",IF(INDEX(PlanTasks[Prerequisite IDs],$V9)="","",INDEX(PlanTasks[Prerequisite IDs],$V9)))} | O9: {=IF($V9="","",IF(INDEX(PlanTasks[Plan section],$V9)="","",INDEX(PlanTasks[Plan section],$V9)))} -> Java Core | P9: {=IF($V9="","",IF(INDEX(PlanTasks[Category],$V9)="","",INDEX(PlanTasks[Category],$V9)))} -> Java & Spring | Q9: {=IF($V9="","",IF(INDEX(PlanTasks[Evidence / result],$V9)="","",INDEX(PlanTasks[Evidence / result],$V9)))} | R9: {=IF($V9="","",IF(INDEX(PlanTasks[Completed on],$V9)="","",INDEX(PlanTasks[Completed on],$V9)))} | S9: {=IF($V9="","",IF(INDEX(PlanTasks[Review due],$V9)="","",INDEX(PlanTasks[Review due],$V9)))} | T9: {=IF($V9="","",IF(INDEX(PlanTasks[AI practice mode],$V9)="","",INDEX(PlanTasks[AI practice mode],$V9)))} -> AI-free first | U9: {=IF($V9="","",IF(INDEX(PlanTasks[Source IDs],$V9)="","",INDEX(PlanTasks[Source IDs],$V9)))} -> S001 | V9: =IF(ROW()-8>$E$4,"",MATCH($C$4&"|"&(ROW()-8),PlanTasks[Category key],0)) -> 5
A10: {=IF($V10="","",INDEX(PlanTasks[Task ID],$V10))} -> JA06 | B10: {=IF($V10="","",IF(INDEX(PlanTasks[Start week],$V10)="","",INDEX(PlanTasks[Start week],$V10)))} -> 1 | C10: {=IF($V10="","",IF(INDEX(PlanTasks[Task / deliverable],$V10)="","",INDEX(PlanTasks[Task / deliverable],$V10)))} -> OOP | D10: {=IF($V10="","",IF(INDEX(PlanTasks[Status],$V10)="","",INDEX(PlanTasks[Status],$V10)))} -> Not started | E10: {=IF($V10="","",IF(INDEX(PlanTasks[Priority],$V10)="","",INDEX(PlanTasks[Priority],$V10)))} -> P0 | F10: {=IF($V10="","",IF(INDEX(PlanTasks[Scope],$V10)="","",INDEX(PlanTasks[Scope],$V10)))} -> Core | G10: {=IF($V10="","",IF(INDEX(PlanTasks[Estimate (h)],$V10)="","",INDEX(PlanTasks[Estimate (h)],$V10)))} -> 0.75 | H10: {=IF($V10="","",IF(INDEX(PlanTasks[Actual (h)],$V10)="","",INDEX(PlanTasks[Actual (h)],$V10)))} -> 0 | I10: {=IF($V10="","",IF(INDEX(PlanTasks[Due date],$V10)="","",INDEX(PlanTasks[Due date],$V10)))} -> 46307 | J10: {=IF($V10="","",IF(INDEX(PlanTasks[Completion check],$V10)="","",INDEX(PlanTasks[Completion check],$V10)))} | K10: {=IF($V10="","",IF(INDEX(PlanTasks[Next action / blocker],$V10)="","",INDEX(PlanTasks[Next action / blocker],$V10)))} | L10: {=IF($V10="","",IF(INDEX(PlanTasks[Done when],$V10)="","",INDEX(PlanTasks[Done when],$V10)))} -> encapsulation, abstraction, inheritance, polymorphism, composition Explain each and when composition is preferable Apply principles without overengineering Encapsulation, composition, interfaces, SOLID trade-offs Model domains with classes/interfaces; composition, immutability, dependency boundaries | M10: {=IF($V10="","",IF(INDEX(PlanTasks[Exercise / interview prompt],$V10)="","",INDEX(PlanTasks[Exercise / interview prompt],$V10)))} -> model order/payment domain Interview: composition vs inheritance? Interview: Composition vs inheritance? Interview: Which SOLID principle is violated here? Refactor a service using composition | N10: {=IF($V10="","",IF(INDEX(PlanTasks[Prerequisite IDs],$V10)="","",INDEX(PlanTasks[Prerequisite IDs],$V10)))} -> G02 | O10: {=IF($V10="","",IF(INDEX(PlanTasks[Plan section],$V10)="","",INDEX(PlanTasks[Plan section],$V10)))} -> Java Core | P10: {=IF($V10="","",IF(INDEX(PlanTasks[Category],$V10)="","",INDEX(PlanTasks[Category],$V10)))} -> Java & Spring | Q10: {=IF($V10="","",IF(INDEX(PlanTasks[Evidence / result],$V10)="","",INDEX(PlanTasks[Evidence / result],$V10)))} | R10: {=IF($V10="","",IF(INDEX(PlanTasks[Completed on],$V10)="","",INDEX(PlanTasks[Completed on],$V10)))} | S10: {=IF($V10="","",IF(INDEX(PlanTasks[Review due],$V10)="","",INDEX(PlanTasks[Review due],$V10)))} | T10: {=IF($V10="","",IF(INDEX(PlanTasks[AI practice mode],$V10)="","",INDEX(PlanTasks[AI practice mode],$V10)))} -> AI-free first | U10: {=IF($V10="","",IF(INDEX(PlanTasks[Source IDs],$V10)="","",INDEX(PlanTasks[Source IDs],$V10)))} -> S001 S019 | V10: =IF(ROW()-8>$E$4,"",MATCH($C$4&"|"&(ROW()-8),PlanTasks[Category key],0)) -> 6
A11: {=IF($V11="","",INDEX(PlanTasks[Task ID],$V11))} -> JA07 | B11: {=IF($V11="","",IF(INDEX(PlanTasks[Start week],$V11)="","",INDEX(PlanTasks[Start week],$V11)))} -> 2 | C11: {=IF($V11="","",IF(INDEX(PlanTasks[Task / deliverable],$V11)="","",INDEX(PlanTasks[Task / deliverable],$V11)))} -> equals/hashCode/immutability | D11: {=IF($V11="","",IF(INDEX(PlanTasks[Status],$V11)="","",INDEX(PlanTasks[Status],$V11)))} -> Not started | E11: {=IF($V11="","",IF(INDEX(PlanTasks[Priority],$V11)="","",INDEX(PlanTasks[Priority],$V11)))} -> P0 | F11: {=IF($V11="","",IF(INDEX(PlanTasks[Scope],$V11)="","",INDEX(PlanTasks[Scope],$V11)))} -> Core | G11: {=IF($V11="","",IF(INDEX(PlanTasks[Estimate (h)],$V11)="","",INDEX(PlanTasks[Estimate (h)],$V11)))} -> 0.75 | H11: {=IF($V11="","",IF(INDEX(PlanTasks[Actual (h)],$V11)="","",INDEX(PlanTasks[Actual (h)],$V11)))} -> 0 | I11: {=IF($V11="","",IF(INDEX(PlanTasks[Due date],$V11)="","",INDEX(PlanTasks[Due date],$V11)))} -> 46307 | J11: {=IF($V11="","",IF(INDEX(PlanTasks[Completion check],$V11)="","",INDEX(PlanTasks[Completion check],$V11)))} | K11: {=IF($V11="","",IF(INDEX(PlanTasks[Next action / blocker],$V11)="","",INDEX(PlanTasks[Next action / blocker],$V11)))} | L11: {=IF($V11="","",IF(INDEX(PlanTasks[Done when],$V11)="","",INDEX(PlanTasks[Done when],$V11)))} -> identity vs equality, hash contracts, immutable value objects | M11: {=IF($V11="","",IF(INDEX(PlanTasks[Exercise / interview prompt],$V11)="","",INDEX(PlanTasks[Exercise / interview prompt],$V11)))} -> value object kata Interview: why can HashMap fail with bad hashCode? | N11: {=IF($V11="","",IF(INDEX(PlanTasks[Prerequisite IDs],$V11)="","",INDEX(PlanTasks[Prerequisite IDs],$V11)))} -> G02 | O11: {=IF($V11="","",IF(INDEX(PlanTasks[Plan section],$V11)="","",INDEX(PlanTasks[Plan section],$V11)))} -> Java Core | P11: {=IF($V11="","",IF(INDEX(PlanTasks[Category],$V11)="","",INDEX(PlanTasks[Category],$V11)))} -> Java & Spring | Q11: {=IF($V11="","",IF(INDEX(PlanTasks[Evidence / result],$V11)="","",INDEX(PlanTasks[Evidence / result],$V11)))} | R11: {=IF($V11="","",IF(INDEX(PlanTasks[Completed on],$V11)="","",INDEX(PlanTasks[Completed on],$V11)))} | S11: {=IF($V11="","",IF(INDEX(PlanTasks[Review due],$V11)="","",INDEX(PlanTasks[Review due],$V11)))} | T11: {=IF($V11="","",IF(INDEX(PlanTasks[AI practice mode],$V11)="","",INDEX(PlanTasks[AI practice mode],$V11)))} -> AI-free first | U11: {=IF($V11="","",IF(INDEX(PlanTasks[Source IDs],$V11)="","",INDEX(PlanTasks[Source IDs],$V11)))} -> S001 | V11: =IF(ROW()-8>$E$4,"",MATCH($C$4&"|"&(ROW()-8),PlanTasks[Category key],0)) -> 17
A12: {=IF($V12="","",INDEX(PlanTasks[Task ID],$V12))} -> JA08 | B12: {=IF($V12="","",IF(INDEX(PlanTasks[Start week],$V12)="","",INDEX(PlanTasks[Start week],$V12)))} -> 2 | C12: {=IF($V12="","",IF(INDEX(PlanTasks[Task / deliverable],$V12)="","",INDEX(PlanTasks[Task / deliverable],$V12)))} -> Collections | D12: {=IF($V12="","",IF(INDEX(PlanTasks[Status],$V12)="","",INDEX(PlanTasks[Status],$V12)))} -> Not started | E12: {=IF($V12="","",IF(INDEX(PlanTasks[Priority],$V12)="","",INDEX(PlanTasks[Priority],$V12)))} -> P0 | F12: {=IF($V12="","",IF(INDEX(PlanTasks[Scope],$V12)="","",INDEX(PlanTasks[Scope],$V12)))} -> Core | G12: {=IF($V12="","",IF(INDEX(PlanTasks[Estimate (h)],$V12)="","",INDEX(PlanTasks[Estimate (h)],$V12)))} -> 0.75 | H12: {=IF($V12="","",IF(INDEX(PlanTasks[Actual (h)],$V12)="","",INDEX(PlanTasks[Actual (h)],$V12)))} -> 0 | I12: {=IF($V12="","",IF(INDEX(PlanTasks[Due date],$V12)="","",INDEX(PlanTasks[Due date],$V12)))} -> 46307 | J12: {=IF($V12="","",IF(INDEX(PlanTasks[Completion check],$V12)="","",INDEX(PlanTasks[Completion check],$V12)))} | K12: {=IF($V12="","",IF(INDEX(PlanTasks[Next action / blocker],$V12)="","",INDEX(PlanTasks[Next action / blocker],$V12)))} | L12: {=IF($V12="","",IF(INDEX(PlanTasks[Done when],$V12)="","",INDEX(PlanTasks[Done when],$V12)))} -> List/Set/Map/Queue, implementations, complexity Choose List/Set/Map/Queue; generics bounds; equality/hashCode | M12: {=IF($V12="","",IF(INDEX(PlanTasks[Exercise / interview prompt],$V12)="","",INDEX(PlanTasks[Exercise / interview prompt],$V12)))} -> collection selection drills Interview: ArrayList vs LinkedList? HashMap internals high level? Implement domain collections exercises | N12: {=IF($V12="","",IF(INDEX(PlanTasks[Prerequisite IDs],$V12)="","",INDEX(PlanTasks[Prerequisite IDs],$V12)))} -> G02 | O12: {=IF($V12="","",IF(INDEX(PlanTasks[Plan section],$V12)="","",INDEX(PlanTasks[Plan section],$V12)))} -> Java Core | P12: {=IF($V12="","",IF(INDEX(PlanTasks[Category],$V12)="","",INDEX(PlanTasks[Category],$V12)))} -> Java & Spring | Q12: {=IF($V12="","",IF(INDEX(PlanTasks[Evidence / result],$V12)="","",INDEX(PlanTasks[Evidence / result],$V12)))} | R12: {=IF($V12="","",IF(INDEX(PlanTasks[Completed on],$V12)="","",INDEX(PlanTasks[Completed on],$V12)))} | S12: {=IF($V12="","",IF(INDEX(PlanTasks[Review due],$V12)="","",INDEX(PlanTasks[Review due],$V12)))} | T12: {=IF($V12="","",IF(INDEX(PlanTasks[AI practice mode],$V12)="","",INDEX(PlanTasks[AI practice mode],$V12)))} -> AI-free first | U12: {=IF($V12="","",IF(INDEX(PlanTasks[Source IDs],$V12)="","",INDEX(PlanTasks[Source IDs],$V12)))} -> S001 | V12: =IF(ROW()-8>$E$4,"",MATCH($C$4&"|"&(ROW()-8),PlanTasks[Category key],0)) -> 18
A13: {=IF($V13="","",INDEX(PlanTasks[Task ID],$V13))} -> JA09 | B13: {=IF($V13="","",IF(INDEX(PlanTasks[Start week],$V13)="","",INDEX(PlanTasks[Start week],$V13)))} -> 3 | C13: {=IF($V13="","",IF(INDEX(PlanTasks[Task / deliverable],$V13)="","",INDEX(PlanTasks[Task / deliverable],$V13)))} -> Generics | D13: {=IF($V13="","",IF(INDEX(PlanTasks[Status],$V13)="","",INDEX(PlanTasks[Status],$V13)))} -> Not started | E13: {=IF($V13="","",IF(INDEX(PlanTasks[Priority],$V13)="","",INDEX(PlanTasks[Priority],$V13)))} -> P1 | F13: {=IF($V13="","",IF(INDEX(PlanTasks[Scope],$V13)="","",INDEX(PlanTasks[Scope],$V13)))} -> Core | G13: {=IF($V13="","",IF(INDEX(PlanTasks[Estimate (h)],$V13)="","",INDEX(PlanTasks[Estimate (h)],$V13)))} -> 0.75 | H13: {=IF($V13="","",IF(INDEX(PlanTasks[Actual (h)],$V13)="","",INDEX(PlanTasks[Actual (h)],$V13)))} -> 0 | I13: {=IF($V13="","",IF(INDEX(PlanTasks[Due date],$V13)="","",INDEX(PlanTasks[Due date],$V13)))} -> 46314 | J13: {=IF($V13="","",IF(INDEX(PlanTasks[Completion check],$V13)="","",INDEX(PlanTasks[Completion check],$V13)))} | K13: {=IF($V13="","",IF(INDEX(PlanTasks[Next action / blocker],$V13)="","",INDEX(PlanTasks[Next action / blocker],$V13)))} | L13: {=IF($V13="","",IF(INDEX(PlanTasks[Done when],$V13)="","",INDEX(PlanTasks[Done when],$V13)))} -> type parameters, bounds, invariance, wildcards basics | M13: {=IF($V13="","",IF(INDEX(PlanTasks[Exercise / interview prompt],$V13)="","",INDEX(PlanTasks[Exercise / interview prompt],$V13)))} -> generic repository/filter exercise Interview: ? extends vs ? super? | N13: {=IF($V13="","",IF(INDEX(PlanTasks[Prerequisite IDs],$V13)="","",INDEX(PlanTasks[Prerequisite IDs],$V13)))} -> G02 | O13: {=IF($V13="","",IF(INDEX(PlanTasks[Plan section],$V13)="","",INDEX(PlanTasks[Plan section],$V13)))} -> Java Core | P13: {=IF($V13="","",IF(INDEX(PlanTasks[Category],$V13)="","",INDEX(PlanTasks[Category],$V13)))} -> Java & Spring | Q13: {=IF($V13="","",IF(INDEX(PlanTasks[Evidence / result],$V13)="","",INDEX(PlanTasks[Evidence / result],$V13)))} | R13: {=IF($V13="","",IF(INDEX(PlanTasks[Completed on],$V13)="","",INDEX(PlanTasks[Completed on],$V13)))} | S13: {=IF($V13="","",IF(INDEX(PlanTasks[Review due],$V13)="","",INDEX(PlanTasks[Review due],$V13)))} | T13: {=IF($V13="","",IF(INDEX(PlanTasks[AI practice mode],$V13)="","",INDEX(PlanTasks[AI practice mode],$V13)))} -> AI-free first | U13: {=IF($V13="","",IF(INDEX(PlanTasks[Source IDs],$V13)="","",INDEX(PlanTasks[Source IDs],$V13)))} -> S001 | V13: =IF(ROW()-8>$E$4,"",MATCH($C$4&"|"&(ROW()-8),PlanTasks[Category key],0)) -> 28
